Workbook

Sheet SUMMARY
C4: Results | D4: MVA | E4: BEL | F4: BoF | G4: d_BoF | H4: dur_L | L4: =BSCR!U4 -> SCR | O4: SCR_market | P4: =BSCR!E18 -> 2221.1875
C5: BASE | D5: =BASE!D2 -> 100000 | E5: =BASE!Q56 -> 94493.616 | F5: =BASE!Q57 -> 5506.3842 | G5: =$F$5-F5 -> 0 | H5: =BASE!Q59 -> 5.6130734 | L5: =BSCR!U5 -> Equity | M5: =BSCR!V5 -> 1790.2664 | O5: SCR_life | P5: =BSCR!E20 -> 1568.0585
C6: EQ STRESS 1 | D6: ='EQ STRESS 1'!D2 -> 68800 | E6: ='EQ STRESS 1'!Q56 -> 65083.882 | F6: ='EQ STRESS 1'!Q57 -> 3716.1178 | G6: =$F$5-F6 -> 1790.2664 | H6: ='EQ STRESS 1'!Q59 -> 5.6132956 | L6: =BSCR!U6 -> Property | M6: =BSCR!V6 -> 286.90166
C7: PROP STRESS | D7: ='PROPERTY STRESS'!$D$2 -> 95000 | E7: ='PROPERTY STRESS'!$Q$56 -> 89780.518 | F7: ='PROPERTY STRESS'!$Q$57 -> 5219.4825 | G7: =$F$5-$F$7 -> 286.90166 | H7: ='PROPERTY STRESS'!$Q$59 -> 5.6130992 | L7: =BSCR!U7 -> IR up | M7: =BSCR!V7 -> 0 | O7: BSCR | P7: =BSCR!K17 -> 3022.2438
C8: IR UP | D8: ='IR UP '!$D$2 -> 100000 | E8: ='IR UP '!$Q$56 -> 94477.93 | F8: ='IR UP '!$Q$57 -> 5522.0696 | G8: =$F$5-$F$8 -> -15.685468 | H8: ='IR UP '!$Q$59 -> 5.6125887 | L8: =BSCR!U8 -> IR down | M8: =BSCR!V8 -> 359.457
C9: IR DOWN | D9: ='IR DOWN '!$D$2 -> 100000 | E9: ='IR DOWN '!$Q$56 -> 94853.073 | F9: ='IR DOWN '!$Q$57 -> 5146.9271 | G9: =$F$5-$F$9 -> 359.457 | H9: ='IR DOWN '!$Q$59 -> 5.6400305 | L9: =BSCR!U9 -> Expense | M9: =BSCR!V9 -> 38.106405
C10: EXPENSE STRESS | D10: ='EXPENSE STRESS'!$D$2 -> 100000 | E10: ='EXPENSE STRESS'!$Q$56 -> 94531.722 | F10: ='EXPENSE STRESS'!$Q$57 -> 5468.2777 | G10: =$F$5-$F$10 -> 38.106405 | H10: ='EXPENSE STRESS'!$Q$59 -> 5.6138741 | L10: =BSCR!U10 -> Mortality | M10: =BSCR!V10 -> 29.30665 | O10: BASE CASE | P10: =BASE!P61 -> PVFP | Q10: =BASE!Q61 -> 3765.8683
C11: MORTALITY | D11: ='LIFE CAT'!$D$2 -> 100000 | E11: ='LIFE CAT'!$Q$56 -> 94498.608 | F11: ='LIFE CAT'!$Q$57 -> 5501.3923 | G11: =$F$5-$F$11 -> 4.991863 | H11: ='LIFE CAT'!$Q$59 -> 5.6058654 | L11: =BSCR!U11 -> Cat | M11: =BSCR!V11 -> 4.991863 | P11: =BASE!P62 -> LEAK | Q11: =BASE!Q62 -> 1740.5158
C12: LIFE CAT | D12: ='LIFE CAT'!$D$2 -> 100000 | E12: ='LIFE CAT'!$Q$56 -> 94498.608 | F12: ='LIFE CAT'!$Q$57 -> 5501.3923 | G12: =$F$5-$F$12 -> 4.991863 | H12: ='LIFE CAT'!$Q$59 -> 5.6058654 | L12: =BSCR!U12 -> Lapse up | M12: =BSCR!V12 -> 1130.4727 | P12: =BASE!P63 -> PVFP PROXY | Q12: =BASE!Q63 -> 4490.4587
C13: LAPSE UP | D13: ='LAPSE STRESS UP '!$D$2 -> 100000 | E13: ='LAPSE STRESS UP '!$Q$56 -> 95624.089 | F13: ='LAPSE STRESS UP '!$Q$57 -> 4375.9114 | G13: =$F$5-$F$13 -> 1130.4727 | H13: ='LAPSE STRESS UP '!$Q$59 -> 4.0158341 | L13: =BSCR!U13 -> Lapse down | M13: =BSCR!V13 -> 0
C14: LASPE DOWN | D14: ='LAPSE STRESS DOWN'!$D$2 -> 100000 | E14: ='LAPSE STRESS DOWN'!$Q$56 -> 92119.809 | F14: ='LAPSE STRESS DOWN'!$Q$57 -> 7880.1908 | G14: =$F$5-$F$14 -> -2373.8067 | H14: ='LAPSE STRESS DOWN'!$Q$59 -> 9.0321241 | L14: =BSCR!U14 -> Lapse mass | M14: =BSCR!V14 -> 1546.912
C15: LASPE MASS | D15: ='LAPSE MASS'!$D$2 -> 100000 | E15: ='LAPSE MASS'!$Q$56 -> 96040.528 | F15: ='LAPSE MASS'!$Q$57 -> 3959.4721 | G15: =$F$5-$F$15 -> 1546.912 | H15: ='LAPSE MASS'!$Q$59 -> 3.4028789

Sheet RATES
C1: RFR_SPPT_NO_VA | D1: SPOT_NO_VA_SHOCK_UP | E1: SPOT_NO_VA_SHOCK_DOWN | G1: DISCOUNTS | K1: FWD DISCOUNTS | O1: FWD RATES
C2: Euro | D2: Euro | E2: Euro | G2: BASE | H2: UP | I2: DOWN | K2: BASE | L2: UP | M2: DOWN | O2: BASE | P2: UP | Q2: DOWN
C3: EUR_31_03_2024_SWP_LLP_20_EXT_40_UFR_3.30 | D3: EUR_31_03_2024_SWP_LLP_20_EXT_40_UFR_3.30 | E3: EUR_31_03_2024_SWP_LLP_20_EXT_40_UFR_3.30 | G3: 1 | H3: 1 | I3: 1
B4: 1 | C4: 0.03514 | D4: 0.05974 | E4: 0.00879 | G4: =(1+C4)^(-$B4) -> 0.9660529 | H4: =(1+D4)^(-$B4) -> 0.94362768 | I4: =(1+E4)^(-$B4) -> 0.99128659 | K4: =G4/G3 -> 0.9660529 | L4: =H4/H3 -> 0.94362768 | M4: =I4/I3 -> 0.99128659 | O4: =-LN(K4) -> 0.034536683 | P4: =-LN(L4) -> 0.058023595 | Q4: =-LN(M4) -> 0.0087515929
B5: 2 | C5: 0.03035 | D5: 0.0516 | E5: 0.01062 | G5: =(1+C5)^(-$B5) -> 0.94195564 | H5: =(1+D5)^(-$B5) -> 0.9042715 | I5: =(1+E5)^(-$B5) -> 0.97909362 | K5: =G5/G4 -> 0.97505596 | L5: =H5/H4 -> 0.95829268 | M5: =I5/I4 -> 0.98769986 | O5: =-LN(K5) -> 0.025260417 | P5: =-LN(L5) -> 0.042602033 | Q5: =-LN(M5) -> 0.012376415
B6: 3 | C6: 0.02783 | D6: 0.04564 | E6: 0.01225 | G6: =(1+C6)^(-$B6) -> 0.92095017 | H6: =(1+D6)^(-$B6) -> 0.87468854 | I6: =(1+E6)^(-$B6) -> 0.96413232 | K6: =G6/G5 -> 0.97770015 | L6: =H6/H5 -> 0.9672853 | M6: =I6/I5 -> 0.98471923 | O6: =-LN(K6) -> 0.02255225 | P6: =-LN(L6) -> 0.033261787 | Q6: =-LN(M6) -> 0.01539872
B7: 4 | C7: 0.02637 | D7: 0.04193 | E7: 0.01319 | G7: =(1+C7)^(-$B7) -> 0.90112326 | H7: =(1+D7)^(-$B7) -> 0.84848824 | I7: =(1+E7)^(-$B7) -> 0.9489349 | K7: =G7/G6 -> 0.97847125 | L7: =H7/H6 -> 0.97004615 | M7: =I7/I6 -> 0.9842372 | O7: =-LN(K7) -> 0.021763871 | P7: =-LN(L7) -> 0.030411636 | Q7: =-LN(M7) -> 0.01588835
B8: 5 | C8: 0.02549 | D8: 0.03951 | E8: 0.01376 | G8: =(1+C8)^(-$B8) -> 0.88174469 | H8: =(1+D8)^(-$B8) -> 0.82386612 | I8: =(1+E8)^(-$B8) -> 0.93395133 | K8: =G8/G7 -> 0.97849509 | L8: =H8/H7 -> 0.97098118 | M8: =I8/I7 -> 0.98421011 | O8: =-LN(K8) -> 0.021739514 | P8: =-LN(L8) -> 0.029448191 | Q8: =-LN(M8) -> 0.015915876
B9: 6 | C9: 0.02502 | D9: 0.03803 | E9: 0.01451 | G9: =(1+C9)^(-$B9) -> 0.86219592 | H9: =(1+D9)^(-$B9) -> 0.79935661 | I9: =(1+E9)^(-$B9) -> 0.91719569 | K9: =G9/G8 -> 0.97782945 | L9: =H9/H8 -> 0.97025061 | M9: =I9/I8 -> 0.98205941 | O9: =-LN(K9) -> 0.022420012 | P9: =-LN(L9) -> 0.030200875 | Q9: =-LN(M9) -> 0.01810347
B10: 7 | C10: 0.02477 | D10: 0.03691 | E10: 0.01511 | G10: =(1+C10)^(-$B10) -> 0.84258782 | H10: =(1+D10)^(-$B10) -> 0.77591216 | I10: =(1+E10)^(-$B10) -> 0.90034355 | K10: =G10/G9 -> 0.97725796 | L10: =H10/H9 -> 0.97067086 | M10: =I10/I9 -> 0.98162645 | O10: =-LN(K10) -> 0.023004633 | P10: =-LN(L10) -> 0.02976784 | Q10: =-LN(M10) -> 0.018544443
B11: 8 | C11: 0.02466 | D11: 0.03625 | E11: 0.01578 | G11: =(1+C11)^(-$B11) -> 0.82292781 | H11: =(1+D11)^(-$B11) -> 0.75211396 | I11: =(1+E11)^(-$B11) -> 0.88227249 | K11: =G11/G10 -> 0.9766671 | L11: =H11/H10 -> 0.96932874 | M11: =I11/I10 -> 0.97992871 | O11: =-LN(K11) -> 0.023609422 | P11: =-LN(L11) -> 0.031151463 | Q11: =-LN(M11) -> 0.020275455
B12: 9 | C12: 0.02464 | D12: 0.03548 | E12: 0.01651 | G12: =(1+C12)^(-$B12) -> 0.8032639 | H12: =(1+D12)^(-$B12) -> 0.73067553 | I12: =(1+E12)^(-$B12) -> 0.86296881 | K12: =G12/G11 -> 0.97610494 | L12: =H12/H11 -> 0.97149577 | M12: =I12/I11 -> 0.9781205 | O12: =-LN(K12) -> 0.024185181 | P12: =-LN(L12) -> 0.028918366 | Q12: =-LN(M12) -> 0.022122403
B13: 10 | C13: 0.0247 | D13: 0.03507 | E13: 0.01704 | G13: =(1+C13)^(-$B13) -> 0.78348852 | H13: =(1+D13)^(-$B13) -> 0.70843953 | I13: =(1+E13)^(-$B13) -> 0.8445389 | K13: =G13/G12 -> 0.97538122 | L13: =H13/H12 -> 0.96956788 | M13: =I13/I12 -> 0.9786436 | O13: =-LN(K13) -> 0.024926886 | P13: =-LN(L13) -> 0.030904787 | Q13: =-LN(M13) -> 0.021587751
B14: 11 | C14: 0.02487 | D14: 0.03487 | E14: 0.01741 | G14: =(1+C14)^(-$B14) -> 0.76320888 | H14: =(1+D14)^(-$B14) -> 0.68589278 | I14: =(1+E14)^(-$B14) -> 0.82707326 | K14: =G14/G13 -> 0.97411622 | L14: =H14/H13 -> 0.96817406 | M14: =I14/I13 -> 0.97931931 | O14: =-LN(K14) -> 0.02622466 | P14: =-LN(L14) -> 0.032343392 | Q14: =-LN(M14) -> 0.020897529
B15: 12 | C15: 0.02487 | D15: 0.03487 | E15: 0.01766 | G15: =(1+C15)^(-$B15) -> 0.74468847 | H15: =(1+D15)^(-$B15) -> 0.66278158 | I15: =(1+E15)^(-$B15) -> 0.81052711 | K15: =G15/G14 -> 0.97573351 | L15: =H15/H14 -> 0.96630495 | M15: =I15/I14 -> 0.97999434 | O15: =-LN(K15) -> 0.024565775 | P15: =-LN(L15) -> 0.034275815 | Q15: =-LN(M15) -> 0.020208484
... B153: 150 | C153: 0.03121 | D153: 0.04121 | E153: 0.02497 | G153: =(1+C153)^(-$B153) -> 0.0099525099 | H153: =(1+D153)^(-$B153) -> 0.0023401862 | I153: =(1+E153)^(-$B153) -> 0.024735852 | K153: =G153/G152 -> 0.96833441 | L153: =H153/H152 -> 0.95904764 | M153: =I153/I152 -> 0.97422105 | O153: =-LN(K153) -> 0.032177782 | P153: =-LN(L153) -> 0.041814533 | Q153: =-LN(M153) -> 0.026117052

Sheet LIFE TABLE MALE FEMALE
A1: Tavole di mortalità della popolazione residente Italia - Maschi e femmine - Anno 2022
A2: Età x | B2: Sopravviventi lx | C2: Decessi dx | D2: Probabilità di morte (per mille) qx | E2: Anni vissuti Lx | F2: Probabilità prospettive di sopravvivenza Px | G2: Speranza di vita ex
A3: 0 | B3: 100000 | C3: 235 | D3: 2.34568 | E3: 99779 | F3: 0.999774 | G3: 82.64
A4: 1 | B4: 99765 | C4: 17 | D4: 0.17468 | E4: 99757 | F4: 0.9998499 | G4: 81.833
A5: 2 | B5: 99748 | C5: 13 | D5: 0.12547 | E5: 99742 | F5: 0.9998901 | G5: 80.847
A6: 3 | B6: 99735 | C6: 9 | D6: 0.09435 | E6: 99731 | F6: 0.9999149 | G6: 79.857
A7: 4 | B7: 99726 | C7: 8 | D7: 0.0759 | E7: 99722 | F7: 0.9999257 | G7: 78.865
A8: 5 | B8: 99719 | C8: 7 | D8: 0.07265 | E8: 99715 | F8: 0.9999279 | G8: 77.87
A9: 6 | B9: 99711 | C9: 7 | D9: 0.07149 | E9: 99708 | F9: 0.9999291 | G9: 76.876
A10: 7 | B10: 99704 | C10: 7 | D10: 0.0704 | E10: 99701 | F10: 0.999933 | G10: 75.882
A11: 8 | B11: 99697 | C11: 6 | D11: 0.06364 | E11: 99694 | F11: 0.9999357 | G11: 74.887
A12: 9 | B12: 99691 | C12: 6 | D12: 0.06498 | E12: 99688 | F12: 0.999934 | G12: 73.892
A13: 10 | B13: 99684 | C13: 7 | D13: 0.06693 | E13: 99681 | F13: 0.9999318 | G13: 72.896
A14: 11 | B14: 99678 | C14: 7 | D14: 0.06941 | E14: 99674 | F14: 0.9999278 | G14: 71.901
... A122: 119 | B122: 0 | C122: 0 | D122: 887.47597 | E122: 0 | F122: 0.1114 | G122: 0.625

Sheet LIFE TABLE MALE
A1: Tavole di mortalità della popolazione residente Italia - Maschi - Anno 2022
A2: Età x | B2: Sopravviventi lx | C2: Decessi dx | D2: Probabilità di morte (per mille) qx | E2: Anni vissuti Lx | F2: Probabilità prospettive di sopravvivenza Px | G2: Speranza di vita ex
A3: 0 | B3: 100000 | C3: 249 | D3: 2.49291 | E3: 99765 | F3: 0.9997548 | G3: 80.59
A4: 1 | B4: 99751 | C4: 20 | D4: 0.19564 | E4: 99741 | F4: 0.9998316 | G4: 79.79
A5: 2 | B5: 99731 | C5: 14 | D5: 0.14114 | E5: 99724 | F5: 0.999876 | G5: 78.805
A6: 3 | B6: 99717 | C6: 11 | D6: 0.10689 | E6: 99712 | F6: 0.9999034 | G6: 77.816
A7: 4 | B7: 99706 | C7: 9 | D7: 0.08633 | E7: 99702 | F7: 0.999914 | G7: 76.825
A8: 5 | B8: 99698 | C8: 9 | D8: 0.08565 | E8: 99694 | F8: 0.9999161 | G8: 75.831
A9: 6 | B9: 99689 | C9: 8 | D9: 0.08209 | E9: 99685 | F9: 0.9999203 | G9: 74.838
A10: 7 | B10: 99681 | C10: 8 | D10: 0.07729 | E10: 99677 | F10: 0.9999288 | G10: 73.844
A11: 8 | B11: 99673 | C11: 6 | D11: 0.0651 | E11: 99670 | F11: 0.9999347 | G11: 72.849
A12: 9 | B12: 99667 | C12: 7 | D12: 0.06556 | E12: 99664 | F12: 0.9999329 | G12: 71.854
A13: 10 | B13: 99660 | C13: 7 | D13: 0.0686 | E13: 99657 | F13: 0.999929 | G13: 70.859
A14: 11 | B14: 99654 | C14: 7 | D14: 0.07336 | E14: 99650 | F14: 0.9999226 | G14: 69.864
... A122: 119 | B122: 0 | C122: 0 | D122: 926.04048 | E122: 0 | F122: 0.0734327 | G122: 0.579

Sheet DATA
A1: DATA | D1: STRESS
A2: F0 | B2: 100000 | D2: Equity stress type 1 | E2: 0.39
A3: C0 | B3: 100000 | D3: Equity stress type 2 | E3: 0.49
A4: Sigma_Eq | B4: 0.2 | D4: Property stress | E4: 0.25
A5: Sigma_Pr | B5: 0.1 | D5: Lapse up | E5: 0.225
A6: Reg_Ded | B6: 0.022 | D6: Lapse down | E6: 0.075
A7: Lapse Rate | B7: 0.15
A8: Expenses / per year | B8: 50
A9: Inflation (flat ann rate) | B9: 0.02
A10: T (years) | B10: 50
A11: x | B11: 60
A12: Commissions | B12: 0.014

Sheet BASE
B1: EQUITY | C1: PROPERTY | D1: ASSET | E1: SURVIVAL PROB | F1: non LAPSE PROB | G1: C lapse | H1: C death | I1: LIAB LAPSE | J1: LIAB DEATH | K1: LIAB SURVIVE | L1: EXPENSES | M1: EQ COMMISSIONS | N1: PR COMMISSIONS | O1: TOT COMMISSIONS | P1: COMMISSIONS LIAB | Q1: DISCOUNTS | R1: TOT LIAB | S1: TOT LIAB DISC | T1: PROFIT PR | U1: PROFIT EQ | V1: TOT PROFIT | W1: PROFIT LIAB | X1: PROFIT LIAB DISCOUNTED
A2: 0 | B2: =DATA!B2*0.8 -> 80000 | C2: =DATA!B2*0.2 -> 20000 | D2: =B2+C2 -> 100000 | E2: =1 -> 1 | F2: =1 -> 1 | G2: =D2-20 -> 99980 | H2: =MAX(D2,DATA!$B$3) -> 100000 | M2: =B2 -> 80000 | N2: =C2 -> 20000 | Q2: =RATES!G3 -> 1
A3: 1 | B3: =B2*EXP(RATES!O4)*(1-DATA!$B$6) -> 80989.354 | C3: =C2*EXP(RATES!O4)*(1-DATA!$B$6) -> 20247.338 | D3: =B3+C3 -> 101236.69 | E3: =E2*(1-'LIFE TABLE MALE'!D63/1000) -> 0.99353213 | F3: =F2*(1-0.15) -> 0.85 | G3: =D3-20 -> 101216.69 | H3: =MAX(D3,DATA!$B$3) -> 101236.69 | I3: =G3*DATA!$B$7*F2*E3 -> 15084.305 | J3: =H3*'LIFE TABLE MALE'!D63/1000*F2*E2 -> 654.78576 | K3: =0 -> 0 | L3: =DATA!$B$8*((1+DATA!$B$9)^A2)*F3*E3 -> 42.225116 | M3: =B2*EXP(RATES!O4)*(DATA!$B$12) -> 1159.3568 | N3: =C2*EXP(RATES!O4)*(DATA!$B$12) -> 289.8392 | O3: =M3+N3 -> 1449.196 | P3: =O3*E3*F3 -> 1223.8494 | Q3: =RATES!G4 -> 0.9660529 | R3: =P3+L3+K3+J3+I3 -> 17005.166 | S3: =R3*Q3 -> 16427.89 | T3: =C2*EXP(RATES!O4)*(DATA!$B$6-DATA!$B$12) -> 165.6224 | U3: =B2*EXP(RATES!O4)*(DATA!$B$6-DATA!$B$12) -> 662.4896 | V3: =T3+U3 -> 828.112 | W3: =V3*E3*F3 -> 699.3425 | X3: =W3*BASE!Q3 -> 675.60185
A4: 2 | B4: =B3*EXP(RATES!O5)*(1-DATA!$B$6) -> 81233.889 | C4: =C3*EXP(RATES!O5)*(1-DATA!$B$6) -> 20308.472 | D4: =B4+C4 -> 101542.36 | E4: =E3*(1-'LIFE TABLE MALE'!D64/1000) -> 0.98647779 | F4: =F3*(1-0.15) -> 0.7225 | G4: =D4-20 -> 101522.36 | H4: =MAX(D4,DATA!$B$3) -> 101542.36 | I4: =G4*DATA!$B$7*F3*E4 -> 12769.068 | J4: =H4*'LIFE TABLE MALE'!D64/1000*F3*E3 -> 608.86689 | K4: =0 -> 0 | L4: =DATA!$B$8*((1+DATA!$B$9)^A3)*F4*E4 -> 36.34924 | M4: =B3*EXP(RATES!O5)*(DATA!$B$12) -> 1162.8573 | N4: =C3*EXP(RATES!O5)*(DATA!$B$12) -> 290.71433 | O4: =M4+N4 -> 1453.5716 | P4: =O4*E4*F4 -> 1036.0044 | Q4: =RATES!G5 -> 0.94195564 | R4: =P4+L4+K4+J4+I4 -> 14450.289 | S4: =R4*Q4 -> 13611.531 | T4: =C3*EXP(RATES!O5)*(DATA!$B$6-DATA!$B$12) -> 166.12247 | U4: =B3*EXP(RATES!O5)*(DATA!$B$6-DATA!$B$12) -> 664.48989 | V4: =T4+U4 -> 830.61237 | W4: =V4*E4*F4 -> 592.00252 | X4: =W4*BASE!Q4 -> 557.64011
A5: 3 | B5: =B4*EXP(RATES!O6)*(1-DATA!$B$6) -> 81258.803 | C5: =C4*EXP(RATES!O6)*(1-DATA!$B$6) -> 20314.701 | D5: =B5+C5 -> 101573.5 | E5: =E4*(1-'LIFE TABLE MALE'!D65/1000) -> 0.97876837 | F5: =F4*(1-0.15) -> 0.614125 | G5: =D5-20 -> 101553.5 | H5: =MAX(D5,DATA!$B$3) -> 101573.5 | I5: =G5*DATA!$B$7*F4*E5 -> 10772.189 | J5: =H5*'LIFE TABLE MALE'!D65/1000*F4*E4 -> 565.77029 | K5: =0 -> 0 | L5: =DATA!$B$8*((1+DATA!$B$9)^A4)*F5*E5 -> 31.2685 | M5: =B4*EXP(RATES!O6)*(DATA!$B$12) -> 1163.2139 | N5: =C4*EXP(RATES!O6)*(DATA!$B$12) -> 290.80349 | O5: =M5+N5 -> 1454.0174 | P5: =O5*E5*F5 -> 873.98971 | Q5: =RATES!G6 -> 0.92095017 | R5: =P5+L5+K5+J5+I5 -> 12243.217 | S5: =R5*Q5 -> 11275.393 | T5: =C4*EXP(RATES!O6)*(DATA!$B$6-DATA!$B$12) -> 166.17342 | U5: =B4*EXP(RATES!O6)*(DATA!$B$6-DATA!$B$12) -> 664.69368 | V5: =T5+U5 -> 830.86711 | W5: =V5*E5*F5 -> 499.42269 | X5: =W5*BASE!Q5 -> 459.94341
A6: 4 | B6: =B5*EXP(RATES!O7)*(1-DATA!$B$6) -> 81219.667 | C6: =C5*EXP(RATES!O7)*(1-DATA!$B$6) -> 20304.917 | D6: =B6+C6 -> 101524.58 | E6: =E5*(1-'LIFE TABLE MALE'!D66/1000) -> 0.97028747 | F6: =F5*(1-0.15) -> 0.52200625 | G6: =D6-20 -> 101504.58 | H6: =MAX(D6,DATA!$B$3) -> 101524.58 | I6: =G6*DATA!$B$7*F5*E6 -> 9072.6491 | J6: =H6*'LIFE TABLE MALE'!D66/1000*F5*E5 -> 528.77385 | K6: =0 -> 0 | L6: =DATA!$B$8*((1+DATA!$B$9)^A5)*F6*E6 -> 26.874887 | M6: =B5*EXP(RATES!O7)*(DATA!$B$12) -> 1162.6537 | N6: =C5*EXP(RATES!O7)*(DATA!$B$12) -> 290.66343 | O6: =M6+N6 -> 1453.3171 | P6: =O6*E6*F6 -> 736.0995 | Q6: =RATES!G7 -> 0.90112326 | R6: =P6+L6+K6+J6+I6 -> 10364.397 | S6: =R6*Q6 -> 9339.5996 | T6: =C5*EXP(RATES!O7)*(DATA!$B$6-DATA!$B$12) -> 166.09339 | U6: =B5*EXP(RATES!O7)*(DATA!$B$6-DATA!$B$12) -> 664.37355 | V6: =T6+U6 -> 830.46694 | W6: =V6*E6*F6 -> 420.62829 | X6: =W6*BASE!Q6 -> 379.03794
A7: 5 | B7: =B6*EXP(RATES!O8)*(1-DATA!$B$6) -> 81178.572 | C7: =C6*EXP(RATES!O8)*(1-DATA!$B$6) -> 20294.643 | D7: =B7+C7 -> 101473.22 | E7: =E6*(1-'LIFE TABLE MALE'!D67/1000) -> 0.96092158 | F7: =F6*(1-0.15) -> 0.44370531 | G7: =D7-20 -> 101453.22 | H7: =MAX(D7,DATA!$B$3) -> 101473.22 | I7: =G7*DATA!$B$7*F6*E7 -> 7633.4475 | J7: =H7*'LIFE TABLE MALE'!D67/1000*F6*E6 -> 496.10815 | K7: =0 -> 0 | L7: =DATA!$B$8*((1+DATA!$B$9)^A6)*F7*E7 -> 23.075614 | M7: =B6*EXP(RATES!O8)*(DATA!$B$12) -> 1162.0655 | N7: =C6*EXP(RATES!O8)*(DATA!$B$12) -> 290.51636 | O7: =M7+N7 -> 1452.5818 | P7: =O7*E7*F7 -> 619.33151 | Q7: =RATES!G8 -> 0.88174469 | R7: =P7+L7+K7+J7+I7 -> 8771.9628 | S7: =R7*Q7 -> 7734.6316 | T7: =C6*EXP(RATES!O8)*(DATA!$B$6-DATA!$B$12) -> 166.00935 | U7: =B6*EXP(RATES!O8)*(DATA!$B$6-DATA!$B$12) -> 664.0374 | V7: =T7+U7 -> 830.04675 | W7: =V7*E7*F7 -> 353.90372 | X7: =W7*BASE!Q7 -> 312.05273
A8: 6 | B8: =B7*EXP(RATES!O9)*(1-DATA!$B$6) -> 81192.731 | C8: =C7*EXP(RATES!O9)*(1-DATA!$B$6) -> 20298.183 | D8: =B8+C8 -> 101490.91 | E8: =E7*(1-'LIFE TABLE MALE'!D68/1000) -> 0.95054817 | F8: =F7*(1-0.15) -> 0.37714952 | G8: =D8-20 -> 101470.91 | H8: =MAX(D8,DATA!$B$3) -> 101490.91 | I8: =G8*DATA!$B$7*F7*E8 -> 6419.5057 | J8: =H8*'LIFE TABLE MALE'!D68/1000*F7*E7 -> 467.1359 | K8: =0 -> 0 | L8: =DATA!$B$8*((1+DATA!$B$9)^A7)*F8*E8 -> 19.790581 | M8: =B7*EXP(RATES!O9)*(DATA!$B$12) -> 1162.2681 | N8: =C7*EXP(RATES!O9)*(DATA!$B$12) -> 290.56703 | O8: =M8+N8 -> 1452.8352 | P8: =O8*E8*F8 -> 520.83964 | Q8: =RATES!G9 -> 0.86219592 | R8: =P8+L8+K8+J8+I8 -> 7427.2718 | S8: =R8*Q8 -> 6403.7635 | T8: =C7*EXP(RATES!O9)*(DATA!$B$6-DATA!$B$12) -> 166.03831 | U8: =B7*EXP(RATES!O9)*(DATA!$B$6-DATA!$B$12) -> 664.15322 | V8: =T8+U8 -> 830.19153 | W8: =V8*E8*F8 -> 297.62265 | X8: =W8*BASE!Q8 -> 256.60904
A9: 7 | B9: =B8*EXP(RATES!O10)*(1-DATA!$B$6) -> 81254.382 | C9: =C8*EXP(RATES!O10)*(1-DATA!$B$6) -> 20313.596 | D9: =B9+C9 -> 101567.98 | E9: =E8*(1-'LIFE TABLE MALE'!D69/1000) -> 0.93939989 | F9: =F8*(1-0.15) -> 0.32057709 | G9: =D9-20 -> 101547.98 | H9: =MAX(D9,DATA!$B$3) -> 101567.98 | I9: =G9*DATA!$B$7*F8*E9 -> 5396.6791 | J9: =H9*'LIFE TABLE MALE'!D69/1000*F8*E8 -> 427.04936 | K9: =0 -> 0 | L9: =DATA!$B$8*((1+DATA!$B$9)^A8)*F9*E9 -> 16.957195 | M9: =B8*EXP(RATES!O10)*(DATA!$B$12) -> 1163.1507 | N9: =C8*EXP(RATES!O10)*(DATA!$B$12) -> 290.78767 | O9: =M9+N9 -> 1453.9383 | P9: =O9*E9*F9 -> 437.85365 | Q9: =RATES!G10 -> 0.84258782 | R9: =P9+L9+K9+J9+I9 -> 6278.5393 | S9: =R9*Q9 -> 5290.2208 | T9: =C8*EXP(RATES!O10)*(DATA!$B$6-DATA!$B$12) -> 166.16438 | U9: =B8*EXP(RATES!O10)*(DATA!$B$6-DATA!$B$12) -> 664.65752 | V9: =T9+U9 -> 830.8219 | W9: =V9*E9*F9 -> 250.20208 | X9: =W9*BASE!Q9 -> 210.81723
A10: 8 | B10: =B9*EXP(RATES!O11)*(1-DATA!$B$6) -> 81365.273 | C10: =C9*EXP(RATES!O11)*(1-DATA!$B$6) -> 20341.318 | D10: =B10+C10 -> 101706.59 | E10: =E9*(1-'LIFE TABLE MALE'!D70/1000) -> 0.92737751 | F10: =F9*(1-0.15) -> 0.27249053 | G10: =D10-20 -> 101686.59 | H10: =MAX(D10,DATA!$B$3) -> 101706.59 | I10: =G10*DATA!$B$7*F9*E10 -> 4534.6523 | J10: =H10*'LIFE TABLE MALE'!D70/1000*F9*E9 -> 391.98744 | K10: =0 -> 0 | L10: =DATA!$B$8*((1+DATA!$B$9)^A9)*F10*E10 -> 14.513734 | M10: =B9*EXP(RATES!O11)*(DATA!$B$12) -> 1164.7381 | N10: =C9*EXP(RATES!O11)*(DATA!$B$12) -> 291.18452 | O10: =M10+N10 -> 1455.9226 | P10: =O10*E10*F10 -> 367.91394 | Q10: =RATES!G11 -> 0.82292781 | R10: =P10+L10+K10+J10+I10 -> 5309.0674 | S10: =R10*Q10 -> 4368.9792 | T10: =C9*EXP(RATES!O11)*(DATA!$B$6-DATA!$B$12) -> 166.39115 | U10: =B9*EXP(RATES!O11)*(DATA!$B$6-DATA!$B$12) -> 665.56461 | V10: =T10+U10 -> 831.95576 | W10: =V10*E10*F10 -> 210.23654 | X10: =W10*BASE!Q10 -> 173.00949
A11: 9 | B11: =B10*EXP(RATES!O12)*(1-DATA!$B$6) -> 81523.24 | C11: =C10*EXP(RATES!O12)*(1-DATA!$B$6) -> 20380.81 | D11: =B11+C11 -> 101904.05 | E11: =E10*(1-'LIFE TABLE MALE'!D71/1000) -> 0.91441742 | F11: =F10*(1-0.15) -> 0.23161695 | G11: =D11-20 -> 101884.05 | H11: =MAX(D11,DATA!$B$3) -> 101904.05 | I11: =G11*DATA!$B$7*F10*E11 -> 3807.9686 | J11: =H11*'LIFE TABLE MALE'!D71/1000*F10*E10 -> 359.87437 | K11: =0 -> 0 | L11: =DATA!$B$8*((1+DATA!$B$9)^A10)*F11*E11 -> 12.407555 | M11: =B10*EXP(RATES!O12)*(DATA!$B$12) -> 1166.9993 | N11: =C10*EXP(RATES!O12)*(DATA!$B$12) -> 291.74984 | O11: =M11+N11 -> 1458.7492 | P11: =O11*E11*F11 -> 308.95516 | Q11: =RATES!G12 -> 0.8032639 | R11: =P11+L11+K11+J11+I11 -> 4489.2057 | S11: =R11*Q11 -> 3606.0168 | T11: =C10*EXP(RATES!O12)*(DATA!$B$6-DATA!$B$12) -> 166.71419 | U11: =B10*EXP(RATES!O12)*(DATA!$B$6-DATA!$B$12) -> 666.85677 | V11: =T11+U11 -> 833.57096 | W11: =V11*E11*F11 -> 176.5458 | X11: =W11*BASE!Q11 -> 141.81287
A12: 10 | B12: =B11*EXP(RATES!O13)*(1-DATA!$B$6) -> 81742.12 | C12: =C11*EXP(RATES!O13)*(1-DATA!$B$6) -> 20435.53 | D12: =B12+C12 -> 102177.65 | E12: =E11*(1-'LIFE TABLE MALE'!D72/1000) -> 0.9000976 | F12: =F11*(1-0.15) -> 0.1968744 | G12: =D12-20 -> 102157.65 | H12: =MAX(D12,DATA!$B$3) -> 102177.65 | I12: =G12*DATA!$B$7*F11*E12 -> 3194.6412 | J12: =H12*'LIFE TABLE MALE'!D72/1000*F11*E11 -> 338.894 | K12: =0 -> 0 | L12: =DATA!$B$8*((1+DATA!$B$9)^A11)*F12*E12 -> 10.588889 | M12: =B11*EXP(RATES!O13)*(DATA!$B$12) -> 1170.1326 | N12: =C11*EXP(RATES!O13)*(DATA!$B$12) -> 292.53315 | O12: =M12+N12 -> 1462.6657 | P12: =O12*E12*F12 -> 259.19341 | Q12: =RATES!G13 -> 0.78348852 | R12: =P12+L12+K12+J12+I12 -> 3803.3175 | S12: =R12*Q12 -> 2979.8556 | T12: =C11*EXP(RATES!O13)*(DATA!$B$6-DATA!$B$12) -> 167.1618 | U12: =B11*EXP(RATES!O13)*(DATA!$B$6-DATA!$B$12) -> 668.6472 | V12: =T12+U12 -> 835.809 | W12: =V12*E12*F12 -> 148.11052 | X12: =W12*BASE!Q12 -> 116.04289
A13: 11 | B13: =B12*EXP(RATES!O14)*(1-DATA!$B$6) -> 82068.024 | C13: =C12*EXP(RATES!O14)*(1-DATA!$B$6) -> 20517.006 | D13: =B13+C13 -> 102585.03 | E13: =E12*(1-'LIFE TABLE MALE'!D73/1000) -> 0.88436967 | F13: =F12*(1-0.15) -> 0.16734324 | G13: =D13-20 -> 102565.03 | H13: =MAX(D13,DATA!$B$3) -> 102585.03 | I13: =G13*DATA!$B$7*F12*E13 -> 2678.6358 | J13: =H13*'LIFE TABLE MALE'!D73/1000*F12*E12 -> 317.64699 | K13: =0 -> 0 | L13: =DATA!$B$8*((1+DATA!$B$9)^A12)*F13*E13 -> 9.0201497 | M13: =B12*EXP(RATES!O14)*(DATA!$B$12) -> 1174.7979 | N13: =C12*EXP(RATES!O14)*(DATA!$B$12) -> 293.69947 | O13: =M13+N13 -> 1468.4974 | P13: =O13*E13*F13 -> 217.32775 | Q13: =RATES!G14 -> 0.76320888 | R13: =P13+L13+K13+J13+I13 -> 3222.6307 | S13: =R13*Q13 -> 2459.5403 | T13: =C12*EXP(RATES!O14)*(DATA!$B$6-DATA!$B$12) -> 167.82827 | U13: =B12*EXP(RATES!O14)*(DATA!$B$6-DATA!$B$12) -> 671.31308 | V13: =T13+U13 -> 839.14135 | W13: =V13*E13*F13 -> 124.18729 | X13: =W13*BASE!Q13 -> 94.780841
A14: 12 | B14: =B13*EXP(RATES!O15)*(1-DATA!$B$6) -> 82258.657 | C14: =C13*EXP(RATES!O15)*(1-DATA!$B$6) -> 20564.664 | D14: =B14+C14 -> 102823.32 | E14: =E13*(1-'LIFE TABLE MALE'!D74/1000) -> 0.86691444 | F14: =F13*(1-0.15) -> 0.14224176 | G14: =D14-20 -> 102803.32 | H14: =MAX(D14,DATA!$B$3) -> 102823.32 | I14: =G14*DATA!$B$7*F13*E14 -> 2237.0867 | J14: =H14*'LIFE TABLE MALE'!D74/1000*F13*E13 -> 300.34842 | K14: =0 -> 0 | L14: =DATA!$B$8*((1+DATA!$B$9)^A13)*F14*E14 -> 7.6661134 | M14: =B13*EXP(RATES!O15)*(DATA!$B$12) -> 1177.5268 | N14: =C13*EXP(RATES!O15)*(DATA!$B$12) -> 294.3817 | O14: =M14+N14 -> 1471.9085 | P14: =O14*E14*F14 -> 181.50314 | Q14: =RATES!G15 -> 0.74468847 | R14: =P14+L14+K14+J14+I14 -> 2726.6044 | S14: =R14*Q14 -> 2030.4709 | T14: =C13*EXP(RATES!O15)*(DATA!$B$6-DATA!$B$12) -> 168.21811 | U14: =B13*EXP(RATES!O15)*(DATA!$B$6-DATA!$B$12) -> 672.87245 | V14: =T14+U14 -> 841.09056 | W14: =V14*E14*F14 -> 103.71608 | X14: =W14*BASE!Q14 -> 77.236171
... A51: 49 | B51: =B50*EXP(RATES!O52)*(1-DATA!$B$6) -> 102111.48 | C51: =C50*EXP(RATES!O52)*(1-DATA!$B$6) -> 25527.869 | D51: =B51+C51 -> 127639.35 | E51: =E50*(1-'LIFE TABLE MALE'!D111/1000) -> 2.6221013e-06 | F51: =F50*(1-0.15) -> 0.00034795843 | G51: =D51-20 -> 127619.35 | H51: =MAX(D51,DATA!$B$3) -> 127639.35 | I51: =G51*DATA!$B$7*F50*E51 -> 2.0547816e-05 | J51: =H51*'LIFE TABLE MALE'!D111/1000*F50*E50 -> 0.00033735942 | K51: =0 -> 0 | L51: =DATA!$B$8*((1+DATA!$B$9)^A50)*F51*E51 -> 1.1801985e-07 | M51: =B50*EXP(RATES!O52)*(DATA!$B$12) -> 1461.7185 | N51: =C50*EXP(RATES!O52)*(DATA!$B$12) -> 365.42962 | O51: =M51+N51 -> 1827.1481 | P51: =O51*E51*F51 -> 1.6670575e-06 | Q51: =RATES!G52 -> 0.26340215 | R51: =P51+L51+K51+J51+I51 -> 0.00035969231 | S51: =R51*Q51 -> 9.4743728e-05 | T51: =C50*EXP(RATES!O52)*(DATA!$B$6-DATA!$B$12) -> 208.81693 | U51: =B50*EXP(RATES!O52)*(DATA!$B$6-DATA!$B$12) -> 835.2677 | V51: =T51+U51 -> 1044.0846 | W51: =V51*E51*F51 -> 9.5260428e-07 | X51: =W51*BASE!Q51 -> 2.5091802e-07
A52: 50 | B52: =B51*EXP(RATES!O53)*(1-DATA!$B$6) -> 103172 | C52: =C51*EXP(RATES!O53)*(1-DATA!$B$6) -> 25793 | D52: =B52+C52 -> 128965 | E52: =E51*(1-'LIFE TABLE MALE'!D112/1000) -> 6.7948871e-07 | F52: =F51*(1-0.15) -> 0.00029576466 | G52: =D52-20 -> 128945 | H52: =MAX(D52,DATA!$B$3) -> 128965 | I52: =G52*DATA!$B$7*F51*E52 -> 4.5730439e-06 | J52: =H52*'LIFE TABLE MALE'!D112/1000*F51*E51 -> 8.7173688e-05 | K52: =E52*D52*F52 -> 2.5917935e-05 | L52: =DATA!$B$8*((1+DATA!$B$9)^A51)*F52*E52 -> 2.6515935e-08 | M52: =B51*EXP(RATES!O53)*(DATA!$B$12) -> 1476.8998 | N52: =C51*EXP(RATES!O53)*(DATA!$B$12) -> 369.22495 | O52: =M52+N52 -> 1846.1247 | P52: =O52*E52*F52 -> 3.7101338e-07 | Q52: =RATES!G53 -> 0.25495931 | R52: =P52+L52+K52+J52+I52 -> 0.0001180622 | S52: =R52*Q52 -> 3.0101056e-05 | T52: =C51*EXP(RATES!O53)*(DATA!$B$6-DATA!$B$12) -> 210.98568 | U52: =B51*EXP(RATES!O53)*(DATA!$B$6-DATA!$B$12) -> 843.94273 | V52: =T52+U52 -> 1054.9284 | W52: =V52*E52*F52 -> 2.1200765e-07 | X52: =W52*BASE!Q52 -> 5.4053324e-08
P56: LIABILITIES | Q56: =SUM(S3:S52) -> 94493.616 | T56: BEL COMPONENTS
P57: BOF | Q57: =DATA!B2-Q56 -> 5506.3842 | T57: DEATH | U57: =SUMPRODUCT(J3:J52,Q3:Q52) -> 6428.626
T58: LAPSE | U58: =SUMPRODUCT(I3:I52,Q3:Q52) -> 81227.1
P59: DURATION | Q59: =SUMPRODUCT(S3:S52,A3:A52)/SUM(S3:S52) -> 5.6130734 | T59: EXPENSES | U59: =SUMPRODUCT(L3:L52,Q3:Q52) -> 247.61987
T60: COMMISSIONS | U60: =SUMPRODUCT(P3:P52,Q3:Q52) -> 6590.2696
P61: PVFP | Q61: =SUM(X3:X52) -> 3765.8683
P62: LEAK | Q62: =D2-Q56-Q61 -> 1740.5158
P63: PVFP PROXY | Q63: =(DATA!B6-DATA!B12)*DATA!B2*Q59 -> 4490.4587

Sheet EQ STRESS 1
B1: EQUITY | C1: PROPERTY | D1: ASSET | E1: SURVIVAL PROB | F1: non LAPSE PROB | G1: C lapse | H1: C death | I1: LIAB LAPSE | J1: LIAB DEATH | K1: LIAB SURVIVE | L1: EXPENSES | M1: EQ COMMISSIONS | N1: PR COMMISSIONS | O1: TOT COMMISSIONS | P1: COMMISSIONS LIAB | Q1: DISCOUNTS | R1: TOT LIAB | S1: TOT LIAB DISC | T1: PROFIT PR | U1: PROFIT EQ | V1: TOT PROFIT | W1: PROFIT LIAB
A2: 0 | B2: =DATA!B2*0.8*(1-DATA!E2) -> 48800 | C2: =DATA!B2*0.2 -> 20000 | D2: =B2+C2 -> 68800 | E2: =1 -> 1 | F2: =1 -> 1 | G2: =D2-20 -> 68780 | H2: =MAX(D2,$B$2+$C$2) -> 68800 | M2: =B2 -> 48800 | N2: =C2 -> 20000 | Q2: =RATES!G3 -> 1
A3: 1 | B3: =B2*EXP(RATES!O4)*(1-DATA!$B$6) -> 49403.506 | C3: =C2*EXP(RATES!O4)*(1-DATA!$B$6) -> 20247.338 | D3: =B3+C3 -> 69650.844 | E3: =E2*(1-'LIFE TABLE MALE'!D63/1000) -> 0.99353213 | F3: =F2*(1-0.15) -> 0.85 | G3: =D3-20 -> 69630.844 | H3: =MAX(D3,$B$2+$C$2) -> 69650.844 | I3: =G3*DATA!$B$7*F2*E3 -> 10377.072 | J3: =H3*'LIFE TABLE MALE'!D63/1000*F2*E2 -> 450.49261 | K3: =0 -> 0 | L3: =DATA!$B$8*((1+DATA!$B$9)^A2)*F3*E3 -> 42.225116 | M3: =B2*EXP(RATES!O4)*(DATA!$B$12) -> 707.20765 | N3: =C2*EXP(RATES!O4)*(DATA!$B$12) -> 289.8392 | O3: =M3+N3 -> 997.04685 | P3: =O3*E3*F3 -> 842.00837 | Q3: =RATES!G4 -> 0.9660529 | R3: =P3+L3+K3+J3+I3 -> 11711.798 | S3: =R3*Q3 -> 11314.217 | T3: =C2*EXP(RATES!O4)*(DATA!$B$6-DATA!$B$12) -> 165.6224 | U3: =B2*EXP(RATES!O4)*(DATA!$B$6-DATA!$B$12) -> 404.11866 | V3: =T3+U3 -> 569.74106 | W3: =V3*E3*F3 -> 481.14764
A4: 2 | B4: =B3*EXP(RATES!O5)*(1-DATA!$B$6) -> 49552.673 | C4: =C3*EXP(RATES!O5)*(1-DATA!$B$6) -> 20308.472 | D4: =B4+C4 -> 69861.145 | E4: =E3*(1-'LIFE TABLE MALE'!D64/1000) -> 0.98647779 | F4: =F3*(1-0.15) -> 0.7225 | G4: =D4-20 -> 69841.145 | H4: =MAX(D4,$B$2+$C$2) -> 69861.145 | I4: =G4*DATA!$B$7*F3*E4 -> 8784.3342 | J4: =H4*'LIFE TABLE MALE'!D64/1000*F3*E3 -> 418.90042 | K4: =0 -> 0 | L4: =DATA!$B$8*((1+DATA!$B$9)^A3)*F4*E4 -> 36.34924 | M4: =B3*EXP(RATES!O5)*(DATA!$B$12) -> 709.34296 | N4: =C3*EXP(RATES!O5)*(DATA!$B$12) -> 290.71433 | O4: =M4+N4 -> 1000.0573 | P4: =O4*E4*F4 -> 712.77104 | Q4: =RATES!G5 -> 0.94195564 | R4: =P4+L4+K4+J4+I4 -> 9952.3549 | S4: =R4*Q4 -> 9374.6768 | T4: =C3*EXP(RATES!O5)*(DATA!$B$6-DATA!$B$12) -> 166.12247 | U4: =B3*EXP(RATES!O5)*(DATA!$B$6-DATA!$B$12) -> 405.33883 | V4: =T4+U4 -> 571.46131 | W4: =V4*E4*F4 -> 407.29774
A5: 3 | B5: =B4*EXP(RATES!O6)*(1-DATA!$B$6) -> 49567.87 | C5: =C4*EXP(RATES!O6)*(1-DATA!$B$6) -> 20314.701 | D5: =B5+C5 -> 69882.571 | E5: =E4*(1-'LIFE TABLE MALE'!D65/1000) -> 0.97876837 | F5: =F4*(1-0.15) -> 0.614125 | G5: =D5-20 -> 69862.571 | H5: =MAX(D5,$B$2+$C$2) -> 69882.571 | I5: =G5*DATA!$B$7*F4*E5 -> 7410.6039 | J5: =H5*'LIFE TABLE MALE'!D65/1000*F4*E4 -> 389.24996 | K5: =0 -> 0 | L5: =DATA!$B$8*((1+DATA!$B$9)^A4)*F5*E5 -> 31.2685 | M5: =B4*EXP(RATES!O6)*(DATA!$B$12) -> 709.56051 | N5: =C4*EXP(RATES!O6)*(DATA!$B$12) -> 290.80349 | O5: =M5+N5 -> 1000.364 | P5: =O5*E5*F5 -> 601.30492 | Q5: =RATES!G6 -> 0.92095017 | R5: =P5+L5+K5+J5+I5 -> 8432.4272 | S5: =R5*Q5 -> 7765.8453 | T5: =C4*EXP(RATES!O6)*(DATA!$B$6-DATA!$B$12) -> 166.17342 | U5: =B4*EXP(RATES!O6)*(DATA!$B$6-DATA!$B$12) -> 405.46315 | V5: =T5+U5 -> 571.63657 | W5: =V5*E5*F5 -> 343.60281
A6: 4 | B6: =B5*EXP(RATES!O7)*(1-DATA!$B$6) -> 49543.997 | C6: =C5*EXP(RATES!O7)*(1-DATA!$B$6) -> 20304.917 | D6: =B6+C6 -> 69848.914 | E6: =E5*(1-'LIFE TABLE MALE'!D66/1000) -> 0.97028747 | F6: =F5*(1-0.15) -> 0.52200625 | G6: =D6-20 -> 69828.914 | H6: =MAX(D6,$B$2+$C$2) -> 69848.914 | I6: =G6*DATA!$B$7*F5*E6 -> 6241.4248 | J6: =H6*'LIFE TABLE MALE'!D66/1000*F5*E5 -> 363.79641 | K6: =0 -> 0 | L6: =DATA!$B$8*((1+DATA!$B$9)^A5)*F6*E6 -> 26.874887 | M6: =B5*EXP(RATES!O7)*(DATA!$B$12) -> 709.21877 | N6: =C5*EXP(RATES!O7)*(DATA!$B$12) -> 290.66343 | O6: =M6+N6 -> 999.8822 | P6: =O6*E6*F6 -> 506.43646 | Q6: =RATES!G7 -> 0.90112326 | R6: =P6+L6+K6+J6+I6 -> 7138.5326 | S6: =R6*Q6 -> 6432.6978 | T6: =C5*EXP(RATES!O7)*(DATA!$B$6-DATA!$B$12) -> 166.09339 | U6: =B5*EXP(RATES!O7)*(DATA!$B$6-DATA!$B$12) -> 405.26787 | V6: =T6+U6 -> 571.36126 | W6: =V6*E6*F6 -> 289.39226
A7: 5 | B7: =B6*EXP(RATES!O8)*(1-DATA!$B$6) -> 49518.929 | C7: =C6*EXP(RATES!O8)*(1-DATA!$B$6) -> 20294.643 | D7: =B7+C7 -> 69813.572 | E7: =E6*(1-'LIFE TABLE MALE'!D67/1000) -> 0.96092158 | F7: =F6*(1-0.15) -> 0.44370531 | G7: =D7-20 -> 69793.572 | H7: =MAX(D7,$B$2+$C$2) -> 69813.572 | I7: =G7*DATA!$B$7*F6*E7 -> 5251.3424 | J7: =H7*'LIFE TABLE MALE'!D67/1000*F6*E6 -> 341.3224 | K7: =0 -> 0 | L7: =DATA!$B$8*((1+DATA!$B$9)^A6)*F7*E7 -> 23.075614 | M7: =B6*EXP(RATES!O8)*(DATA!$B$12) -> 708.85993 | N7: =C6*EXP(RATES!O8)*(DATA!$B$12) -> 290.51636 | O7: =M7+N7 -> 999.37629 | P7: =O7*E7*F7 -> 426.10008 | Q7: =RATES!G8 -> 0.88174469 | R7: =P7+L7+K7+J7+I7 -> 6041.8405 | S7: =R7*Q7 -> 5327.3607 | T7: =C6*EXP(RATES!O8)*(DATA!$B$6-DATA!$B$12) -> 166.00935 | U7: =B6*EXP(RATES!O8)*(DATA!$B$6-DATA!$B$12) -> 405.06282 | V7: =T7+U7 -> 571.07217 | W7: =V7*E7*F7 -> 243.48576
A8: 6 | B8: =B7*EXP(RATES!O9)*(1-DATA!$B$6) -> 49527.566 | C8: =C7*EXP(RATES!O9)*(1-DATA!$B$6) -> 20298.183 | D8: =B8+C8 -> 69825.749 | E8: =E7*(1-'LIFE TABLE MALE'!D68/1000) -> 0.95054817 | F8: =F7*(1-0.15) -> 0.37714952 | G8: =D8-20 -> 69805.749 | H8: =MAX(D8,$B$2+$C$2) -> 69825.749 | I8: =G8*DATA!$B$7*F7*E8 -> 4416.2252 | J8: =H8*'LIFE TABLE MALE'!D68/1000*F7*E7 -> 321.3895 | K8: =0 -> 0 | L8: =DATA!$B$8*((1+DATA!$B$9)^A7)*F8*E8 -> 19.790581 | M8: =B7*EXP(RATES!O9)*(DATA!$B$12) -> 708.98356 | N8: =C7*EXP(RATES!O9)*(DATA!$B$12) -> 290.56703 | O8: =M8+N8 -> 999.5506 | P8: =O8*E8*F8 -> 358.33767 | Q8: =RATES!G9 -> 0.86219592 | R8: =P8+L8+K8+J8+I8 -> 5115.7429 | S8: =R8*Q8 -> 4410.7727 | T8: =C7*EXP(RATES!O9)*(DATA!$B$6-DATA!$B$12) -> 166.03831 | U8: =B7*EXP(RATES!O9)*(DATA!$B$6-DATA!$B$12) -> 405.13347 | V8: =T8+U8 -> 571.17177 | W8: =V8*E8*F8 -> 204.76438
A9: 7 | B9: =B8*EXP(RATES!O10)*(1-DATA!$B$6) -> 49565.173 | C9: =C8*EXP(RATES!O10)*(1-DATA!$B$6) -> 20313.596 | D9: =B9+C9 -> 69878.769 | E9: =E8*(1-'LIFE TABLE MALE'!D69/1000) -> 0.93939989 | F9: =F8*(1-0.15) -> 0.32057709 | G9: =D9-20 -> 69858.769 | H9: =MAX(D9,$B$2+$C$2) -> 69878.769 | I9: =G9*DATA!$B$7*F8*E9 -> 3712.5836 | J9: =H9*'LIFE TABLE MALE'!D69/1000*F8*E8 -> 293.80996 | K9: =0 -> 0 | L9: =DATA!$B$8*((1+DATA!$B$9)^A8)*F9*E9 -> 16.957195 | M9: =B8*EXP(RATES!O10)*(DATA!$B$12) -> 709.5219 | N9: =C8*EXP(RATES!O10)*(DATA!$B$12) -> 290.78767 | O9: =M9+N9 -> 1000.3096 | P9: =O9*E9*F9 -> 301.24331 | Q9: =RATES!G10 -> 0.84258782 | R9: =P9+L9+K9+J9+I9 -> 4324.5941 | S9: =R9*Q9 -> 3643.8503 | T9: =C8*EXP(RATES!O10)*(DATA!$B$6-DATA!$B$12) -> 166.16438 | U9: =B8*EXP(RATES!O10)*(DATA!$B$6-DATA!$B$12) -> 405.44109 | V9: =T9+U9 -> 571.60547 | W9: =V9*E9*F9 -> 172.13903
A10: 8 | B10: =B9*EXP(RATES!O11)*(1-DATA!$B$6) -> 49632.817 | C10: =C9*EXP(RATES!O11)*(1-DATA!$B$6) -> 20341.318 | D10: =B10+C10 -> 69974.135 | E10: =E9*(1-'LIFE TABLE MALE'!D70/1000) -> 0.92737751 | F10: =F9*(1-0.15) -> 0.27249053 | G10: =D10-20 -> 69954.135 | H10: =MAX(D10,$B$2+$C$2) -> 69974.135 | I10: =G10*DATA!$B$7*F9*E10 -> 3119.5625 | J10: =H10*'LIFE TABLE MALE'!D70/1000*F9*E9 -> 269.68736 | K10: =0 -> 0 | L10: =DATA!$B$8*((1+DATA!$B$9)^A9)*F10*E10 -> 14.513734 | M10: =B9*EXP(RATES!O11)*(DATA!$B$12) -> 710.49022 | N10: =C9*EXP(RATES!O11)*(DATA!$B$12) -> 291.18452 | O10: =M10+N10 -> 1001.6747 | P10: =O10*E10*F10 -> 253.12479 | Q10: =RATES!G11 -> 0.82292781 | R10: =P10+L10+K10+J10+I10 -> 3656.8884 | S10: =R10*Q10 -> 3009.3551 | T10: =C9*EXP(RATES!O11)*(DATA!$B$6-DATA!$B$12) -> 166.39115 | U10: =B9*EXP(RATES!O11)*(DATA!$B$6-DATA!$B$12) -> 405.99441 | V10: =T10+U10 -> 572.38556 | W10: =V10*E10*F10 -> 144.64274
A11: 9 | B11: =B10*EXP(RATES!O12)*(1-DATA!$B$6) -> 49729.177 | C11: =C10*EXP(RATES!O12)*(1-DATA!$B$6) -> 20380.81 | D11: =B11+C11 -> 70109.987 | E11: =E10*(1-'LIFE TABLE MALE'!D71/1000) -> 0.91441742 | F11: =F10*(1-0.15) -> 0.23161695 | G11: =D11-20 -> 70089.987 | H11: =MAX(D11,$B$2+$C$2) -> 70109.987 | I11: =G11*DATA!$B$7*F10*E11 -> 2619.6492 | J11: =H11*'LIFE TABLE MALE'!D71/1000*F10*E10 -> 247.59357 | K11: =0 -> 0 | L11: =DATA!$B$8*((1+DATA!$B$9)^A10)*F11*E11 -> 12.407555 | M11: =B10*EXP(RATES!O12)*(DATA!$B$12) -> 711.8696 | N11: =C10*EXP(RATES!O12)*(DATA!$B$12) -> 291.74984 | O11: =M11+N11 -> 1003.6194 | P11: =O11*E11*F11 -> 212.56115 | Q11: =RATES!G12 -> 0.8032639 | R11: =P11+L11+K11+J11+I11 -> 3092.2114 | S11: =R11*Q11 -> 2483.8618 | T11: =C10*EXP(RATES!O12)*(DATA!$B$6-DATA!$B$12) -> 166.71419 | U11: =B10*EXP(RATES!O12)*(DATA!$B$6-DATA!$B$12) -> 406.78263 | V11: =T11+U11 -> 573.49682 | W11: =V11*E11*F11 -> 121.46351
A12: 10 | B12: =B11*EXP(RATES!O13)*(1-DATA!$B$6) -> 49862.693 | C12: =C11*EXP(RATES!O13)*(1-DATA!$B$6) -> 20435.53 | D12: =B12+C12 -> 70298.223 | E12: =E11*(1-'LIFE TABLE MALE'!D72/1000) -> 0.9000976 | F12: =F11*(1-0.15) -> 0.1968744 | G12: =D12-20 -> 70278.223 | H12: =MAX(D12,$B$2+$C$2) -> 70298.223 | I12: =G12*DATA!$B$7*F11*E12 -> 2197.718 | J12: =H12*'LIFE TABLE MALE'!D72/1000*F11*E11 -> 233.15907 | K12: =0 -> 0 | L12: =DATA!$B$8*((1+DATA!$B$9)^A11)*F12*E12 -> 10.588889 | M12: =B11*EXP(RATES!O13)*(DATA!$B$12) -> 713.78088 | N12: =C11*EXP(RATES!O13)*(DATA!$B$12) -> 292.53315 | O12: =M12+N12 -> 1006.314 | P12: =O12*E12*F12 -> 178.32506 | Q12: =RATES!G13 -> 0.78348852 | R12: =P12+L12+K12+J12+I12 -> 2619.791 | S12: =R12*Q12 -> 2052.5762 | T12: =C11*EXP(RATES!O13)*(DATA!$B$6-DATA!$B$12) -> 167.1618 | U12: =B11*EXP(RATES!O13)*(DATA!$B$6-DATA!$B$12) -> 407.87479 | V12: =T12+U12 -> 575.03659 | W12: =V12*E12*F12 -> 101.90004
A13: 11 | B13: =B12*EXP(RATES!O14)*(1-DATA!$B$6) -> 50061.495 | C13: =C12*EXP(RATES!O14)*(1-DATA!$B$6) -> 20517.006 | D13: =B13+C13 -> 70578.501 | E13: =E12*(1-'LIFE TABLE MALE'!D73/1000) -> 0.88436967 | F13: =F12*(1-0.15) -> 0.16734324 | G13: =D13-20 -> 70558.501 | H13: =MAX(D13,$B$2+$C$2) -> 70578.501 | I13: =G13*DATA!$B$7*F12*E13 -> 1842.7385 | J13: =H13*'LIFE TABLE MALE'!D73/1000*F12*E12 -> 218.54113 | K13: =0 -> 0 | L13: =DATA!$B$8*((1+DATA!$B$9)^A12)*F13*E13 -> 9.0201497 | M13: =B12*EXP(RATES!O14)*(DATA!$B$12) -> 716.62671 | N13: =C12*EXP(RATES!O14)*(DATA!$B$12) -> 293.69947 | O13: =M13+N13 -> 1010.3262 | P13: =O13*E13*F13 -> 149.52149 | Q13: =RATES!G14 -> 0.76320888 | R13: =P13+L13+K13+J13+I13 -> 2219.8212 | S13: =R13*Q13 -> 1694.1873 | T13: =C12*EXP(RATES!O14)*(DATA!$B$6-DATA!$B$12) -> 167.82827 | U13: =B12*EXP(RATES!O14)*(DATA!$B$6-DATA!$B$12) -> 409.50098 | V13: =T13+U13 -> 577.32925 | W13: =V13*E13*F13 -> 85.440854
A14: 12 | B14: =B13*EXP(RATES!O15)*(1-DATA!$B$6) -> 50177.78 | C14: =C13*EXP(RATES!O15)*(1-DATA!$B$6) -> 20564.664 | D14: =B14+C14 -> 70742.445 | E14: =E13*(1-'LIFE TABLE MALE'!D74/1000) -> 0.86691444 | F14: =F13*(1-0.15) -> 0.14224176 | G14: =D14-20 -> 70722.445 | H14: =MAX(D14,$B$2+$C$2) -> 70742.445 | I14: =G14*DATA!$B$7*F13*E14 -> 1538.9799 | J14: =H14*'LIFE TABLE MALE'!D74/1000*F13*E13 -> 206.63971 | K14: =0 -> 0 | L14: =DATA!$B$8*((1+DATA!$B$9)^A13)*F14*E14 -> 7.6661134 | M14: =B13*EXP(RATES!O15)*(DATA!$B$12) -> 718.29134 | N14: =C13*EXP(RATES!O15)*(DATA!$B$12) -> 294.3817 | O14: =M14+N14 -> 1012.673 | P14: =O14*E14*F14 -> 124.87416 | Q14: =RATES!G15 -> 0.74468847 | R14: =P14+L14+K14+J14+I14 -> 1878.1599 | S14: =R14*Q14 -> 1398.644 | T14: =C13*EXP(RATES!O15)*(DATA!$B$6-DATA!$B$12) -> 168.21811 | U14: =B13*EXP(RATES!O15)*(DATA!$B$6-DATA!$B$12) -> 410.45219 | V14: =T14+U14 -> 578.6703 | W14: =V14*E14*F14 -> 71.356664
... A51: 49 | B51: =B50*EXP(RATES!O52)*(1-DATA!$B$6) -> 62288.001 | C51: =C50*EXP(RATES!O52)*(1-DATA!$B$6) -> 25527.869 | D51: =B51+C51 -> 87815.87 | E51: =E50*(1-'LIFE TABLE MALE'!D111/1000) -> 2.6221013e-06 | F51: =F50*(1-0.15) -> 0.00034795843 | G51: =D51-20 -> 87795.87 | H51: =MAX(D51,$B$2+$C$2) -> 87815.87 | I51: =G51*DATA!$B$7*F50*E51 -> 1.4135893e-05 | J51: =H51*'LIFE TABLE MALE'!D111/1000*F50*E50 -> 0.00023210328 | K51: =0 -> 0 | L51: =DATA!$B$8*((1+DATA!$B$9)^A50)*F51*E51 -> 1.1801985e-07 | M51: =B50*EXP(RATES!O52)*(DATA!$B$12) -> 891.64827 | N51: =C50*EXP(RATES!O52)*(DATA!$B$12) -> 365.42962 | O51: =M51+N51 -> 1257.0779 | P51: =O51*E51*F51 -> 1.1469356e-06 | Q51: =RATES!G52 -> 0.26340215 | R51: =P51+L51+K51+J51+I51 -> 0.00024750413 | S51: =R51*Q51 -> 6.5193119e-05 | T51: =C50*EXP(RATES!O52)*(DATA!$B$6-DATA!$B$12) -> 208.81693 | U51: =B50*EXP(RATES!O52)*(DATA!$B$6-DATA!$B$12) -> 509.5133 | V51: =T51+U51 -> 718.33022 | W51: =V51*E51*F51 -> 6.5539174e-07
A52: 50 | B52: =B51*EXP(RATES!O53)*(1-DATA!$B$6) -> 62934.92 | C52: =C51*EXP(RATES!O53)*(1-DATA!$B$6) -> 25793 | D52: =B52+C52 -> 88727.919 | E52: =E51*(1-'LIFE TABLE MALE'!D112/1000) -> 6.7948871e-07 | F52: =F51*(1-0.15) -> 0.00029576466 | G52: =D52-20 -> 88707.919 | H52: =MAX(D52,$B$2+$C$2) -> 88727.919 | I52: =G52*DATA!$B$7*F51*E52 -> 3.1460329e-06 | J52: =H52*'LIFE TABLE MALE'!D112/1000*F51*E51 -> 5.9975497e-05 | K52: =E52*D52*F52 -> 1.7831539e-05 | L52: =DATA!$B$8*((1+DATA!$B$9)^A51)*F52*E52 -> 2.6515935e-08 | M52: =B51*EXP(RATES!O53)*(DATA!$B$12) -> 900.90887 | N52: =C51*EXP(RATES!O53)*(DATA!$B$12) -> 369.22495 | O52: =M52+N52 -> 1270.1338 | P52: =O52*E52*F52 -> 2.552572e-07 | Q52: =RATES!G53 -> 0.25495931 | R52: =P52+L52+K52+J52+I52 -> 8.1234842e-05 | S52: =R52*Q52 -> 2.071158e-05 | T52: =C51*EXP(RATES!O53)*(DATA!$B$6-DATA!$B$12) -> 210.98568 | U52: =B51*EXP(RATES!O53)*(DATA!$B$6-DATA!$B$12) -> 514.80507 | V52: =T52+U52 -> 725.79075 | W52: =V52*E52*F52 -> 1.4586126e-07
P56: LIABILITIES | Q56: =SUM(S3:S52) -> 65083.882 | T56: BEL COMPONENTS
P57: BOF | Q57: =B2+C2-Q56 -> 3716.1178 | T57: DEATH | U57: =SUMPRODUCT(J3:J52,Q3:Q52) -> 4422.8947
T58: LAPSE | U58: =SUMPRODUCT(I3:I52,Q3:Q52) -> 55879.262
P59: DURATION | Q59: =SUMPRODUCT(S3:S52,A3:A52)/SUM(S3:S52) -> 5.6132956 | T59: EXPENSES | U59: =SUMPRODUCT(L3:L52,Q3:Q52) -> 247.61987
T60: COMMISSIONS | U60: =SUMPRODUCT(P3:P52,Q3:Q52) -> 4534.1055

Sheet PROPERTY STRESS
B1: EQUITY | C1: PROPERTY | D1: ASSET | E1: SURVIVAL PROB | F1: non LAPSE PROB | G1: C lapse | H1: C death | I1: LIAB LAPSE | J1: LIAB DEATH | K1: LIAB SURVIVE | L1: EXPENSES | M1: EQ COMMISSIONS | N1: PR COMMISSIONS | O1: TOT COMMISSIONS | P1: COMMISSIONS LIAB | Q1: DISCOUNTS | R1: TOT LIAB | S1: TOT LIAB DISC | T1: PROFIT PR | U1: PROFIT EQ | V1: TOT PROFIT | W1: PROFIT LIAB
A2: 0 | B2: =DATA!B2*0.8 -> 80000 | C2: =DATA!B2*0.2*(1-DATA!E4) -> 15000 | D2: =B2+C2 -> 95000 | E2: =1 -> 1 | F2: =1 -> 1 | G2: =D2-20 -> 94980 | H2: =MAX(D2,$B$2+$C$2) -> 95000 | M2: =B2 -> 80000 | N2: =C2 -> 15000 | Q2: =RATES!G3 -> 1
A3: 1 | B3: =B2*EXP(RATES!O4)*(1-DATA!$B$6) -> 80989.354 | C3: =C2*EXP(RATES!O4)*(1-DATA!$B$6) -> 15185.504 | D3: =B3+C3 -> 96174.857 | E3: =E2*(1-'LIFE TABLE MALE'!D63/1000) -> 0.99353213 | F3: =F2*(1-0.15) -> 0.85 | G3: =D3-20 -> 96154.857 | H3: =MAX(D3,$B$2+$C$2) -> 96174.857 | I3: =G3*DATA!$B$7*F2*E3 -> 14329.941 | J3: =H3*'LIFE TABLE MALE'!D63/1000*F2*E2 -> 622.04647 | K3: =0 -> 0 | L3: =DATA!$B$8*((1+DATA!$B$9)^A2)*F3*E3 -> 42.225116 | M3: =B2*EXP(RATES!O4)*(DATA!$B$12) -> 1159.3568 | N3: =C2*EXP(RATES!O4)*(DATA!$B$12) -> 217.3794 | O3: =M3+N3 -> 1376.7362 | P3: =O3*E3*F3 -> 1162.6569 | Q3: =RATES!G4 -> 0.9660529 | R3: =P3+L3+K3+J3+I3 -> 16156.87 | S3: =R3*Q3 -> 15608.391 | T3: =C2*EXP(RATES!O4)*(DATA!$B$6-DATA!$B$12) -> 124.2168 | U3: =B2*EXP(RATES!O4)*(DATA!$B$6-DATA!$B$12) -> 662.4896 | V3: =T3+U3 -> 786.7064 | W3: =V3*E3*F3 -> 664.37537
A4: 2 | B4: =B3*EXP(RATES!O5)*(1-DATA!$B$6) -> 81233.889 | C4: =C3*EXP(RATES!O5)*(1-DATA!$B$6) -> 15231.354 | D4: =B4+C4 -> 96465.244 | E4: =E3*(1-'LIFE TABLE MALE'!D64/1000) -> 0.98647779 | F4: =F3*(1-0.15) -> 0.7225 | G4: =D4-20 -> 96445.244 | H4: =MAX(D4,$B$2+$C$2) -> 96465.244 | I4: =G4*DATA!$B$7*F3*E4 -> 12130.489 | J4: =H4*'LIFE TABLE MALE'!D64/1000*F3*E3 -> 578.42354 | K4: =0 -> 0 | L4: =DATA!$B$8*((1+DATA!$B$9)^A3)*F4*E4 -> 36.34924 | M4: =B3*EXP(RATES!O5)*(DATA!$B$12) -> 1162.8573 | N4: =C3*EXP(RATES!O5)*(DATA!$B$12) -> 218.03575 | O4: =M4+N4 -> 1380.8931 | P4: =O4*E4*F4 -> 984.20419 | Q4: =RATES!G5 -> 0.94195564 | R4: =P4+L4+K4+J4+I4 -> 13729.466 | S4: =R4*Q4 -> 12932.548 | T4: =C3*EXP(RATES!O5)*(DATA!$B$6-DATA!$B$12) -> 124.59185 | U4: =B3*EXP(RATES!O5)*(DATA!$B$6-DATA!$B$12) -> 664.48989 | V4: =T4+U4 -> 789.08175 | W4: =V4*E4*F4 -> 562.4024
A5: 3 | B5: =B4*EXP(RATES!O6)*(1-DATA!$B$6) -> 81258.803 | C5: =C4*EXP(RATES!O6)*(1-DATA!$B$6) -> 15236.026 | D5: =B5+C5 -> 96494.828 | E5: =E4*(1-'LIFE TABLE MALE'!D65/1000) -> 0.97876837 | F5: =F4*(1-0.15) -> 0.614125 | G5: =D5-20 -> 96474.828 | H5: =MAX(D5,$B$2+$C$2) -> 96494.828 | I5: =G5*DATA!$B$7*F4*E5 -> 10233.473 | J5: =H5*'LIFE TABLE MALE'!D65/1000*F4*E4 -> 537.48178 | K5: =0 -> 0 | L5: =DATA!$B$8*((1+DATA!$B$9)^A4)*F5*E5 -> 31.2685 | M5: =B4*EXP(RATES!O6)*(DATA!$B$12) -> 1163.2139 | N5: =C4*EXP(RATES!O6)*(DATA!$B$12) -> 218.10262 | O5: =M5+N5 -> 1381.3166 | P5: =O5*E5*F5 -> 830.29022 | Q5: =RATES!G6 -> 0.92095017 | R5: =P5+L5+K5+J5+I5 -> 11632.514 | S5: =R5*Q5 -> 10712.965 | T5: =C4*EXP(RATES!O6)*(DATA!$B$6-DATA!$B$12) -> 124.63007 | U5: =B4*EXP(RATES!O6)*(DATA!$B$6-DATA!$B$12) -> 664.69368 | V5: =T5+U5 -> 789.32375 | W5: =V5*E5*F5 -> 474.45156
A6: 4 | B6: =B5*EXP(RATES!O7)*(1-DATA!$B$6) -> 81219.667 | C6: =C5*EXP(RATES!O7)*(1-DATA!$B$6) -> 15228.688 | D6: =B6+C6 -> 96448.354 | E6: =E5*(1-'LIFE TABLE MALE'!D66/1000) -> 0.97028747 | F6: =F5*(1-0.15) -> 0.52200625 | G6: =D6-20 -> 96428.354 | H6: =MAX(D6,$B$2+$C$2) -> 96448.354 | I6: =G6*DATA!$B$7*F5*E6 -> 8618.9272 | J6: =H6*'LIFE TABLE MALE'!D66/1000*F5*E5 -> 502.33516 | K6: =0 -> 0 | L6: =DATA!$B$8*((1+DATA!$B$9)^A5)*F6*E6 -> 26.874887 | M6: =B5*EXP(RATES!O7)*(DATA!$B$12) -> 1162.6537 | N6: =C5*EXP(RATES!O7)*(DATA!$B$12) -> 217.99757 | O6: =M6+N6 -> 1380.6513 | P6: =O6*E6*F6 -> 699.29453 | Q6: =RATES!G7 -> 0.90112326 | R6: =P6+L6+K6+J6+I6 -> 9847.4318 | S6: =R6*Q6 -> 8873.7499 | T6: =C5*EXP(RATES!O7)*(DATA!$B$6-DATA!$B$12) -> 124.57004 | U6: =B5*EXP(RATES!O7)*(DATA!$B$6-DATA!$B$12) -> 664.37355 | V6: =T6+U6 -> 788.94359 | W6: =V6*E6*F6 -> 399.59687
A7: 5 | B7: =B6*EXP(RATES!O8)*(1-DATA!$B$6) -> 81178.572 | C7: =C6*EXP(RATES!O8)*(1-DATA!$B$6) -> 15220.982 | D7: =B7+C7 -> 96399.555 | E7: =E6*(1-'LIFE TABLE MALE'!D67/1000) -> 0.96092158 | F7: =F6*(1-0.15) -> 0.44370531 | G7: =D7-20 -> 96379.555 | H7: =MAX(D7,$B$2+$C$2) -> 96399.555 | I7: =G7*DATA!$B$7*F6*E7 -> 7251.6999 | J7: =H7*'LIFE TABLE MALE'!D67/1000*F6*E6 -> 471.30274 | K7: =0 -> 0 | L7: =DATA!$B$8*((1+DATA!$B$9)^A6)*F7*E7 -> 23.075614 | M7: =B6*EXP(RATES!O8)*(DATA!$B$12) -> 1162.0655 | N7: =C6*EXP(RATES!O8)*(DATA!$B$12) -> 217.88727 | O7: =M7+N7 -> 1379.9527 | P7: =O7*E7*F7 -> 588.36494 | Q7: =RATES!G8 -> 0.88174469 | R7: =P7+L7+K7+J7+I7 -> 8334.4432 | S7: =R7*Q7 -> 7348.851 | T7: =C6*EXP(RATES!O8)*(DATA!$B$6-DATA!$B$12) -> 124.50701 | U7: =B6*EXP(RATES!O8)*(DATA!$B$6-DATA!$B$12) -> 664.0374 | V7: =T7+U7 -> 788.54441 | W7: =V7*E7*F7 -> 336.20853
A8: 6 | B8: =B7*EXP(RATES!O9)*(1-DATA!$B$6) -> 81192.731 | C8: =C7*EXP(RATES!O9)*(1-DATA!$B$6) -> 15223.637 | D8: =B8+C8 -> 96416.369 | E8: =E7*(1-'LIFE TABLE MALE'!D68/1000) -> 0.95054817 | F8: =F7*(1-0.15) -> 0.37714952 | G8: =D8-20 -> 96396.369 | H8: =MAX(D8,$B$2+$C$2) -> 96416.369 | I8: =G8*DATA!$B$7*F7*E8 -> 6098.4672 | J8: =H8*'LIFE TABLE MALE'!D68/1000*F7*E7 -> 443.77911 | K8: =0 -> 0 | L8: =DATA!$B$8*((1+DATA!$B$9)^A7)*F8*E8 -> 19.790581 | M8: =B7*EXP(RATES!O9)*(DATA!$B$12) -> 1162.2681 | N8: =C7*EXP(RATES!O9)*(DATA!$B$12) -> 217.92528 | O8: =M8+N8 -> 1380.1934 | P8: =O8*E8*F8 -> 494.79766 | Q8: =RATES!G9 -> 0.86219592 | R8: =P8+L8+K8+J8+I8 -> 7056.8345 | S8: =R8*Q8 -> 6084.3739 | T8: =C7*EXP(RATES!O9)*(DATA!$B$6-DATA!$B$12) -> 124.52873 | U8: =B7*EXP(RATES!O9)*(DATA!$B$6-DATA!$B$12) -> 664.15322 | V8: =T8+U8 -> 788.68195 | W8: =V8*E8*F8 -> 282.74152
A9: 7 | B9: =B8*EXP(RATES!O10)*(1-DATA!$B$6) -> 81254.382 | C9: =C8*EXP(RATES!O10)*(1-DATA!$B$6) -> 15235.197 | D9: =B9+C9 -> 96489.579 | E9: =E8*(1-'LIFE TABLE MALE'!D69/1000) -> 0.93939989 | F9: =F8*(1-0.15) -> 0.32057709 | G9: =D9-20 -> 96469.579 | H9: =MAX(D9,$B$2+$C$2) -> 96489.579 | I9: =G9*DATA!$B$7*F8*E9 -> 5126.792 | J9: =H9*'LIFE TABLE MALE'!D69/1000*F8*E8 -> 405.69689 | K9: =0 -> 0 | L9: =DATA!$B$8*((1+DATA!$B$9)^A8)*F9*E9 -> 16.957195 | M9: =B8*EXP(RATES!O10)*(DATA!$B$12) -> 1163.1507 | N9: =C8*EXP(RATES!O10)*(DATA!$B$12) -> 218.09075 | O9: =M9+N9 -> 1381.2414 | P9: =O9*E9*F9 -> 415.96096 | Q9: =RATES!G10 -> 0.84258782 | R9: =P9+L9+K9+J9+I9 -> 5965.4071 | S9: =R9*Q9 -> 5026.3794 | T9: =C8*EXP(RATES!O10)*(DATA!$B$6-DATA!$B$12) -> 124.62329 | U9: =B8*EXP(RATES!O10)*(DATA!$B$6-DATA!$B$12) -> 664.65752 | V9: =T9+U9 -> 789.28081 | W9: =V9*E9*F9 -> 237.69198
A10: 8 | B10: =B9*EXP(RATES!O11)*(1-DATA!$B$6) -> 81365.273 | C10: =C9*EXP(RATES!O11)*(1-DATA!$B$6) -> 15255.989 | D10: =B10+C10 -> 96621.262 | E10: =E9*(1-'LIFE TABLE MALE'!D70/1000) -> 0.92737751 | F10: =F9*(1-0.15) -> 0.27249053 | G10: =D10-20 -> 96601.262 | H10: =MAX(D10,$B$2+$C$2) -> 96621.262 | I10: =G10*DATA!$B$7*F9*E10 -> 4307.8751 | J10: =H10*'LIFE TABLE MALE'!D70/1000*F9*E9 -> 372.38807 | K10: =0 -> 0 | L10: =DATA!$B$8*((1+DATA!$B$9)^A9)*F10*E10 -> 14.513734 | M10: =B9*EXP(RATES!O11)*(DATA!$B$12) -> 1164.7381 | N10: =C9*EXP(RATES!O11)*(DATA!$B$12) -> 218.38839 | O10: =M10+N10 -> 1383.1265 | P10: =O10*E10*F10 -> 349.51825 | Q10: =RATES!G11 -> 0.82292781 | R10: =P10+L10+K10+J10+I10 -> 5044.2951 | S10: =R10*Q10 -> 4151.0907 | T10: =C9*EXP(RATES!O11)*(DATA!$B$6-DATA!$B$12) -> 124.79336 | U10: =B9*EXP(RATES!O11)*(DATA!$B$6-DATA!$B$12) -> 665.56461 | V10: =T10+U10 -> 790.35797 | W10: =V10*E10*F10 -> 199.72471
A11: 9 | B11: =B10*EXP(RATES!O12)*(1-DATA!$B$6) -> 81523.24 | C11: =C10*EXP(RATES!O12)*(1-DATA!$B$6) -> 15285.608 | D11: =B11+C11 -> 96808.848 | E11: =E10*(1-'LIFE TABLE MALE'!D71/1000) -> 0.91441742 | F11: =F10*(1-0.15) -> 0.23161695 | G11: =D11-20 -> 96788.848 | H11: =MAX(D11,$B$2+$C$2) -> 96808.848 | I11: =G11*DATA!$B$7*F10*E11 -> 3617.5328 | J11: =H11*'LIFE TABLE MALE'!D71/1000*F10*E10 -> 341.88065 | K11: =0 -> 0 | L11: =DATA!$B$8*((1+DATA!$B$9)^A10)*F11*E11 -> 12.407555 | M11: =B10*EXP(RATES!O12)*(DATA!$B$12) -> 1166.9993 | N11: =C10*EXP(RATES!O12)*(DATA!$B$12) -> 218.81238 | O11: =M11+N11 -> 1385.8117 | P11: =O11*E11*F11 -> 293.5074 | Q11: =RATES!G12 -> 0.8032639 | R11: =P11+L11+K11+J11+I11 -> 4265.3284 | S11: =R11*Q11 -> 3426.1843 | T11: =C10*EXP(RATES!O12)*(DATA!$B$6-DATA!$B$12) -> 125.03564 | U11: =B10*EXP(RATES!O12)*(DATA!$B$6-DATA!$B$12) -> 666.85677 | V11: =T11+U11 -> 791.89242 | W11: =V11*E11*F11 -> 167.71851
A12: 10 | B12: =B11*EXP(RATES!O13)*(1-DATA!$B$6) -> 81742.12 | C12: =C11*EXP(RATES!O13)*(1-DATA!$B$6) -> 15326.647 | D12: =B12+C12 -> 97068.767 | E12: =E11*(1-'LIFE TABLE MALE'!D72/1000) -> 0.9000976 | F12: =F11*(1-0.15) -> 0.1968744 | G12: =D12-20 -> 97048.767 | H12: =MAX(D12,$B$2+$C$2) -> 97068.767 | I12: =G12*DATA!$B$7*F11*E12 -> 3034.8779 | J12: =H12*'LIFE TABLE MALE'!D72/1000*F11*E11 -> 321.9493 | K12: =0 -> 0 | L12: =DATA!$B$8*((1+DATA!$B$9)^A11)*F12*E12 -> 10.588889 | M12: =B11*EXP(RATES!O13)*(DATA!$B$12) -> 1170.1326 | N12: =C11*EXP(RATES!O13)*(DATA!$B$12) -> 219.39986 | O12: =M12+N12 -> 1389.5325 | P12: =O12*E12*F12 -> 246.23374 | Q12: =RATES!G13 -> 0.78348852 | R12: =P12+L12+K12+J12+I12 -> 3613.6498 | S12: =R12*Q12 -> 2831.2531 | T12: =C11*EXP(RATES!O13)*(DATA!$B$6-DATA!$B$12) -> 125.37135 | U12: =B11*EXP(RATES!O13)*(DATA!$B$6-DATA!$B$12) -> 668.6472 | V12: =T12+U12 -> 794.01855 | W12: =V12*E12*F12 -> 140.70499
A13: 11 | B13: =B12*EXP(RATES!O14)*(1-DATA!$B$6) -> 82068.024 | C13: =C12*EXP(RATES!O14)*(1-DATA!$B$6) -> 15387.754 | D13: =B13+C13 -> 97455.778 | E13: =E12*(1-'LIFE TABLE MALE'!D73/1000) -> 0.88436967 | F13: =F12*(1-0.15) -> 0.16734324 | G13: =D13-20 -> 97435.778 | H13: =MAX(D13,$B$2+$C$2) -> 97455.778 | I13: =G13*DATA!$B$7*F12*E13 -> 2544.6779 | J13: =H13*'LIFE TABLE MALE'!D73/1000*F12*E12 -> 301.76464 | K13: =0 -> 0 | L13: =DATA!$B$8*((1+DATA!$B$9)^A12)*F13*E13 -> 9.0201497 | M13: =B12*EXP(RATES!O14)*(DATA!$B$12) -> 1174.7979 | N13: =C12*EXP(RATES!O14)*(DATA!$B$12) -> 220.2746 | O13: =M13+N13 -> 1395.0725 | P13: =O13*E13*F13 -> 206.46137 | Q13: =RATES!G14 -> 0.76320888 | R13: =P13+L13+K13+J13+I13 -> 3061.924 | S13: =R13*Q13 -> 2336.8876 | T13: =C12*EXP(RATES!O14)*(DATA!$B$6-DATA!$B$12) -> 125.8712 | U13: =B12*EXP(RATES!O14)*(DATA!$B$6-DATA!$B$12) -> 671.31308 | V13: =T13+U13 -> 797.18428 | W13: =V13*E13*F13 -> 117.97792
A14: 12 | B14: =B13*EXP(RATES!O15)*(1-DATA!$B$6) -> 82258.657 | C14: =C13*EXP(RATES!O15)*(1-DATA!$B$6) -> 15423.498 | D14: =B14+C14 -> 97682.155 | E14: =E13*(1-'LIFE TABLE MALE'!D74/1000) -> 0.86691444 | F14: =F13*(1-0.15) -> 0.14224176 | G14: =D14-20 -> 97662.155 | H14: =MAX(D14,$B$2+$C$2) -> 97682.155 | I14: =G14*DATA!$B$7*F13*E14 -> 2125.2106 | J14: =H14*'LIFE TABLE MALE'!D74/1000*F13*E13 -> 285.331 | K14: =0 -> 0 | L14: =DATA!$B$8*((1+DATA!$B$9)^A13)*F14*E14 -> 7.6661134 | M14: =B13*EXP(RATES!O15)*(DATA!$B$12) -> 1177.5268 | N14: =C13*EXP(RATES!O15)*(DATA!$B$12) -> 220.78627 | O14: =M14+N14 -> 1398.3131 | P14: =O14*E14*F14 -> 172.42799 | Q14: =RATES!G15 -> 0.74468847 | R14: =P14+L14+K14+J14+I14 -> 2590.6357 | S14: =R14*Q14 -> 1929.2166 | T14: =C13*EXP(RATES!O15)*(DATA!$B$6-DATA!$B$12) -> 126.16358 | U14: =B13*EXP(RATES!O15)*(DATA!$B$6-DATA!$B$12) -> 672.87245 | V14: =T14+U14 -> 799.03603 | W14: =V14*E14*F14 -> 98.530278
... A51: 49 | B51: =B50*EXP(RATES!O52)*(1-DATA!$B$6) -> 102111.48 | C51: =C50*EXP(RATES!O52)*(1-DATA!$B$6) -> 19145.902 | D51: =B51+C51 -> 121257.38 | E51: =E50*(1-'LIFE TABLE MALE'!D111/1000) -> 2.6221013e-06 | F51: =F50*(1-0.15) -> 0.00034795843 | G51: =D51-20 -> 121237.38 | H51: =MAX(D51,$B$2+$C$2) -> 121257.38 | I51: =G51*DATA!$B$7*F50*E51 -> 1.9520264e-05 | J51: =H51*'LIFE TABLE MALE'!D111/1000*F50*E50 -> 0.00032049145 | K51: =0 -> 0 | L51: =DATA!$B$8*((1+DATA!$B$9)^A50)*F51*E51 -> 1.1801985e-07 | M51: =B50*EXP(RATES!O52)*(DATA!$B$12) -> 1461.7185 | N51: =C50*EXP(RATES!O52)*(DATA!$B$12) -> 274.07221 | O51: =M51+N51 -> 1735.7907 | P51: =O51*E51*F51 -> 1.5837046e-06 | Q51: =RATES!G52 -> 0.26340215 | R51: =P51+L51+K51+J51+I51 -> 0.00034171344 | S51: =R51*Q51 -> 9.0008054e-05 | T51: =C50*EXP(RATES!O52)*(DATA!$B$6-DATA!$B$12) -> 156.61269 | U51: =B50*EXP(RATES!O52)*(DATA!$B$6-DATA!$B$12) -> 835.2677 | V51: =T51+U51 -> 991.88039 | W51: =V51*E51*F51 -> 9.0497406e-07
A52: 50 | B52: =B51*EXP(RATES!O53)*(1-DATA!$B$6) -> 103172 | C52: =C51*EXP(RATES!O53)*(1-DATA!$B$6) -> 19344.75 | D52: =B52+C52 -> 122516.75 | E52: =E51*(1-'LIFE TABLE MALE'!D112/1000) -> 6.7948871e-07 | F52: =F51*(1-0.15) -> 0.00029576466 | G52: =D52-20 -> 122496.75 | H52: =MAX(D52,$B$2+$C$2) -> 122516.75 | I52: =G52*DATA!$B$7*F51*E52 -> 4.3443562e-06 | J52: =H52*'LIFE TABLE MALE'!D112/1000*F51*E51 -> 8.2815004e-05 | K52: =E52*D52*F52 -> 2.4622038e-05 | L52: =DATA!$B$8*((1+DATA!$B$9)^A51)*F52*E52 -> 2.6515935e-08 | M52: =B51*EXP(RATES!O53)*(DATA!$B$12) -> 1476.8998 | N52: =C51*EXP(RATES!O53)*(DATA!$B$12) -> 276.91871 | O52: =M52+N52 -> 1753.8185 | P52: =O52*E52*F52 -> 3.5246271e-07 | Q52: =RATES!G53 -> 0.25495931 | R52: =P52+L52+K52+J52+I52 -> 0.00011216038 | S52: =R52*Q52 -> 2.8596332e-05 | T52: =C51*EXP(RATES!O53)*(DATA!$B$6-DATA!$B$12) -> 158.23926 | U52: =B51*EXP(RATES!O53)*(DATA!$B$6-DATA!$B$12) -> 843.94273 | V52: =T52+U52 -> 1002.182 | W52: =V52*E52*F52 -> 2.0140726e-07
P56: LIABILITIES | Q56: =SUM(S3:S52) -> 89780.518 | T56: BEL COMPONENTS
P57: BOF | Q57: =$B$2+$C$2-Q56 -> 5219.4825 | T57: DEATH | U57: =SUMPRODUCT(J3:J52,Q3:Q52) -> 6107.1947
T58: LAPSE | U58: =SUMPRODUCT(I3:I52,Q3:Q52) -> 77164.947
P59: DURATION | Q59: =SUMPRODUCT(S3:S52,A3:A52)/SUM(S3:S52) -> 5.6130992 | T59: EXPENSES | U59: =SUMPRODUCT(L3:L52,Q3:Q52) -> 247.61987
T60: COMMISSIONS | U60: =SUMPRODUCT(P3:P52,Q3:Q52) -> 6260.7561

Sheet IR UP 
B1: EQUITY | C1: PROPERTY | D1: ASSET | E1: SURVIVAL PROB | F1: non LAPSE PROB | G1: C lapse | H1: C death | I1: LIAB LAPSE | J1: LIAB DEATH | K1: LIAB SURVIVE | L1: EXPENSES | M1: EQ COMMISSIONS | N1: PR COMMISSIONS | O1: TOT COMMISSIONS | P1: COMMISSIONS LIAB | Q1: DISCOUNTS | R1: TOT LIAB | S1: TOT LIAB DISC | T1: PROFIT PR | U1: PROFIT EQ | V1: TOT PROFIT | W1: PROFIT LIAB
A2: 0 | B2: =DATA!B2*0.8 -> 80000 | C2: =DATA!B2*0.2 -> 20000 | D2: =B2+C2 -> 100000 | E2: =1 -> 1 | F2: =1 -> 1 | G2: =D2-20 -> 99980 | H2: =MAX(D2,DATA!$B$3) -> 100000 | M2: =B2 -> 80000 | N2: =C2 -> 20000 | Q2: =RATES!G3 -> 1
A3: 1 | B3: =B2*EXP(RATES!P4)*(1-DATA!$B$6) -> 82914.058 | C3: =C2*EXP(RATES!P4)*(1-DATA!$B$6) -> 20728.514 | D3: =B3+C3 -> 103642.57 | E3: =E2*(1-'LIFE TABLE MALE'!D63/1000) -> 0.99353213 | F3: =F2*(1-0.15) -> 0.85 | G3: =D3-20 -> 103622.57 | H3: =MAX(D3,DATA!$B$3) -> 103642.57 | I3: =G3*DATA!$B$7*F2*E3 -> 15442.853 | J3: =H3*'LIFE TABLE MALE'!D63/1000*F2*E2 -> 670.34668 | K3: =0 -> 0 | L3: =DATA!$B$8*((1+DATA!$B$9)^A2)*F3*E3 -> 42.225116 | M3: =B2*EXP(RATES!P4)*(DATA!$B$12) -> 1186.9088 | N3: =C2*EXP(RATES!P4)*(DATA!$B$12) -> 296.7272 | O3: =M3+N3 -> 1483.636 | P3: =O3*E3*F3 -> 1252.934 | Q3: =RATES!H4 -> 0.94362768 | R3: =P3+L3+K3+J3+I3 -> 17408.359 | S3: =R3*Q3 -> 16427.009 | T3: =C2*EXP(RATES!P4)*(DATA!$B$6-DATA!$B$12) -> 169.5584 | U3: =B2*EXP(RATES!P4)*(DATA!$B$6-DATA!$B$12) -> 678.2336 | V3: =T3+U3 -> 847.792 | W3: =V3*E3*F3 -> 715.9623
A4: 2 | B4: =B3*EXP(RATES!P5)*(1-DATA!$B$6) -> 84619.188 | C4: =C3*EXP(RATES!P5)*(1-DATA!$B$6) -> 21154.797 | D4: =B4+C4 -> 105773.98 | E4: =E3*(1-'LIFE TABLE MALE'!D64/1000) -> 0.98647779 | F4: =F3*(1-0.15) -> 0.7225 | G4: =D4-20 -> 105753.98 | H4: =MAX(D4,DATA!$B$3) -> 105773.98 | I4: =G4*DATA!$B$7*F3*E4 -> 13301.305 | J4: =H4*'LIFE TABLE MALE'!D64/1000*F3*E3 -> 634.24048 | K4: =0 -> 0 | L4: =DATA!$B$8*((1+DATA!$B$9)^A3)*F4*E4 -> 36.34924 | M4: =B3*EXP(RATES!P5)*(DATA!$B$12) -> 1211.3176 | N4: =C3*EXP(RATES!P5)*(DATA!$B$12) -> 302.8294 | O4: =M4+N4 -> 1514.147 | P4: =O4*E4*F4 -> 1079.1783 | Q4: =RATES!H5 -> 0.9042715 | R4: =P4+L4+K4+J4+I4 -> 15051.073 | S4: =R4*Q4 -> 13610.256 | T4: =C3*EXP(RATES!P5)*(DATA!$B$6-DATA!$B$12) -> 173.04537 | U4: =B3*EXP(RATES!P5)*(DATA!$B$6-DATA!$B$12) -> 692.18149 | V4: =T4+U4 -> 865.22687 | W4: =V4*E4*F4 -> 616.67332
A5: 3 | B5: =B4*EXP(RATES!P6)*(1-DATA!$B$6) -> 85556.521 | C5: =C4*EXP(RATES!P6)*(1-DATA!$B$6) -> 21389.13 | D5: =B5+C5 -> 106945.65 | E5: =E4*(1-'LIFE TABLE MALE'!D65/1000) -> 0.97876837 | F5: =F4*(1-0.15) -> 0.614125 | G5: =D5-20 -> 106925.65 | H5: =MAX(D5,DATA!$B$3) -> 106945.65 | I5: =G5*DATA!$B$7*F4*E5 -> 11342.034 | J5: =H5*'LIFE TABLE MALE'!D65/1000*F4*E4 -> 595.69346 | K5: =0 -> 0 | L5: =DATA!$B$8*((1+DATA!$B$9)^A4)*F5*E5 -> 31.2685 | M5: =B4*EXP(RATES!P6)*(DATA!$B$12) -> 1224.7355 | N5: =C4*EXP(RATES!P6)*(DATA!$B$12) -> 306.18387 | O5: =M5+N5 -> 1530.9193 | P5: =O5*E5*F5 -> 920.21438 | Q5: =RATES!H6 -> 0.87468854 | R5: =P5+L5+K5+J5+I5 -> 12889.21 | S5: =R5*Q5 -> 11274.044 | T5: =C4*EXP(RATES!P6)*(DATA!$B$6-DATA!$B$12) -> 174.96221 | U5: =B4*EXP(RATES!P6)*(DATA!$B$6-DATA!$B$12) -> 699.84884 | V5: =T5+U5 -> 874.81105 | W5: =V5*E5*F5 -> 525.83679
A6: 4 | B6: =B5*EXP(RATES!P7)*(1-DATA!$B$6) -> 86258.038 | C6: =C5*EXP(RATES!P7)*(1-DATA!$B$6) -> 21564.51 | D6: =B6+C6 -> 107822.55 | E6: =E5*(1-'LIFE TABLE MALE'!D66/1000) -> 0.97028747 | F6: =F5*(1-0.15) -> 0.52200625 | G6: =D6-20 -> 107802.55 | H6: =MAX(D6,DATA!$B$3) -> 107822.55 | I6: =G6*DATA!$B$7*F5*E6 -> 9635.5716 | J6: =H6*'LIFE TABLE MALE'!D66/1000*F5*E5 -> 561.57575 | K6: =0 -> 0 | L6: =DATA!$B$8*((1+DATA!$B$9)^A5)*F6*E6 -> 26.874887 | M6: =B5*EXP(RATES!P7)*(DATA!$B$12) -> 1234.7776 | N6: =C5*EXP(RATES!P7)*(DATA!$B$12) -> 308.69441 | O6: =M6+N6 -> 1543.4721 | P6: =O6*E6*F6 -> 781.76261 | Q6: =RATES!H7 -> 0.84848824 | R6: =P6+L6+K6+J6+I6 -> 11005.785 | S6: =R6*Q6 -> 9338.2791 | T6: =C5*EXP(RATES!P7)*(DATA!$B$6-DATA!$B$12) -> 176.39681 | U6: =B5*EXP(RATES!P7)*(DATA!$B$6-DATA!$B$12) -> 705.58723 | V6: =T6+U6 -> 881.98403 | W6: =V6*E6*F6 -> 446.72149
A7: 5 | B7: =B6*EXP(RATES!P8)*(1-DATA!$B$6) -> 86881.562 | C7: =C6*EXP(RATES!P8)*(1-DATA!$B$6) -> 21720.39 | D7: =B7+C7 -> 108601.95 | E7: =E6*(1-'LIFE TABLE MALE'!D67/1000) -> 0.96092158 | F7: =F6*(1-0.15) -> 0.44370531 | G7: =D7-20 -> 108581.95 | H7: =MAX(D7,DATA!$B$3) -> 108601.95 | I7: =G7*DATA!$B$7*F6*E7 -> 8169.8212 | J7: =H7*'LIFE TABLE MALE'!D67/1000*F6*E6 -> 530.96093 | K7: =0 -> 0 | L7: =DATA!$B$8*((1+DATA!$B$9)^A6)*F7*E7 -> 23.075614 | M7: =B6*EXP(RATES!P8)*(DATA!$B$12) -> 1243.7033 | N7: =C6*EXP(RATES!P8)*(DATA!$B$12) -> 310.92583 | O7: =M7+N7 -> 1554.6292 | P7: =O7*E7*F7 -> 662.84103 | Q7: =RATES!H8 -> 0.82386612 | R7: =P7+L7+K7+J7+I7 -> 9386.6988 | S7: =R7*Q7 -> 7733.3831 | T7: =C6*EXP(RATES!P8)*(DATA!$B$6-DATA!$B$12) -> 177.67191 | U7: =B6*EXP(RATES!P8)*(DATA!$B$6-DATA!$B$12) -> 710.68762 | V7: =T7+U7 -> 888.35953 | W7: =V7*E7*F7 -> 378.76631
A8: 6 | B8: =B7*EXP(RATES!P9)*(1-DATA!$B$6) -> 87575.484 | C8: =C7*EXP(RATES!P9)*(1-DATA!$B$6) -> 21893.871 | D8: =B8+C8 -> 109469.36 | E8: =E7*(1-'LIFE TABLE MALE'!D68/1000) -> 0.95054817 | F8: =F7*(1-0.15) -> 0.37714952 | G8: =D8-20 -> 109449.36 | H8: =MAX(D8,DATA!$B$3) -> 109469.36 | I8: =G8*DATA!$B$7*F7*E8 -> 6924.2577 | J8: =H8*'LIFE TABLE MALE'!D68/1000*F7*E7 -> 503.85856 | K8: =0 -> 0 | L8: =DATA!$B$8*((1+DATA!$B$9)^A7)*F8*E8 -> 19.790581 | M8: =B7*EXP(RATES!P9)*(DATA!$B$12) -> 1253.6368 | N8: =C7*EXP(RATES!P9)*(DATA!$B$12) -> 313.4092 | O8: =M8+N8 -> 1567.046 | P8: =O8*E8*F8 -> 561.78408 | Q8: =RATES!H9 -> 0.79935661 | R8: =P8+L8+K8+J8+I8 -> 8009.6909 | S8: =R8*Q8 -> 6402.5994 | T8: =C7*EXP(RATES!P9)*(DATA!$B$6-DATA!$B$12) -> 179.09097 | U8: =B7*EXP(RATES!P9)*(DATA!$B$6-DATA!$B$12) -> 716.36388 | V8: =T8+U8 -> 895.45485 | W8: =V8*E8*F8 -> 321.01947
A9: 7 | B9: =B8*EXP(RATES!P10)*(1-DATA!$B$6) -> 88236.731 | C9: =C8*EXP(RATES!P10)*(1-DATA!$B$6) -> 22059.183 | D9: =B9+C9 -> 110295.91 | E9: =E8*(1-'LIFE TABLE MALE'!D69/1000) -> 0.93939989 | F9: =F8*(1-0.15) -> 0.32057709 | G9: =D9-20 -> 110275.91 | H9: =MAX(D9,DATA!$B$3) -> 110295.91 | I9: =G9*DATA!$B$7*F8*E9 -> 5860.5177 | J9: =H9*'LIFE TABLE MALE'!D69/1000*F8*E8 -> 463.74655 | K9: =0 -> 0 | L9: =DATA!$B$8*((1+DATA!$B$9)^A8)*F9*E9 -> 16.957195 | M9: =B8*EXP(RATES!P10)*(DATA!$B$12) -> 1263.1025 | N9: =C8*EXP(RATES!P10)*(DATA!$B$12) -> 315.77562 | O9: =M9+N9 -> 1578.8781 | P9: =O9*E9*F9 -> 475.47927 | Q9: =RATES!H10 -> 0.77591216 | R9: =P9+L9+K9+J9+I9 -> 6816.7008 | S9: =R9*Q9 -> 5289.161 | T9: =C8*EXP(RATES!P10)*(DATA!$B$6-DATA!$B$12) -> 180.44321 | U9: =B8*EXP(RATES!P10)*(DATA!$B$6-DATA!$B$12) -> 721.77285 | V9: =T9+U9 -> 902.21606 | W9: =V9*E9*F9 -> 271.70244
A10: 8 | B10: =B9*EXP(RATES!P11)*(1-DATA!$B$6) -> 89026.064 | C10: =C9*EXP(RATES!P11)*(1-DATA!$B$6) -> 22256.516 | D10: =B10+C10 -> 111282.58 | E10: =E9*(1-'LIFE TABLE MALE'!D70/1000) -> 0.92737751 | F10: =F9*(1-0.15) -> 0.27249053 | G10: =D10-20 -> 111262.58 | H10: =MAX(D10,DATA!$B$3) -> 111282.58 | I10: =G10*DATA!$B$7*F9*E10 -> 4961.6877 | J10: =H10*'LIFE TABLE MALE'!D70/1000*F9*E9 -> 428.89427 | K10: =0 -> 0 | L10: =DATA!$B$8*((1+DATA!$B$9)^A9)*F10*E10 -> 14.513734 | M10: =B9*EXP(RATES!P11)*(DATA!$B$12) -> 1274.4017 | N10: =C9*EXP(RATES!P11)*(DATA!$B$12) -> 318.60043 | O10: =M10+N10 -> 1593.0022 | P10: =O10*E10*F10 -> 402.55417 | Q10: =RATES!H11 -> 0.75211396 | R10: =P10+L10+K10+J10+I10 -> 5807.6499 | S10: =R10*Q10 -> 4368.0146 | T10: =C9*EXP(RATES!P11)*(DATA!$B$6-DATA!$B$12) -> 182.05739 | U10: =B9*EXP(RATES!P11)*(DATA!$B$6-DATA!$B$12) -> 728.22956 | V10: =T10+U10 -> 910.28695 | W10: =V10*E10*F10 -> 230.03096
A11: 9 | B11: =B10*EXP(RATES!P12)*(1-DATA!$B$6) -> 89622.1 | C11: =C10*EXP(RATES!P12)*(1-DATA!$B$6) -> 22405.525 | D11: =B11+C11 -> 112027.62 | E11: =E10*(1-'LIFE TABLE MALE'!D71/1000) -> 0.91441742 | F11: =F10*(1-0.15) -> 0.23161695 | G11: =D11-20 -> 112007.62 | H11: =MAX(D11,DATA!$B$3) -> 112027.62 | I11: =G11*DATA!$B$7*F10*E11 -> 4186.3424 | J11: =H11*'LIFE TABLE MALE'!D71/1000*F10*E10 -> 395.62579 | K11: =0 -> 0 | L11: =DATA!$B$8*((1+DATA!$B$9)^A10)*F11*E11 -> 12.407555 | M11: =B10*EXP(RATES!P12)*(DATA!$B$12) -> 1282.9339 | N11: =C10*EXP(RATES!P12)*(DATA!$B$12) -> 320.73349 | O11: =M11+N11 -> 1603.6674 | P11: =O11*E11*F11 -> 339.64805 | Q11: =RATES!H12 -> 0.73067553 | R11: =P11+L11+K11+J11+I11 -> 4934.0238 | S11: =R11*Q11 -> 3605.1704 | T11: =C10*EXP(RATES!P12)*(DATA!$B$6-DATA!$B$12) -> 183.27628 | U11: =B10*EXP(RATES!P12)*(DATA!$B$6-DATA!$B$12) -> 733.10511 | V11: =T11+U11 -> 916.38139 | W11: =V11*E11*F11 -> 194.0846
A12: 10 | B12: =B11*EXP(RATES!P13)*(1-DATA!$B$6) -> 90401.523 | C12: =C11*EXP(RATES!P13)*(1-DATA!$B$6) -> 22600.381 | D12: =B12+C12 -> 113001.9 | E12: =E11*(1-'LIFE TABLE MALE'!D72/1000) -> 0.9000976 | F12: =F11*(1-0.15) -> 0.1968744 | G12: =D12-20 -> 112981.9 | H12: =MAX(D12,DATA!$B$3) -> 113001.9 | I12: =G12*DATA!$B$7*F11*E12 -> 3533.1338 | J12: =H12*'LIFE TABLE MALE'!D72/1000*F11*E11 -> 374.79495 | K12: =0 -> 0 | L12: =DATA!$B$8*((1+DATA!$B$9)^A11)*F12*E12 -> 10.588889 | M12: =B11*EXP(RATES!P13)*(DATA!$B$12) -> 1294.0913 | N12: =C11*EXP(RATES!P13)*(DATA!$B$12) -> 323.52283 | O12: =M12+N12 -> 1617.6142 | P12: =O12*E12*F12 -> 286.65122 | Q12: =RATES!H13 -> 0.70843953 | R12: =P12+L12+K12+J12+I12 -> 4205.1688 | S12: =R12*Q12 -> 2979.1078 | T12: =C11*EXP(RATES!P13)*(DATA!$B$6-DATA!$B$12) -> 184.87019 | U12: =B11*EXP(RATES!P13)*(DATA!$B$6-DATA!$B$12) -> 739.48076 | V12: =T12+U12 -> 924.35095 | W12: =V12*E12*F12 -> 163.8007
A13: 11 | B13: =B12*EXP(RATES!P14)*(1-DATA!$B$6) -> 91319.003 | C13: =C12*EXP(RATES!P14)*(1-DATA!$B$6) -> 22829.751 | D13: =B13+C13 -> 114148.75 | E13: =E12*(1-'LIFE TABLE MALE'!D73/1000) -> 0.88436967 | F13: =F12*(1-0.15) -> 0.16734324 | G13: =D13-20 -> 114128.75 | H13: =MAX(D13,DATA!$B$3) -> 114148.75 | I13: =G13*DATA!$B$7*F12*E13 -> 2980.6393 | J13: =H13*'LIFE TABLE MALE'!D73/1000*F12*E12 -> 353.45321 | K13: =0 -> 0 | L13: =DATA!$B$8*((1+DATA!$B$9)^A12)*F13*E13 -> 9.0201497 | M13: =B12*EXP(RATES!P14)*(DATA!$B$12) -> 1307.225 | N13: =C12*EXP(RATES!P14)*(DATA!$B$12) -> 326.80625 | O13: =M13+N13 -> 1634.0312 | P13: =O13*E13*F13 -> 241.82566 | Q13: =RATES!H14 -> 0.68589278 | R13: =P13+L13+K13+J13+I13 -> 3584.9383 | S13: =R13*Q13 -> 2458.8833 | T13: =C12*EXP(RATES!P14)*(DATA!$B$6-DATA!$B$12) -> 186.74643 | U13: =B12*EXP(RATES!P14)*(DATA!$B$6-DATA!$B$12) -> 746.98571 | V13: =T13+U13 -> 933.73213 | W13: =V13*E13*F13 -> 138.18609
A14: 12 | B14: =B13*EXP(RATES!P15)*(1-DATA!$B$6) -> 92424.224 | C14: =C13*EXP(RATES!P15)*(1-DATA!$B$6) -> 23106.056 | D14: =B14+C14 -> 115530.28 | E14: =E13*(1-'LIFE TABLE MALE'!D74/1000) -> 0.86691444 | F14: =F13*(1-0.15) -> 0.14224176 | G14: =D14-20 -> 115510.28 | H14: =MAX(D14,DATA!$B$3) -> 115530.28 | I14: =G14*DATA!$B$7*F13*E14 -> 2513.6008 | J14: =H14*'LIFE TABLE MALE'!D74/1000*F13*E13 -> 337.46563 | K14: =0 -> 0 | L14: =DATA!$B$8*((1+DATA!$B$9)^A13)*F14*E14 -> 7.6661134 | M14: =B13*EXP(RATES!P15)*(DATA!$B$12) -> 1323.0461 | N14: =C13*EXP(RATES!P15)*(DATA!$B$12) -> 330.76154 | O14: =M14+N14 -> 1653.8077 | P14: =O14*E14*F14 -> 203.9334 | Q14: =RATES!H15 -> 0.66278158 | R14: =P14+L14+K14+J14+I14 -> 3062.666 | S14: =R14*Q14 -> 2029.8786 | T14: =C13*EXP(RATES!P15)*(DATA!$B$6-DATA!$B$12) -> 189.00659 | U14: =B13*EXP(RATES!P15)*(DATA!$B$6-DATA!$B$12) -> 756.02637 | V14: =T14+U14 -> 945.03296 | W14: =V14*E14*F14 -> 116.53337
... A51: 49 | B51: =B50*EXP(RATES!P52)*(1-DATA!$B$6) -> 164120.21 | C51: =C50*EXP(RATES!P52)*(1-DATA!$B$6) -> 41030.052 | D51: =B51+C51 -> 205150.26 | E51: =E50*(1-'LIFE TABLE MALE'!D111/1000) -> 2.6221013e-06 | F51: =F50*(1-0.15) -> 0.00034795843 | G51: =D51-20 -> 205130.26 | H51: =MAX(D51,DATA!$B$3) -> 205150.26 | I51: =G51*DATA!$B$7*F50*E51 -> 3.3027743e-05 | J51: =H51*'LIFE TABLE MALE'!D111/1000*F50*E50 -> 0.00054222601 | K51: =0 -> 0 | L51: =DATA!$B$8*((1+DATA!$B$9)^A50)*F51*E51 -> 1.1801985e-07 | M51: =B50*EXP(RATES!P52)*(DATA!$B$12) -> 2349.3691 | N51: =C50*EXP(RATES!P52)*(DATA!$B$12) -> 587.34226 | O51: =M51+N51 -> 2936.7113 | P51: =O51*E51*F51 -> 2.6794033e-06 | Q51: =RATES!H52 -> 0.16388221 | R51: =P51+L51+K51+J51+I51 -> 0.00057805117 | S51: =R51*Q51 -> 9.4732303e-05 | T51: =C50*EXP(RATES!P52)*(DATA!$B$6-DATA!$B$12) -> 335.62415 | U51: =B50*EXP(RATES!P52)*(DATA!$B$6-DATA!$B$12) -> 1342.4966 | V51: =T51+U51 -> 1678.1208 | W51: =V51*E51*F51 -> 1.5310876e-06
A52: 50 | B52: =B51*EXP(RATES!P53)*(1-DATA!$B$6) -> 167429.82 | C52: =C51*EXP(RATES!P53)*(1-DATA!$B$6) -> 41857.456 | D52: =B52+C52 -> 209287.28 | E52: =E51*(1-'LIFE TABLE MALE'!D112/1000) -> 6.7948871e-07 | F52: =F51*(1-0.15) -> 0.00029576466 | G52: =D52-20 -> 209267.28 | H52: =MAX(D52,DATA!$B$3) -> 209287.28 | I52: =G52*DATA!$B$7*F51*E52 -> 7.4216795e-06 | J52: =H52*'LIFE TABLE MALE'!D112/1000*F51*E51 -> 0.00014146741 | K52: =E52*D52*F52 -> 4.2060203e-05 | L52: =DATA!$B$8*((1+DATA!$B$9)^A51)*F52*E52 -> 2.6515935e-08 | M52: =B51*EXP(RATES!P53)*(DATA!$B$12) -> 2396.7459 | N52: =C51*EXP(RATES!P53)*(DATA!$B$12) -> 599.18649 | O52: =M52+N52 -> 2995.9324 | P52: =O52*E52*F52 -> 6.020888e-07 | Q52: =RATES!H53 -> 0.15710858 | R52: =P52+L52+K52+J52+I52 -> 0.00019157789 | S52: =R52*Q52 -> 3.0098531e-05 | T52: =C51*EXP(RATES!P53)*(DATA!$B$6-DATA!$B$12) -> 342.39228 | U52: =B51*EXP(RATES!P53)*(DATA!$B$6-DATA!$B$12) -> 1369.5691 | V52: =T52+U52 -> 1711.9614 | W52: =V52*E52*F52 -> 3.4405074e-07
P56: LIABILITIES | Q56: =SUM(S3:S52) -> 94477.93 | T56: BEL COMPONENTS
P57: BOF | Q57: =DATA!B2-Q56 -> 5522.0696 | T57: DEATH | U57: =SUMPRODUCT(J3:J52,Q3:Q52) -> 6428.626
T58: LAPSE | U58: =SUMPRODUCT(I3:I52,Q3:Q52) -> 81228.124
P59: DURATION | Q59: =SUMPRODUCT(S3:S52,A3:A52)/SUM(S3:S52) -> 5.6125887 | T59: EXPENSES | U59: =SUMPRODUCT(L3:L52,Q3:Q52) -> 230.91047
T60: COMMISSIONS | U60: =SUMPRODUCT(P3:P52,Q3:Q52) -> 6590.2696

Sheet IR DOWN 
B1: EQUITY | C1: PROPERTY | D1: ASSET | E1: SURVIVAL PROB | F1: non LAPSE PROB | G1: C lapse | H1: C death | I1: LIAB LAPSE | J1: LIAB DEATH | K1: LIAB SURVIVE | L1: EXPENSES | M1: EQ COMMISSIONS | N1: PR COMMISSIONS | O1: TOT COMMISSIONS | P1: COMMISSIONS LIAB | Q1: DISCOUNTS | R1: TOT LIAB | S1: TOT LIAB DISC | T1: PROFIT PR | U1: PROFIT EQ | V1: TOT PROFIT | W1: PROFIT LIAB
A2: 0 | B2: =DATA!B2*0.8 -> 80000 | C2: =DATA!B2*0.2 -> 20000 | D2: =B2+C2 -> 100000 | E2: =1 -> 1 | F2: =1 -> 1 | G2: =D2-20 -> 99980 | H2: =MAX(D2,DATA!$B$3) -> 100000 | M2: =B2 -> 80000 | N2: =C2 -> 20000 | Q2: =RATES!G3 -> 1
A3: 1 | B3: =B2*EXP(RATES!Q4)*(1-DATA!$B$6) -> 78927.73 | C3: =C2*EXP(RATES!Q4)*(1-DATA!$B$6) -> 19731.932 | D3: =B3+C3 -> 98659.662 | E3: =E2*(1-'LIFE TABLE MALE'!D63/1000) -> 0.99353213 | F3: =F2*(1-0.15) -> 0.85 | G3: =D3-20 -> 98639.662 | H3: =MAX(D3,DATA!$B$3) -> 100000 | I3: =G3*DATA!$B$7*F2*E3 -> 14700.251 | J3: =H3*'LIFE TABLE MALE'!D63/1000*F2*E2 -> 646.787 | K3: =0 -> 0 | L3: =DATA!$B$8*((1+DATA!$B$9)^A2)*F3*E3 -> 42.225116 | M3: =B2*EXP(RATES!Q4)*(DATA!$B$12) -> 1129.8448 | N3: =C2*EXP(RATES!Q4)*(DATA!$B$12) -> 282.4612 | O3: =M3+N3 -> 1412.306 | P3: =O3*E3*F3 -> 1192.6957 | Q3: =RATES!I4 -> 0.99128659 | R3: =P3+L3+K3+J3+I3 -> 16581.959 | S3: =R3*Q3 -> 16437.473 | T3: =C2*EXP(RATES!Q4)*(DATA!$B$6-DATA!$B$12) -> 161.4064 | U3: =B2*EXP(RATES!Q4)*(DATA!$B$6-DATA!$B$12) -> 645.6256 | V3: =T3+U3 -> 807.032 | W3: =V3*E3*F3 -> 681.54039
A4: 2 | B4: =B3*EXP(RATES!Q5)*(1-DATA!$B$6) -> 78152.608 | C4: =C3*EXP(RATES!Q5)*(1-DATA!$B$6) -> 19538.152 | D4: =B4+C4 -> 97690.76 | E4: =E3*(1-'LIFE TABLE MALE'!D64/1000) -> 0.98647779 | F4: =F3*(1-0.15) -> 0.7225 | G4: =D4-20 -> 97670.76 | H4: =MAX(D4,DATA!$B$3) -> 100000 | I4: =G4*DATA!$B$7*F3*E4 -> 12284.63 | J4: =H4*'LIFE TABLE MALE'!D64/1000*F3*E3 -> 599.6186 | K4: =0 -> 0 | L4: =DATA!$B$8*((1+DATA!$B$9)^A3)*F4*E4 -> 36.34924 | M4: =B3*EXP(RATES!Q5)*(DATA!$B$12) -> 1118.749 | N4: =C3*EXP(RATES!Q5)*(DATA!$B$12) -> 279.68725 | O4: =M4+N4 -> 1398.4362 | P4: =O4*E4*F4 -> 996.70774 | Q4: =RATES!I5 -> 0.97909362 | R4: =P4+L4+K4+J4+I4 -> 13917.305 | S4: =R4*Q4 -> 13626.345 | T4: =C3*EXP(RATES!Q5)*(DATA!$B$6-DATA!$B$12) -> 159.82128 | U4: =B3*EXP(RATES!Q5)*(DATA!$B$6-DATA!$B$12) -> 639.28513 | V4: =T4+U4 -> 799.10642 | W4: =V4*E4*F4 -> 569.54728
A5: 3 | B5: =B4*EXP(RATES!Q6)*(1-DATA!$B$6) -> 77619.333 | C5: =C4*EXP(RATES!Q6)*(1-DATA!$B$6) -> 19404.833 | D5: =B5+C5 -> 97024.167 | E5: =E4*(1-'LIFE TABLE MALE'!D65/1000) -> 0.97876837 | F5: =F4*(1-0.15) -> 0.614125 | G5: =D5-20 -> 97004.167 | H5: =MAX(D5,DATA!$B$3) -> 100000 | I5: =G5*DATA!$B$7*F4*E5 -> 10289.622 | J5: =H5*'LIFE TABLE MALE'!D65/1000*F4*E4 -> 557.00578 | K5: =0 -> 0 | L5: =DATA!$B$8*((1+DATA!$B$9)^A4)*F5*E5 -> 31.2685 | M5: =B4*EXP(RATES!Q6)*(DATA!$B$12) -> 1111.1152 | N5: =C4*EXP(RATES!Q6)*(DATA!$B$12) -> 277.7788 | O5: =M5+N5 -> 1388.894 | P5: =O5*E5*F5 -> 834.84491 | Q5: =RATES!I6 -> 0.96413232 | R5: =P5+L5+K5+J5+I5 -> 11712.741 | S5: =R5*Q5 -> 11292.633 | T5: =C4*EXP(RATES!Q6)*(DATA!$B$6-DATA!$B$12) -> 158.73074 | U5: =B4*EXP(RATES!Q6)*(DATA!$B$6-DATA!$B$12) -> 634.92297 | V5: =T5+U5 -> 793.65371 | W5: =V5*E5*F5 -> 477.05424
A6: 4 | B6: =B5*EXP(RATES!Q7)*(1-DATA!$B$6) -> 77127.452 | C6: =C5*EXP(RATES!Q7)*(1-DATA!$B$6) -> 19281.863 | D6: =B6+C6 -> 96409.315 | E6: =E5*(1-'LIFE TABLE MALE'!D66/1000) -> 0.97028747 | F6: =F5*(1-0.15) -> 0.52200625 | G6: =D6-20 -> 96389.315 | H6: =MAX(D6,DATA!$B$3) -> 100000 | I6: =G6*DATA!$B$7*F5*E6 -> 8615.4379 | J6: =H6*'LIFE TABLE MALE'!D66/1000*F5*E5 -> 520.83331 | K6: =0 -> 0 | L6: =DATA!$B$8*((1+DATA!$B$9)^A5)*F6*E6 -> 26.874887 | M6: =B5*EXP(RATES!Q7)*(DATA!$B$12) -> 1104.074 | N6: =C5*EXP(RATES!Q7)*(DATA!$B$12) -> 276.01849 | O6: =M6+N6 -> 1380.0924 | P6: =O6*E6*F6 -> 699.01147 | Q6: =RATES!I7 -> 0.9489349 | R6: =P6+L6+K6+J6+I6 -> 9862.1575 | S6: =R6*Q6 -> 9358.5455 | T6: =C5*EXP(RATES!Q7)*(DATA!$B$6-DATA!$B$12) -> 157.72485 | U6: =B5*EXP(RATES!Q7)*(DATA!$B$6-DATA!$B$12) -> 630.8994 | V6: =T6+U6 -> 788.62426 | W6: =V6*E6*F6 -> 399.43513
A7: 5 | B7: =B6*EXP(RATES!Q8)*(1-DATA!$B$6) -> 76640.798 | C7: =C6*EXP(RATES!Q8)*(1-DATA!$B$6) -> 19160.199 | D7: =B7+C7 -> 95800.997 | E7: =E6*(1-'LIFE TABLE MALE'!D67/1000) -> 0.96092158 | F7: =F6*(1-0.15) -> 0.44370531 | G7: =D7-20 -> 95780.997 | H7: =MAX(D7,DATA!$B$3) -> 100000 | I7: =G7*DATA!$B$7*F6*E7 -> 7206.6638 | J7: =H7*'LIFE TABLE MALE'!D67/1000*F6*E6 -> 488.90551 | K7: =0 -> 0 | L7: =DATA!$B$8*((1+DATA!$B$9)^A6)*F7*E7 -> 23.075614 | M7: =B6*EXP(RATES!Q8)*(DATA!$B$12) -> 1097.1075 | N7: =C6*EXP(RATES!Q8)*(DATA!$B$12) -> 274.27688 | O7: =M7+N7 -> 1371.3844 | P7: =O7*E7*F7 -> 584.7117 | Q7: =RATES!I8 -> 0.93395133 | R7: =P7+L7+K7+J7+I7 -> 8303.3566 | S7: =R7*Q7 -> 7754.9309 | T7: =C6*EXP(RATES!Q8)*(DATA!$B$6-DATA!$B$12) -> 156.72965 | U7: =B6*EXP(RATES!Q8)*(DATA!$B$6-DATA!$B$12) -> 626.91859 | V7: =T7+U7 -> 783.64824 | W7: =V7*E7*F7 -> 334.12097
A8: 6 | B8: =B7*EXP(RATES!Q9)*(1-DATA!$B$6) -> 76323.998 | C8: =C7*EXP(RATES!Q9)*(1-DATA!$B$6) -> 19080.999 | D8: =B8+C8 -> 95404.997 | E8: =E7*(1-'LIFE TABLE MALE'!D68/1000) -> 0.95054817 | F8: =F7*(1-0.15) -> 0.37714952 | G8: =D8-20 -> 95384.997 | H8: =MAX(D8,DATA!$B$3) -> 100000 | I8: =G8*DATA!$B$7*F7*E8 -> 6034.4833 | J8: =H8*'LIFE TABLE MALE'!D68/1000*F7*E7 -> 460.27362 | K8: =0 -> 0 | L8: =DATA!$B$8*((1+DATA!$B$9)^A7)*F8*E8 -> 19.790581 | M8: =B7*EXP(RATES!Q9)*(DATA!$B$12) -> 1092.5726 | N8: =C7*EXP(RATES!Q9)*(DATA!$B$12) -> 273.14314 | O8: =M8+N8 -> 1365.7157 | P8: =O8*E8*F8 -> 489.60742 | Q8: =RATES!I9 -> 0.91719569 | R8: =P8+L8+K8+J8+I8 -> 7004.1549 | S8: =R8*Q8 -> 6424.1807 | T8: =C7*EXP(RATES!Q9)*(DATA!$B$6-DATA!$B$12) -> 156.08179 | U8: =B7*EXP(RATES!Q9)*(DATA!$B$6-DATA!$B$12) -> 624.32718 | V8: =T8+U8 -> 780.40897 | W8: =V8*E8*F8 -> 279.77567
A9: 7 | B9: =B8*EXP(RATES!Q10)*(1-DATA!$B$6) -> 76042.032 | C9: =C8*EXP(RATES!Q10)*(1-DATA!$B$6) -> 19010.508 | D9: =B9+C9 -> 95052.54 | E9: =E8*(1-'LIFE TABLE MALE'!D69/1000) -> 0.93939989 | F9: =F8*(1-0.15) -> 0.32057709 | G9: =D9-20 -> 95032.54 | H9: =MAX(D9,DATA!$B$3) -> 100000 | I9: =G9*DATA!$B$7*F8*E9 -> 5050.4219 | J9: =H9*'LIFE TABLE MALE'!D69/1000*F8*E8 -> 420.45669 | K9: =0 -> 0 | L9: =DATA!$B$8*((1+DATA!$B$9)^A8)*F9*E9 -> 16.957195 | M9: =B8*EXP(RATES!Q10)*(DATA!$B$12) -> 1088.5362 | N9: =C8*EXP(RATES!Q10)*(DATA!$B$12) -> 272.13406 | O9: =M9+N9 -> 1360.6703 | P9: =O9*E9*F9 -> 409.76597 | Q9: =RATES!I10 -> 0.90034355 | R9: =P9+L9+K9+J9+I9 -> 5897.6017 | S9: =R9*Q9 -> 5309.8677 | T9: =C8*EXP(RATES!Q10)*(DATA!$B$6-DATA!$B$12) -> 155.50518 | U9: =B8*EXP(RATES!Q10)*(DATA!$B$6-DATA!$B$12) -> 622.02071 | V9: =T9+U9 -> 777.52589 | W9: =V9*E9*F9 -> 234.15199
A10: 8 | B10: =B9*EXP(RATES!Q11)*(1-DATA!$B$6) -> 75892.365 | C10: =C9*EXP(RATES!Q11)*(1-DATA!$B$6) -> 18973.091 | D10: =B10+C10 -> 94865.456 | E10: =E9*(1-'LIFE TABLE MALE'!D70/1000) -> 0.92737751 | F10: =F9*(1-0.15) -> 0.27249053 | G10: =D10-20 -> 94845.456 | H10: =MAX(D10,DATA!$B$3) -> 100000 | I10: =G10*DATA!$B$7*F9*E10 -> 4229.5759 | J10: =H10*'LIFE TABLE MALE'!D70/1000*F9*E9 -> 385.41007 | K10: =0 -> 0 | L10: =DATA!$B$8*((1+DATA!$B$9)^A9)*F10*E10 -> 14.513734 | M10: =B9*EXP(RATES!Q11)*(DATA!$B$12) -> 1086.3938 | N10: =C9*EXP(RATES!Q11)*(DATA!$B$12) -> 271.59844 | O10: =M10+N10 -> 1357.9922 | P10: =O10*E10*F10 -> 343.16678 | Q10: =RATES!I11 -> 0.88227249 | R10: =P10+L10+K10+J10+I10 -> 4972.6665 | S10: =R10*Q10 -> 4387.2469 | T10: =C9*EXP(RATES!Q11)*(DATA!$B$6-DATA!$B$12) -> 155.19911 | U10: =B9*EXP(RATES!Q11)*(DATA!$B$6-DATA!$B$12) -> 620.79644 | V10: =T10+U10 -> 775.99555 | W10: =V10*E10*F10 -> 196.09531
A11: 9 | B11: =B10*EXP(RATES!Q12)*(1-DATA!$B$6) -> 75883.015 | C11: =C10*EXP(RATES!Q12)*(1-DATA!$B$6) -> 18970.754 | D11: =B11+C11 -> 94853.769 | E11: =E10*(1-'LIFE TABLE MALE'!D71/1000) -> 0.91441742 | F11: =F10*(1-0.15) -> 0.23161695 | G11: =D11-20 -> 94833.769 | H11: =MAX(D11,DATA!$B$3) -> 100000 | I11: =G11*DATA!$B$7*F10*E11 -> 3544.4607 | J11: =H11*'LIFE TABLE MALE'!D71/1000*F10*E10 -> 353.15021 | K11: =0 -> 0 | L11: =DATA!$B$8*((1+DATA!$B$9)^A10)*F11*E11 -> 12.407555 | M11: =B10*EXP(RATES!Q12)*(DATA!$B$12) -> 1086.2599 | N11: =C10*EXP(RATES!Q12)*(DATA!$B$12) -> 271.56498 | O11: =M11+N11 -> 1357.8249 | P11: =O11*E11*F11 -> 287.57994 | Q11: =RATES!I12 -> 0.86296881 | R11: =P11+L11+K11+J11+I11 -> 4197.5984 | S11: =R11*Q11 -> 3622.3965 | T11: =C10*EXP(RATES!Q12)*(DATA!$B$6-DATA!$B$12) -> 155.17999 | U11: =B10*EXP(RATES!Q12)*(DATA!$B$6-DATA!$B$12) -> 620.71996 | V11: =T11+U11 -> 775.89995 | W11: =V11*E11*F11 -> 164.3314
A12: 10 | B12: =B11*EXP(RATES!Q13)*(1-DATA!$B$6) -> 75833.111 | C12: =C11*EXP(RATES!Q13)*(1-DATA!$B$6) -> 18958.278 | D12: =B12+C12 -> 94791.389 | E12: =E11*(1-'LIFE TABLE MALE'!D72/1000) -> 0.9000976 | F12: =F11*(1-0.15) -> 0.1968744 | G12: =D12-20 -> 94771.389 | H12: =MAX(D12,DATA!$B$3) -> 100000 | I12: =G12*DATA!$B$7*F11*E12 -> 2963.6604 | J12: =H12*'LIFE TABLE MALE'!D72/1000*F11*E11 -> 331.67136 | K12: =0 -> 0 | L12: =DATA!$B$8*((1+DATA!$B$9)^A11)*F12*E12 -> 10.588889 | M12: =B11*EXP(RATES!Q13)*(DATA!$B$12) -> 1085.5456 | N12: =C11*EXP(RATES!Q13)*(DATA!$B$12) -> 271.38639 | O12: =M12+N12 -> 1356.932 | P12: =O12*E12*F12 -> 240.45672 | Q12: =RATES!I13 -> 0.8445389 | R12: =P12+L12+K12+J12+I12 -> 3546.3774 | S12: =R12*Q12 -> 2995.0537 | T12: =C11*EXP(RATES!Q13)*(DATA!$B$6-DATA!$B$12) -> 155.07794 | U12: =B11*EXP(RATES!Q13)*(DATA!$B$6-DATA!$B$12) -> 620.31175 | V12: =T12+U12 -> 775.38969 | W12: =V12*E12*F12 -> 137.40384
A13: 11 | B13: =B12*EXP(RATES!Q14)*(1-DATA!$B$6) -> 75730.951 | C13: =C12*EXP(RATES!Q14)*(1-DATA!$B$6) -> 18932.738 | D13: =B13+C13 -> 94663.689 | E13: =E12*(1-'LIFE TABLE MALE'!D73/1000) -> 0.88436967 | F13: =F12*(1-0.15) -> 0.16734324 | G13: =D13-20 -> 94643.689 | H13: =MAX(D13,DATA!$B$3) -> 100000 | I13: =G13*DATA!$B$7*F12*E13 -> 2471.7584 | J13: =H13*'LIFE TABLE MALE'!D73/1000*F12*E12 -> 309.64263 | K13: =0 -> 0 | L13: =DATA!$B$8*((1+DATA!$B$9)^A12)*F13*E13 -> 9.0201497 | M13: =B12*EXP(RATES!Q14)*(DATA!$B$12) -> 1084.0831 | N13: =C12*EXP(RATES!Q14)*(DATA!$B$12) -> 271.02079 | O13: =M13+N13 -> 1355.1039 | P13: =O13*E13*F13 -> 200.54629 | Q13: =RATES!I14 -> 0.82707326 | R13: =P13+L13+K13+J13+I13 -> 2990.9674 | S13: =R13*Q13 -> 2473.7492 | T13: =C12*EXP(RATES!Q14)*(DATA!$B$6-DATA!$B$12) -> 154.86902 | U13: =B12*EXP(RATES!Q14)*(DATA!$B$6-DATA!$B$12) -> 619.47608 | V13: =T13+U13 -> 774.3451 | W13: =V13*E13*F13 -> 114.59788
A14: 12 | B14: =B13*EXP(RATES!Q15)*(1-DATA!$B$6) -> 75576.835 | C14: =C13*EXP(RATES!Q15)*(1-DATA!$B$6) -> 18894.209 | D14: =B14+C14 -> 94471.043 | E14: =E13*(1-'LIFE TABLE MALE'!D74/1000) -> 0.86691444 | F14: =F13*(1-0.15) -> 0.14224176 | G14: =D14-20 -> 94451.043 | H14: =MAX(D14,DATA!$B$3) -> 100000 | I14: =G14*DATA!$B$7*F13*E14 -> 2055.3342 | J14: =H14*'LIFE TABLE MALE'!D74/1000*F13*E13 -> 292.10146 | K14: =0 -> 0 | L14: =DATA!$B$8*((1+DATA!$B$9)^A13)*F14*E14 -> 7.6661134 | M14: =B13*EXP(RATES!Q15)*(DATA!$B$12) -> 1081.877 | N14: =C13*EXP(RATES!Q15)*(DATA!$B$12) -> 270.46924 | O14: =M14+N14 -> 1352.3462 | P14: =O14*E14*F14 -> 166.75975 | Q14: =RATES!I15 -> 0.81052711 | R14: =P14+L14+K14+J14+I14 -> 2521.8615 | S14: =R14*Q14 -> 2044.0371 | T14: =C13*EXP(RATES!Q15)*(DATA!$B$6-DATA!$B$12) -> 154.55385 | U14: =B13*EXP(RATES!Q15)*(DATA!$B$6-DATA!$B$12) -> 618.21542 | V14: =T14+U14 -> 772.76927 | W14: =V14*E14*F14 -> 95.291286
... A51: 49 | B51: =B50*EXP(RATES!Q52)*(1-DATA!$B$6) -> 73154.665 | C51: =C50*EXP(RATES!Q52)*(1-DATA!$B$6) -> 18288.666 | D51: =B51+C51 -> 91443.331 | E51: =E50*(1-'LIFE TABLE MALE'!D111/1000) -> 2.6221013e-06 | F51: =F50*(1-0.15) -> 0.00034795843 | G51: =D51-20 -> 91423.331 | H51: =MAX(D51,DATA!$B$3) -> 100000 | I51: =G51*DATA!$B$7*F50*E51 -> 1.4719945e-05 | J51: =H51*'LIFE TABLE MALE'!D111/1000*F50*E50 -> 0.00026430676 | K51: =0 -> 0 | L51: =DATA!$B$8*((1+DATA!$B$9)^A50)*F51*E51 -> 1.1801985e-07 | M51: =B50*EXP(RATES!Q52)*(DATA!$B$12) -> 1047.2038 | N51: =C50*EXP(RATES!Q52)*(DATA!$B$12) -> 261.80095 | O51: =M51+N51 -> 1309.0047 | P51: =O51*E51*F51 -> 1.1943127e-06 | Q51: =RATES!I52 -> 0.36766463 | R51: =P51+L51+K51+J51+I51 -> 0.00028033904 | S51: =R51*Q51 -> 0.00010307075 | T51: =C50*EXP(RATES!Q52)*(DATA!$B$6-DATA!$B$12) -> 149.60054 | U51: =B50*EXP(RATES!Q52)*(DATA!$B$6-DATA!$B$12) -> 598.40217 | V51: =T51+U51 -> 748.00271 | W51: =V51*E51*F51 -> 6.8246439e-07
A52: 50 | B52: =B51*EXP(RATES!Q53)*(1-DATA!$B$6) -> 73415.781 | C52: =C51*EXP(RATES!Q53)*(1-DATA!$B$6) -> 18353.945 | D52: =B52+C52 -> 91769.726 | E52: =E51*(1-'LIFE TABLE MALE'!D112/1000) -> 6.7948871e-07 | F52: =F51*(1-0.15) -> 0.00029576466 | G52: =D52-20 -> 91749.726 | H52: =MAX(D52,DATA!$B$3) -> 100000 | I52: =G52*DATA!$B$7*F51*E52 -> 3.2539108e-06 | J52: =H52*'LIFE TABLE MALE'!D112/1000*F51*E51 -> 6.7594842e-05 | K52: =E52*D52*F52 -> 1.8442847e-05 | L52: =DATA!$B$8*((1+DATA!$B$9)^A51)*F52*E52 -> 2.6515935e-08 | M52: =B51*EXP(RATES!Q53)*(DATA!$B$12) -> 1050.9416 | N52: =C51*EXP(RATES!Q53)*(DATA!$B$12) -> 262.73541 | O52: =M52+N52 -> 1313.6771 | P52: =O52*E52*F52 -> 2.6400804e-07 | Q52: =RATES!I53 -> 0.35829711 | R52: =P52+L52+K52+J52+I52 -> 8.9582124e-05 | S52: =R52*Q52 -> 3.2097016e-05 | T52: =C51*EXP(RATES!Q53)*(DATA!$B$6-DATA!$B$12) -> 150.13452 | U52: =B51*EXP(RATES!Q53)*(DATA!$B$6-DATA!$B$12) -> 600.53808 | V52: =T52+U52 -> 750.67261 | W52: =V52*E52*F52 -> 1.5086174e-07
P56: LIABILITIES | Q56: =SUM(S3:S52) -> 94853.073 | T56: BEL COMPONENTS
P57: BOF | Q57: =DATA!B2-Q56 -> 5146.9271 | T57: DEATH | U57: =SUMPRODUCT(J3:J52,Q3:Q52) -> 6774.2896
T58: LAPSE | U58: =SUMPRODUCT(I3:I52,Q3:Q52) -> 81226.193
P59: DURATION | Q59: =SUMPRODUCT(S3:S52,A3:A52)/SUM(S3:S52) -> 5.6400305 | T59: EXPENSES | U59: =SUMPRODUCT(L3:L52,Q3:Q52) -> 262.32108
T60: COMMISSIONS | U60: =SUMPRODUCT(P3:P52,Q3:Q52) -> 6590.2696

Sheet EXPENSE STRESS
B1: EQUITY | C1: PROPERTY | D1: ASSET | E1: SURVIVAL PROB | F1: non LAPSE PROB | G1: C lapse | H1: C death | I1: LIAB LAPSE | J1: LIAB DEATH | K1: LIAB SURVIVE | L1: EXPENSES | M1: EQ COMMISSIONS | N1: PR COMMISSIONS | O1: TOT COMMISSIONS | P1: COMMISSIONS LIAB | Q1: DISCOUNTS | R1: TOT LIAB | S1: TOT LIAB DISC | T1: PROFIT PR | U1: PROFIT EQ | V1: TOT PROFIT | W1: PROFIT LIAB | X1: PROFIT LIAB DISCOUNTED
A2: 0 | B2: =DATA!B2*0.8 -> 80000 | C2: =DATA!B2*0.2 -> 20000 | D2: =B2+C2 -> 100000 | E2: =1 -> 1 | F2: =1 -> 1 | G2: =D2-20 -> 99980 | H2: =MAX(D2,DATA!$B$3) -> 100000 | M2: =B2 -> 80000 | N2: =C2 -> 20000 | Q2: =RATES!G3 -> 1
A3: 1 | B3: =B2*EXP(RATES!O4)*(1-DATA!$B$6) -> 80989.354 | C3: =C2*EXP(RATES!O4)*(1-DATA!$B$6) -> 20247.338 | D3: =B3+C3 -> 101236.69 | E3: =E2*(1-'LIFE TABLE MALE'!D63/1000) -> 0.99353213 | F3: =F2*(1-0.15) -> 0.85 | G3: =D3-20 -> 101216.69 | H3: =MAX(D3,DATA!$B$3) -> 101236.69 | I3: =G3*DATA!$B$7*F2*E3 -> 15084.305 | J3: =H3*'LIFE TABLE MALE'!D63/1000*F2*E2 -> 654.78576 | K3: =0 -> 0 | L3: =DATA!$B$8*1.1*((1+DATA!$B$9+0.01)^A2)*F3*E3 -> 46.447627 | M3: =B2*EXP(RATES!O4)*(DATA!$B$12) -> 1159.3568 | N3: =C2*EXP(RATES!O4)*(DATA!$B$12) -> 289.8392 | O3: =M3+N3 -> 1449.196 | P3: =O3*E3*F3 -> 1223.8494 | Q3: =RATES!G4 -> 0.9660529 | R3: =P3+L3+K3+J3+I3 -> 17009.388 | S3: =R3*Q3 -> 16431.969 | T3: =C2*EXP(RATES!O4)*(DATA!$B$6-DATA!$B$12) -> 165.6224 | U3: =B2*EXP(RATES!O4)*(DATA!$B$6-DATA!$B$12) -> 662.4896 | V3: =T3+U3 -> 828.112 | W3: =V3*E3*F3 -> 699.3425 | X3: =W3*BASE!Q3 -> 675.60185
A4: 2 | B4: =B3*EXP(RATES!O5)*(1-DATA!$B$6) -> 81233.889 | C4: =C3*EXP(RATES!O5)*(1-DATA!$B$6) -> 20308.472 | D4: =B4+C4 -> 101542.36 | E4: =E3*(1-'LIFE TABLE MALE'!D64/1000) -> 0.98647779 | F4: =F3*(1-0.15) -> 0.7225 | G4: =D4-20 -> 101522.36 | H4: =MAX(D4,DATA!$B$3) -> 101542.36 | I4: =G4*DATA!$B$7*F3*E4 -> 12769.068 | J4: =H4*'LIFE TABLE MALE'!D64/1000*F3*E3 -> 608.86689 | K4: =0 -> 0 | L4: =DATA!$B$8*1.1*((1+DATA!$B$9+0.01)^A3)*F4*E4 -> 40.376166 | M4: =B3*EXP(RATES!O5)*(DATA!$B$12) -> 1162.8573 | N4: =C3*EXP(RATES!O5)*(DATA!$B$12) -> 290.71433 | O4: =M4+N4 -> 1453.5716 | P4: =O4*E4*F4 -> 1036.0044 | Q4: =RATES!G5 -> 0.94195564 | R4: =P4+L4+K4+J4+I4 -> 14454.316 | S4: =R4*Q4 -> 13615.324 | T4: =C3*EXP(RATES!O5)*(DATA!$B$6-DATA!$B$12) -> 166.12247 | U4: =B3*EXP(RATES!O5)*(DATA!$B$6-DATA!$B$12) -> 664.48989 | V4: =T4+U4 -> 830.61237 | W4: =V4*E4*F4 -> 592.00252 | X4: =W4*BASE!Q4 -> 557.64011
A5: 3 | B5: =B4*EXP(RATES!O6)*(1-DATA!$B$6) -> 81258.803 | C5: =C4*EXP(RATES!O6)*(1-DATA!$B$6) -> 20314.701 | D5: =B5+C5 -> 101573.5 | E5: =E4*(1-'LIFE TABLE MALE'!D65/1000) -> 0.97876837 | F5: =F4*(1-0.15) -> 0.614125 | G5: =D5-20 -> 101553.5 | H5: =MAX(D5,DATA!$B$3) -> 101573.5 | I5: =G5*DATA!$B$7*F4*E5 -> 10772.189 | J5: =H5*'LIFE TABLE MALE'!D65/1000*F4*E4 -> 565.77029 | K5: =0 -> 0 | L5: =DATA!$B$8*1.1*((1+DATA!$B$9+0.01)^A4)*F5*E5 -> 35.073075 | M5: =B4*EXP(RATES!O6)*(DATA!$B$12) -> 1163.2139 | N5: =C4*EXP(RATES!O6)*(DATA!$B$12) -> 290.80349 | O5: =M5+N5 -> 1454.0174 | P5: =O5*E5*F5 -> 873.98971 | Q5: =RATES!G6 -> 0.92095017 | R5: =P5+L5+K5+J5+I5 -> 12247.022 | S5: =R5*Q5 -> 11278.897 | T5: =C4*EXP(RATES!O6)*(DATA!$B$6-DATA!$B$12) -> 166.17342 | U5: =B4*EXP(RATES!O6)*(DATA!$B$6-DATA!$B$12) -> 664.69368 | V5: =T5+U5 -> 830.86711 | W5: =V5*E5*F5 -> 499.42269 | X5: =W5*BASE!Q5 -> 459.94341
A6: 4 | B6: =B5*EXP(RATES!O7)*(1-DATA!$B$6) -> 81219.667 | C6: =C5*EXP(RATES!O7)*(1-DATA!$B$6) -> 20304.917 | D6: =B6+C6 -> 101524.58 | E6: =E5*(1-'LIFE TABLE MALE'!D66/1000) -> 0.97028747 | F6: =F5*(1-0.15) -> 0.52200625 | G6: =D6-20 -> 101504.58 | H6: =MAX(D6,DATA!$B$3) -> 101524.58 | I6: =G6*DATA!$B$7*F5*E6 -> 9072.6491 | J6: =H6*'LIFE TABLE MALE'!D66/1000*F5*E5 -> 528.77385 | K6: =0 -> 0 | L6: =DATA!$B$8*1.1*((1+DATA!$B$9+0.01)^A5)*F6*E6 -> 30.440409 | M6: =B5*EXP(RATES!O7)*(DATA!$B$12) -> 1162.6537 | N6: =C5*EXP(RATES!O7)*(DATA!$B$12) -> 290.66343 | O6: =M6+N6 -> 1453.3171 | P6: =O6*E6*F6 -> 736.0995 | Q6: =RATES!G7 -> 0.90112326 | R6: =P6+L6+K6+J6+I6 -> 10367.963 | S6: =R6*Q6 -> 9342.8125 | T6: =C5*EXP(RATES!O7)*(DATA!$B$6-DATA!$B$12) -> 166.09339 | U6: =B5*EXP(RATES!O7)*(DATA!$B$6-DATA!$B$12) -> 664.37355 | V6: =T6+U6 -> 830.46694 | W6: =V6*E6*F6 -> 420.62829 | X6: =W6*BASE!Q6 -> 379.03794
A7: 5 | B7: =B6*EXP(RATES!O8)*(1-DATA!$B$6) -> 81178.572 | C7: =C6*EXP(RATES!O8)*(1-DATA!$B$6) -> 20294.643 | D7: =B7+C7 -> 101473.22 | E7: =E6*(1-'LIFE TABLE MALE'!D67/1000) -> 0.96092158 | F7: =F6*(1-0.15) -> 0.44370531 | G7: =D7-20 -> 101453.22 | H7: =MAX(D7,DATA!$B$3) -> 101473.22 | I7: =G7*DATA!$B$7*F6*E7 -> 7633.4475 | J7: =H7*'LIFE TABLE MALE'!D67/1000*F6*E6 -> 496.10815 | K7: =0 -> 0 | L7: =DATA!$B$8*1.1*((1+DATA!$B$9+0.01)^A6)*F7*E7 -> 26.393328 | M7: =B6*EXP(RATES!O8)*(DATA!$B$12) -> 1162.0655 | N7: =C6*EXP(RATES!O8)*(DATA!$B$12) -> 290.51636 | O7: =M7+N7 -> 1452.5818 | P7: =O7*E7*F7 -> 619.33151 | Q7: =RATES!G8 -> 0.88174469 | R7: =P7+L7+K7+J7+I7 -> 8775.2805 | S7: =R7*Q7 -> 7737.5569 | T7: =C6*EXP(RATES!O8)*(DATA!$B$6-DATA!$B$12) -> 166.00935 | U7: =B6*EXP(RATES!O8)*(DATA!$B$6-DATA!$B$12) -> 664.0374 | V7: =T7+U7 -> 830.04675 | W7: =V7*E7*F7 -> 353.90372 | X7: =W7*BASE!Q7 -> 312.05273
A8: 6 | B8: =B7*EXP(RATES!O9)*(1-DATA!$B$6) -> 81192.731 | C8: =C7*EXP(RATES!O9)*(1-DATA!$B$6) -> 20298.183 | D8: =B8+C8 -> 101490.91 | E8: =E7*(1-'LIFE TABLE MALE'!D68/1000) -> 0.95054817 | F8: =F7*(1-0.15) -> 0.37714952 | G8: =D8-20 -> 101470.91 | H8: =MAX(D8,DATA!$B$3) -> 101490.91 | I8: =G8*DATA!$B$7*F7*E8 -> 6419.5057 | J8: =H8*'LIFE TABLE MALE'!D68/1000*F7*E7 -> 467.1359 | K8: =0 -> 0 | L8: =DATA!$B$8*1.1*((1+DATA!$B$9+0.01)^A7)*F8*E8 -> 22.857909 | M8: =B7*EXP(RATES!O9)*(DATA!$B$12) -> 1162.2681 | N8: =C7*EXP(RATES!O9)*(DATA!$B$12) -> 290.56703 | O8: =M8+N8 -> 1452.8352 | P8: =O8*E8*F8 -> 520.83964 | Q8: =RATES!G9 -> 0.86219592 | R8: =P8+L8+K8+J8+I8 -> 7430.3392 | S8: =R8*Q8 -> 6406.4081 | T8: =C7*EXP(RATES!O9)*(DATA!$B$6-DATA!$B$12) -> 166.03831 | U8: =B7*EXP(RATES!O9)*(DATA!$B$6-DATA!$B$12) -> 664.15322 | V8: =T8+U8 -> 830.19153 | W8: =V8*E8*F8 -> 297.62265 | X8: =W8*BASE!Q8 -> 256.60904
A9: 7 | B9: =B8*EXP(RATES!O10)*(1-DATA!$B$6) -> 81254.382 | C9: =C8*EXP(RATES!O10)*(1-DATA!$B$6) -> 20313.596 | D9: =B9+C9 -> 101567.98 | E9: =E8*(1-'LIFE TABLE MALE'!D69/1000) -> 0.93939989 | F9: =F8*(1-0.15) -> 0.32057709 | G9: =D9-20 -> 101547.98 | H9: =MAX(D9,DATA!$B$3) -> 101567.98 | I9: =G9*DATA!$B$7*F8*E9 -> 5396.6791 | J9: =H9*'LIFE TABLE MALE'!D69/1000*F8*E8 -> 427.04936 | K9: =0 -> 0 | L9: =DATA!$B$8*1.1*((1+DATA!$B$9+0.01)^A8)*F9*E9 -> 19.777392 | M9: =B8*EXP(RATES!O10)*(DATA!$B$12) -> 1163.1507 | N9: =C8*EXP(RATES!O10)*(DATA!$B$12) -> 290.78767 | O9: =M9+N9 -> 1453.9383 | P9: =O9*E9*F9 -> 437.85365 | Q9: =RATES!G10 -> 0.84258782 | R9: =P9+L9+K9+J9+I9 -> 6281.3595 | S9: =R9*Q9 -> 5292.5971 | T9: =C8*EXP(RATES!O10)*(DATA!$B$6-DATA!$B$12) -> 166.16438 | U9: =B8*EXP(RATES!O10)*(DATA!$B$6-DATA!$B$12) -> 664.65752 | V9: =T9+U9 -> 830.8219 | W9: =V9*E9*F9 -> 250.20208 | X9: =W9*BASE!Q9 -> 210.81723
A10: 8 | B10: =B9*EXP(RATES!O11)*(1-DATA!$B$6) -> 81365.273 | C10: =C9*EXP(RATES!O11)*(1-DATA!$B$6) -> 20341.318 | D10: =B10+C10 -> 101706.59 | E10: =E9*(1-'LIFE TABLE MALE'!D70/1000) -> 0.92737751 | F10: =F9*(1-0.15) -> 0.27249053 | G10: =D10-20 -> 101686.59 | H10: =MAX(D10,DATA!$B$3) -> 101706.59 | I10: =G10*DATA!$B$7*F9*E10 -> 4534.6523 | J10: =H10*'LIFE TABLE MALE'!D70/1000*F9*E9 -> 391.98744 | K10: =0 -> 0 | L10: =DATA!$B$8*1.1*((1+DATA!$B$9+0.01)^A9)*F10*E10 -> 17.093509 | M10: =B9*EXP(RATES!O11)*(DATA!$B$12) -> 1164.7381 | N10: =C9*EXP(RATES!O11)*(DATA!$B$12) -> 291.18452 | O10: =M10+N10 -> 1455.9226 | P10: =O10*E10*F10 -> 367.91394 | Q10: =RATES!G11 -> 0.82292781 | R10: =P10+L10+K10+J10+I10 -> 5311.6472 | S10: =R10*Q10 -> 4371.1021 | T10: =C9*EXP(RATES!O11)*(DATA!$B$6-DATA!$B$12) -> 166.39115 | U10: =B9*EXP(RATES!O11)*(DATA!$B$6-DATA!$B$12) -> 665.56461 | V10: =T10+U10 -> 831.95576 | W10: =V10*E10*F10 -> 210.23654 | X10: =W10*BASE!Q10 -> 173.00949
A11: 9 | B11: =B10*EXP(RATES!O12)*(1-DATA!$B$6) -> 81523.24 | C11: =C10*EXP(RATES!O12)*(1-DATA!$B$6) -> 20380.81 | D11: =B11+C11 -> 101904.05 | E11: =E10*(1-'LIFE TABLE MALE'!D71/1000) -> 0.91441742 | F11: =F10*(1-0.15) -> 0.23161695 | G11: =D11-20 -> 101884.05 | H11: =MAX(D11,DATA!$B$3) -> 101904.05 | I11: =G11*DATA!$B$7*F10*E11 -> 3807.9686 | J11: =H11*'LIFE TABLE MALE'!D71/1000*F10*E10 -> 359.87437 | K11: =0 -> 0 | L11: =DATA!$B$8*1.1*((1+DATA!$B$9+0.01)^A10)*F11*E11 -> 14.756226 | M11: =B10*EXP(RATES!O12)*(DATA!$B$12) -> 1166.9993 | N11: =C10*EXP(RATES!O12)*(DATA!$B$12) -> 291.74984 | O11: =M11+N11 -> 1458.7492 | P11: =O11*E11*F11 -> 308.95516 | Q11: =RATES!G12 -> 0.8032639 | R11: =P11+L11+K11+J11+I11 -> 4491.5543 | S11: =R11*Q11 -> 3607.9034 | T11: =C10*EXP(RATES!O12)*(DATA!$B$6-DATA!$B$12) -> 166.71419 | U11: =B10*EXP(RATES!O12)*(DATA!$B$6-DATA!$B$12) -> 666.85677 | V11: =T11+U11 -> 833.57096 | W11: =V11*E11*F11 -> 176.5458 | X11: =W11*BASE!Q11 -> 141.81287
A12: 10 | B12: =B11*EXP(RATES!O13)*(1-DATA!$B$6) -> 81742.12 | C12: =C11*EXP(RATES!O13)*(1-DATA!$B$6) -> 20435.53 | D12: =B12+C12 -> 102177.65 | E12: =E11*(1-'LIFE TABLE MALE'!D72/1000) -> 0.9000976 | F12: =F11*(1-0.15) -> 0.1968744 | G12: =D12-20 -> 102157.65 | H12: =MAX(D12,DATA!$B$3) -> 102177.65 | I12: =G12*DATA!$B$7*F11*E12 -> 3194.6412 | J12: =H12*'LIFE TABLE MALE'!D72/1000*F11*E11 -> 338.894 | K12: =0 -> 0 | L12: =DATA!$B$8*1.1*((1+DATA!$B$9+0.01)^A11)*F12*E12 -> 12.716763 | M12: =B11*EXP(RATES!O13)*(DATA!$B$12) -> 1170.1326 | N12: =C11*EXP(RATES!O13)*(DATA!$B$12) -> 292.53315 | O12: =M12+N12 -> 1462.6657 | P12: =O12*E12*F12 -> 259.19341 | Q12: =RATES!G13 -> 0.78348852 | R12: =P12+L12+K12+J12+I12 -> 3805.4453 | S12: =R12*Q12 -> 2981.5227 | T12: =C11*EXP(RATES!O13)*(DATA!$B$6-DATA!$B$12) -> 167.1618 | U12: =B11*EXP(RATES!O13)*(DATA!$B$6-DATA!$B$12) -> 668.6472 | V12: =T12+U12 -> 835.809 | W12: =V12*E12*F12 -> 148.11052 | X12: =W12*BASE!Q12 -> 116.04289
A13: 11 | B13: =B12*EXP(RATES!O14)*(1-DATA!$B$6) -> 82068.024 | C13: =C12*EXP(RATES!O14)*(1-DATA!$B$6) -> 20517.006 | D13: =B13+C13 -> 102585.03 | E13: =E12*(1-'LIFE TABLE MALE'!D73/1000) -> 0.88436967 | F13: =F12*(1-0.15) -> 0.16734324 | G13: =D13-20 -> 102565.03 | H13: =MAX(D13,DATA!$B$3) -> 102585.03 | I13: =G13*DATA!$B$7*F12*E13 -> 2678.6358 | J13: =H13*'LIFE TABLE MALE'!D73/1000*F12*E12 -> 317.64699 | K13: =0 -> 0 | L13: =DATA!$B$8*1.1*((1+DATA!$B$9+0.01)^A12)*F13*E13 -> 10.938983 | M13: =B12*EXP(RATES!O14)*(DATA!$B$12) -> 1174.7979 | N13: =C12*EXP(RATES!O14)*(DATA!$B$12) -> 293.69947 | O13: =M13+N13 -> 1468.4974 | P13: =O13*E13*F13 -> 217.32775 | Q13: =RATES!G14 -> 0.76320888 | R13: =P13+L13+K13+J13+I13 -> 3224.5495 | S13: =R13*Q13 -> 2461.0048 | T13: =C12*EXP(RATES!O14)*(DATA!$B$6-DATA!$B$12) -> 167.82827 | U13: =B12*EXP(RATES!O14)*(DATA!$B$6-DATA!$B$12) -> 671.31308 | V13: =T13+U13 -> 839.14135 | W13: =V13*E13*F13 -> 124.18729 | X13: =W13*BASE!Q13 -> 94.780841
A14: 12 | B14: =B13*EXP(RATES!O15)*(1-DATA!$B$6) -> 82258.657 | C14: =C13*EXP(RATES!O15)*(1-DATA!$B$6) -> 20564.664 | D14: =B14+C14 -> 102823.32 | E14: =E13*(1-'LIFE TABLE MALE'!D74/1000) -> 0.86691444 | F14: =F13*(1-0.15) -> 0.14224176 | G14: =D14-20 -> 102803.32 | H14: =MAX(D14,DATA!$B$3) -> 102823.32 | I14: =G14*DATA!$B$7*F13*E14 -> 2237.0867 | J14: =H14*'LIFE TABLE MALE'!D74/1000*F13*E13 -> 300.34842 | K14: =0 -> 0 | L14: =DATA!$B$8*1.1*((1+DATA!$B$9+0.01)^A13)*F14*E14 -> 9.3880524 | M14: =B13*EXP(RATES!O15)*(DATA!$B$12) -> 1177.5268 | N14: =C13*EXP(RATES!O15)*(DATA!$B$12) -> 294.3817 | O14: =M14+N14 -> 1471.9085 | P14: =O14*E14*F14 -> 181.50314 | Q14: =RATES!G15 -> 0.74468847 | R14: =P14+L14+K14+J14+I14 -> 2728.3263 | S14: =R14*Q14 -> 2031.7532 | T14: =C13*EXP(RATES!O15)*(DATA!$B$6-DATA!$B$12) -> 168.21811 | U14: =B13*EXP(RATES!O15)*(DATA!$B$6-DATA!$B$12) -> 672.87245 | V14: =T14+U14 -> 841.09056 | W14: =V14*E14*F14 -> 103.71608 | X14: =W14*BASE!Q14 -> 77.236171
... A51: 49 | B51: =B50*EXP(RATES!O52)*(1-DATA!$B$6) -> 102111.48 | C51: =C50*EXP(RATES!O52)*(1-DATA!$B$6) -> 25527.869 | D51: =B51+C51 -> 127639.35 | E51: =E50*(1-'LIFE TABLE MALE'!D111/1000) -> 2.6221013e-06 | F51: =F50*(1-0.15) -> 0.00034795843 | G51: =D51-20 -> 127619.35 | H51: =MAX(D51,DATA!$B$3) -> 127639.35 | I51: =G51*DATA!$B$7*F50*E51 -> 2.0547816e-05 | J51: =H51*'LIFE TABLE MALE'!D111/1000*F50*E50 -> 0.00033735942 | K51: =0 -> 0 | L51: =DATA!$B$8*1.1*((1+DATA!$B$9+0.01)^A50)*F51*E51 -> 2.0736063e-07 | M51: =B50*EXP(RATES!O52)*(DATA!$B$12) -> 1461.7185 | N51: =C50*EXP(RATES!O52)*(DATA!$B$12) -> 365.42962 | O51: =M51+N51 -> 1827.1481 | P51: =O51*E51*F51 -> 1.6670575e-06 | Q51: =RATES!G52 -> 0.26340215 | R51: =P51+L51+K51+J51+I51 -> 0.00035978165 | S51: =R51*Q51 -> 9.4767261e-05 | T51: =C50*EXP(RATES!O52)*(DATA!$B$6-DATA!$B$12) -> 208.81693 | U51: =B50*EXP(RATES!O52)*(DATA!$B$6-DATA!$B$12) -> 835.2677 | V51: =T51+U51 -> 1044.0846 | W51: =V51*E51*F51 -> 9.5260428e-07 | X51: =W51*BASE!Q51 -> 2.5091802e-07
A52: 50 | B52: =B51*EXP(RATES!O53)*(1-DATA!$B$6) -> 103172 | C52: =C51*EXP(RATES!O53)*(1-DATA!$B$6) -> 25793 | D52: =B52+C52 -> 128965 | E52: =E51*(1-'LIFE TABLE MALE'!D112/1000) -> 6.7948871e-07 | F52: =F51*(1-0.15) -> 0.00029576466 | G52: =D52-20 -> 128945 | H52: =MAX(D52,DATA!$B$3) -> 128965 | I52: =G52*DATA!$B$7*F51*E52 -> 4.5730439e-06 | J52: =H52*'LIFE TABLE MALE'!D112/1000*F51*E51 -> 8.7173688e-05 | K52: =E52*D52*F52 -> 2.5917935e-05 | L52: =DATA!$B$8*1.1*((1+DATA!$B$9+0.01)^A51)*F52*E52 -> 4.704519e-08 | M52: =B51*EXP(RATES!O53)*(DATA!$B$12) -> 1476.8998 | N52: =C51*EXP(RATES!O53)*(DATA!$B$12) -> 369.22495 | O52: =M52+N52 -> 1846.1247 | P52: =O52*E52*F52 -> 3.7101338e-07 | Q52: =RATES!G53 -> 0.25495931 | R52: =P52+L52+K52+J52+I52 -> 0.00011808272 | S52: =R52*Q52 -> 3.010629e-05 | T52: =C51*EXP(RATES!O53)*(DATA!$B$6-DATA!$B$12) -> 210.98568 | U52: =B51*EXP(RATES!O53)*(DATA!$B$6-DATA!$B$12) -> 843.94273 | V52: =T52+U52 -> 1054.9284 | W52: =V52*E52*F52 -> 2.1200765e-07 | X52: =W52*BASE!Q52 -> 5.4053324e-08
P56: LIABILITIES | Q56: =SUM(S3:S52) -> 94531.722 | T56: BEL COMPONENTS
P57: BOF | Q57: =DATA!B2-Q56 -> 5468.2777 | T57: DEATH | U57: =SUMPRODUCT(J3:J52,Q3:Q52) -> 6428.626
T58: LAPSE | U58: =SUMPRODUCT(I3:I52,Q3:Q52) -> 81227.1
P59: DURATION | Q59: =SUMPRODUCT(S3:S52,A3:A52)/SUM(S3:S52) -> 5.6138741 | T59: EXPENSES | U59: =SUMPRODUCT(L3:L52,Q3:Q52) -> 285.72627
T60: COMMISSIONS | U60: =SUMPRODUCT(P3:P52,Q3:Q52) -> 6590.2696

Sheet MORTALITY
B1: EQUITY | C1: PROPERTY | D1: ASSET | E1: SURVIVAL PROB | F1: non LAPSE PROB | G1: C lapse | H1: C death | I1: LIAB LAPSE | J1: LIAB DEATH | K1: LIAB SURVIVE | L1: EXPENSES | M1: EQ COMMISSIONS | N1: PR COMMISSIONS | O1: TOT COMMISSIONS | P1: COMMISSIONS LIAB | Q1: DISCOUNTS | R1: TOT LIAB | S1: TOT LIAB DISC | T1: PROFIT PR | U1: PROFIT EQ | V1: TOT PROFIT | W1: PROFIT LIAB | X1: PROFIT LIAB DISCOUNTED
A2: 0 | B2: =DATA!B2*0.8 -> 80000 | C2: =DATA!B2*0.2 -> 20000 | D2: =B2+C2 -> 100000 | E2: =1 -> 1 | F2: =1 -> 1 | G2: =D2-20 -> 99980 | H2: =MAX(D2,DATA!$B$3) -> 100000 | M2: =B2 -> 80000 | N2: =C2 -> 20000 | Q2: =RATES!G3 -> 1
A3: 1 | B3: =B2*EXP(RATES!O4)*(1-DATA!$B$6) -> 80989.354 | C3: =C2*EXP(RATES!O4)*(1-DATA!$B$6) -> 20247.338 | D3: =B3+C3 -> 101236.69 | E3: =E2*(1-'LIFE TABLE MALE'!D63/1000*1.15) -> 0.99256195 | F3: =F2*(1-0.15) -> 0.85 | G3: =D3-20 -> 101216.69 | H3: =MAX(D3,DATA!$B$3) -> 101236.69 | I3: =G3*DATA!$B$7*F2*E3 -> 15069.576 | J3: =H3*'LIFE TABLE MALE'!D63/1000*1.15*F2*E2 -> 753.00363 | K3: =0 -> 0 | L3: =DATA!$B$8*((1+DATA!$B$9)^A2)*F3*E3 -> 42.183883 | M3: =B2*EXP(RATES!O4)*(DATA!$B$12) -> 1159.3568 | N3: =C2*EXP(RATES!O4)*(DATA!$B$12) -> 289.8392 | O3: =M3+N3 -> 1449.196 | P3: =O3*E3*F3 -> 1222.6543 | Q3: =RATES!G4 -> 0.9660529 | R3: =P3+L3+K3+J3+I3 -> 17087.417 | S3: =R3*Q3 -> 16507.349 | T3: =C2*EXP(RATES!O4)*(DATA!$B$6-DATA!$B$12) -> 165.6224 | U3: =B2*EXP(RATES!O4)*(DATA!$B$6-DATA!$B$12) -> 662.4896 | V3: =T3+U3 -> 828.112 | W3: =V3*E3*F3 -> 698.65959 | X3: =W3*BASE!Q3 -> 674.94213
A4: 2 | B4: =B3*EXP(RATES!O5)*(1-DATA!$B$6) -> 81233.889 | C4: =C3*EXP(RATES!O5)*(1-DATA!$B$6) -> 20308.472 | D4: =B4+C4 -> 101542.36 | E4: =E3*(1-'LIFE TABLE MALE'!D64/1000*1.15) -> 0.98445738 | F4: =F3*(1-0.15) -> 0.7225 | G4: =D4-20 -> 101522.36 | H4: =MAX(D4,DATA!$B$3) -> 101542.36 | I4: =G4*DATA!$B$7*F3*E4 -> 12742.916 | J4: =H4*'LIFE TABLE MALE'!D64/1000*1.15*F3*E3 -> 699.51318 | K4: =0 -> 0 | L4: =DATA!$B$8*((1+DATA!$B$9)^A3)*F4*E4 -> 36.274793 | M4: =B3*EXP(RATES!O5)*(DATA!$B$12) -> 1162.8573 | N4: =C3*EXP(RATES!O5)*(DATA!$B$12) -> 290.71433 | O4: =M4+N4 -> 1453.5716 | P4: =O4*E4*F4 -> 1033.8826 | Q4: =RATES!G5 -> 0.94195564 | R4: =P4+L4+K4+J4+I4 -> 14512.586 | S4: =R4*Q4 -> 13670.213 | T4: =C3*EXP(RATES!O5)*(DATA!$B$6-DATA!$B$12) -> 166.12247 | U4: =B3*EXP(RATES!O5)*(DATA!$B$6-DATA!$B$12) -> 664.48989 | V4: =T4+U4 -> 830.61237 | W4: =V4*E4*F4 -> 590.79004 | X4: =W4*BASE!Q4 -> 556.49801
A5: 3 | B5: =B4*EXP(RATES!O6)*(1-DATA!$B$6) -> 81258.803 | C5: =C4*EXP(RATES!O6)*(1-DATA!$B$6) -> 20314.701 | D5: =B5+C5 -> 101573.5 | E5: =E4*(1-'LIFE TABLE MALE'!D65/1000*1.15) -> 0.97560971 | F5: =F4*(1-0.15) -> 0.614125 | G5: =D5-20 -> 101553.5 | H5: =MAX(D5,DATA!$B$3) -> 101573.5 | I5: =G5*DATA!$B$7*F4*E5 -> 10737.425 | J5: =H5*'LIFE TABLE MALE'!D65/1000*1.15*F4*E4 -> 649.30326 | K5: =0 -> 0 | L5: =DATA!$B$8*((1+DATA!$B$9)^A4)*F5*E5 -> 31.167591 | M5: =B4*EXP(RATES!O6)*(DATA!$B$12) -> 1163.2139 | N5: =C4*EXP(RATES!O6)*(DATA!$B$12) -> 290.80349 | O5: =M5+N5 -> 1454.0174 | P5: =O5*E5*F5 -> 871.16918 | Q5: =RATES!G6 -> 0.92095017 | R5: =P5+L5+K5+J5+I5 -> 12289.065 | S5: =R5*Q5 -> 11317.616 | T5: =C4*EXP(RATES!O6)*(DATA!$B$6-DATA!$B$12) -> 166.17342 | U5: =B4*EXP(RATES!O6)*(DATA!$B$6-DATA!$B$12) -> 664.69368 | V5: =T5+U5 -> 830.86711 | W5: =V5*E5*F5 -> 497.81096 | X5: =W5*BASE!Q5 -> 458.45909
A6: 4 | B6: =B5*EXP(RATES!O7)*(1-DATA!$B$6) -> 81219.667 | C6: =C5*EXP(RATES!O7)*(1-DATA!$B$6) -> 20304.917 | D6: =B6+C6 -> 101524.58 | E6: =E5*(1-'LIFE TABLE MALE'!D66/1000*1.15) -> 0.96588815 | F6: =F5*(1-0.15) -> 0.52200625 | G6: =D6-20 -> 101504.58 | H6: =MAX(D6,DATA!$B$3) -> 101524.58 | I6: =G6*DATA!$B$7*F5*E6 -> 9031.5133 | J6: =H6*'LIFE TABLE MALE'!D66/1000*1.15*F5*E5 -> 606.12751 | K6: =0 -> 0 | L6: =DATA!$B$8*((1+DATA!$B$9)^A5)*F6*E6 -> 26.753035 | M6: =B5*EXP(RATES!O7)*(DATA!$B$12) -> 1162.6537 | N6: =C5*EXP(RATES!O7)*(DATA!$B$12) -> 290.66343 | O6: =M6+N6 -> 1453.3171 | P6: =O6*E6*F6 -> 732.762 | Q6: =RATES!G7 -> 0.90112326 | R6: =P6+L6+K6+J6+I6 -> 10397.156 | S6: =R6*Q6 -> 9369.119 | T6: =C5*EXP(RATES!O7)*(DATA!$B$6-DATA!$B$12) -> 166.09339 | U6: =B5*EXP(RATES!O7)*(DATA!$B$6-DATA!$B$12) -> 664.37355 | V6: =T6+U6 -> 830.46694 | W6: =V6*E6*F6 -> 418.72114 | X6: =W6*BASE!Q6 -> 377.31936
A7: 5 | B7: =B6*EXP(RATES!O8)*(1-DATA!$B$6) -> 81178.572 | C7: =C6*EXP(RATES!O8)*(1-DATA!$B$6) -> 20294.643 | D7: =B7+C7 -> 101473.22 | E7: =E6*(1-'LIFE TABLE MALE'!D67/1000*1.15) -> 0.9551662 | F7: =F6*(1-0.15) -> 0.44370531 | G7: =D7-20 -> 101453.22 | H7: =MAX(D7,DATA!$B$3) -> 101473.22 | I7: =G7*DATA!$B$7*F6*E7 -> 7587.7275 | J7: =H7*'LIFE TABLE MALE'!D67/1000*1.15*F6*E6 -> 567.93759 | K7: =0 -> 0 | L7: =DATA!$B$8*((1+DATA!$B$9)^A6)*F7*E7 -> 22.937404 | M7: =B6*EXP(RATES!O8)*(DATA!$B$12) -> 1162.0655 | N7: =C6*EXP(RATES!O8)*(DATA!$B$12) -> 290.51636 | O7: =M7+N7 -> 1452.5818 | P7: =O7*E7*F7 -> 615.62207 | Q7: =RATES!G8 -> 0.88174469 | R7: =P7+L7+K7+J7+I7 -> 8794.2246 | S7: =R7*Q7 -> 7754.2608 | T7: =C6*EXP(RATES!O8)*(DATA!$B$6-DATA!$B$12) -> 166.00935 | U7: =B6*EXP(RATES!O8)*(DATA!$B$6-DATA!$B$12) -> 664.0374 | V7: =T7+U7 -> 830.04675 | W7: =V7*E7*F7 -> 351.78404 | X7: =W7*BASE!Q7 -> 310.18371
A8: 6 | B8: =B7*EXP(RATES!O9)*(1-DATA!$B$6) -> 81192.731 | C8: =C7*EXP(RATES!O9)*(1-DATA!$B$6) -> 20298.183 | D8: =B8+C8 -> 101490.91 | E8: =E7*(1-'LIFE TABLE MALE'!D68/1000*1.15) -> 0.94330823 | F8: =F7*(1-0.15) -> 0.37714952 | G8: =D8-20 -> 101470.91 | H8: =MAX(D8,DATA!$B$3) -> 101490.91 | I8: =G8*DATA!$B$7*F7*E8 -> 6370.611 | J8: =H8*'LIFE TABLE MALE'!D68/1000*1.15*F7*E7 -> 533.98873 | K8: =0 -> 0 | L8: =DATA!$B$8*((1+DATA!$B$9)^A7)*F8*E8 -> 19.639844 | M8: =B7*EXP(RATES!O9)*(DATA!$B$12) -> 1162.2681 | N8: =C7*EXP(RATES!O9)*(DATA!$B$12) -> 290.56703 | O8: =M8+N8 -> 1452.8352 | P8: =O8*E8*F8 -> 516.87262 | Q8: =RATES!G9 -> 0.86219592 | R8: =P8+L8+K8+J8+I8 -> 7441.1122 | S8: =R8*Q8 -> 6415.6966 | T8: =C7*EXP(RATES!O9)*(DATA!$B$6-DATA!$B$12) -> 166.03831 | U8: =B7*EXP(RATES!O9)*(DATA!$B$6-DATA!$B$12) -> 664.15322 | V8: =T8+U8 -> 830.19153 | W8: =V8*E8*F8 -> 295.35578 | X8: =W8*BASE!Q8 -> 254.65455
A9: 7 | B9: =B8*EXP(RATES!O10)*(1-DATA!$B$6) -> 81254.382 | C9: =C8*EXP(RATES!O10)*(1-DATA!$B$6) -> 20313.596 | D9: =B9+C9 -> 101567.98 | E9: =E8*(1-'LIFE TABLE MALE'!D69/1000*1.15) -> 0.93058537 | F9: =F8*(1-0.15) -> 0.32057709 | G9: =D9-20 -> 101547.98 | H9: =MAX(D9,DATA!$B$3) -> 101567.98 | I9: =G9*DATA!$B$7*F8*E9 -> 5346.0413 | J9: =H9*'LIFE TABLE MALE'!D69/1000*1.15*F8*E8 -> 487.3662 | K9: =0 -> 0 | L9: =DATA!$B$8*((1+DATA!$B$9)^A8)*F9*E9 -> 16.798083 | M9: =B8*EXP(RATES!O10)*(DATA!$B$12) -> 1163.1507 | N9: =C8*EXP(RATES!O10)*(DATA!$B$12) -> 290.78767 | O9: =M9+N9 -> 1453.9383 | P9: =O9*E9*F9 -> 433.7452 | Q9: =RATES!G10 -> 0.84258782 | R9: =P9+L9+K9+J9+I9 -> 6283.9508 | S9: =R9*Q9 -> 5294.7804 | T9: =C8*EXP(RATES!O10)*(DATA!$B$6-DATA!$B$12) -> 166.16438 | U9: =B8*EXP(RATES!O10)*(DATA!$B$6-DATA!$B$12) -> 664.65752 | V9: =T9+U9 -> 830.8219 | W9: =V9*E9*F9 -> 247.8544 | X9: =W9*BASE!Q9 -> 208.8391
A10: 8 | B10: =B9*EXP(RATES!O11)*(1-DATA!$B$6) -> 81365.273 | C10: =C9*EXP(RATES!O11)*(1-DATA!$B$6) -> 20341.318 | D10: =B10+C10 -> 101706.59 | E10: =E9*(1-'LIFE TABLE MALE'!D70/1000*1.15) -> 0.91688935 | F10: =F9*(1-0.15) -> 0.27249053 | G10: =D10-20 -> 101686.59 | H10: =MAX(D10,DATA!$B$3) -> 101706.59 | I10: =G10*DATA!$B$7*F9*E10 -> 4483.3677 | J10: =H10*'LIFE TABLE MALE'!D70/1000*1.15*F9*E9 -> 446.55577 | K10: =0 -> 0 | L10: =DATA!$B$8*((1+DATA!$B$9)^A9)*F10*E10 -> 14.349592 | M10: =B9*EXP(RATES!O11)*(DATA!$B$12) -> 1164.7381 | N10: =C9*EXP(RATES!O11)*(DATA!$B$12) -> 291.18452 | O10: =M10+N10 -> 1455.9226 | P10: =O10*E10*F10 -> 363.75303 | Q10: =RATES!G11 -> 0.82292781 | R10: =P10+L10+K10+J10+I10 -> 5308.0261 | S10: =R10*Q10 -> 4368.1223 | T10: =C9*EXP(RATES!O11)*(DATA!$B$6-DATA!$B$12) -> 166.39115 | U10: =B9*EXP(RATES!O11)*(DATA!$B$6-DATA!$B$12) -> 665.56461 | V10: =T10+U10 -> 831.95576 | W10: =V10*E10*F10 -> 207.85887 | X10: =W10*BASE!Q10 -> 171.05285
A11: 9 | B11: =B10*EXP(RATES!O12)*(1-DATA!$B$6) -> 81523.24 | C11: =C10*EXP(RATES!O12)*(1-DATA!$B$6) -> 20380.81 | D11: =B11+C11 -> 101904.05 | E11: =E10*(1-'LIFE TABLE MALE'!D71/1000*1.15) -> 0.90215381 | F11: =F10*(1-0.15) -> 0.23161695 | G11: =D11-20 -> 101884.05 | H11: =MAX(D11,DATA!$B$3) -> 101904.05 | I11: =G11*DATA!$B$7*F10*E11 -> 3756.8984 | J11: =H11*'LIFE TABLE MALE'!D71/1000*1.15*F10*E10 -> 409.17503 | K11: =0 -> 0 | L11: =DATA!$B$8*((1+DATA!$B$9)^A10)*F11*E11 -> 12.241152 | M11: =B10*EXP(RATES!O12)*(DATA!$B$12) -> 1166.9993 | N11: =C10*EXP(RATES!O12)*(DATA!$B$12) -> 291.74984 | O11: =M11+N11 -> 1458.7492 | P11: =O11*E11*F11 -> 304.81164 | Q11: =RATES!G12 -> 0.8032639 | R11: =P11+L11+K11+J11+I11 -> 4483.1262 | S11: =R11*Q11 -> 3601.1334 | T11: =C10*EXP(RATES!O12)*(DATA!$B$6-DATA!$B$12) -> 166.71419 | U11: =B10*EXP(RATES!O12)*(DATA!$B$6-DATA!$B$12) -> 666.85677 | V11: =T11+U11 -> 833.57096 | W11: =V11*E11*F11 -> 174.17808 | X11: =W11*BASE!Q11 -> 139.91096
A12: 10 | B12: =B11*EXP(RATES!O13)*(1-DATA!$B$6) -> 81742.12 | C12: =C11*EXP(RATES!O13)*(1-DATA!$B$6) -> 20435.53 | D12: =B12+C12 -> 102177.65 | E12: =E11*(1-'LIFE TABLE MALE'!D72/1000*1.15) -> 0.88590687 | F12: =F11*(1-0.15) -> 0.1968744 | G12: =D12-20 -> 102157.65 | H12: =MAX(D12,DATA!$B$3) -> 102177.65 | I12: =G12*DATA!$B$7*F11*E12 -> 3144.2752 | J12: =H12*'LIFE TABLE MALE'!D72/1000*1.15*F11*E11 -> 384.5013 | K12: =0 -> 0 | L12: =DATA!$B$8*((1+DATA!$B$9)^A11)*F12*E12 -> 10.421947 | M12: =B11*EXP(RATES!O13)*(DATA!$B$12) -> 1170.1326 | N12: =C11*EXP(RATES!O13)*(DATA!$B$12) -> 292.53315 | O12: =M12+N12 -> 1462.6657 | P12: =O12*E12*F12 -> 255.10702 | Q12: =RATES!G13 -> 0.78348852 | R12: =P12+L12+K12+J12+I12 -> 3794.3055 | S12: =R12*Q12 -> 2972.7948 | T12: =C11*EXP(RATES!O13)*(DATA!$B$6-DATA!$B$12) -> 167.1618 | U12: =B11*EXP(RATES!O13)*(DATA!$B$6-DATA!$B$12) -> 668.6472 | V12: =T12+U12 -> 835.809 | W12: =V12*E12*F12 -> 145.77544 | X12: =W12*BASE!Q12 -> 114.21339
A13: 11 | B13: =B12*EXP(RATES!O14)*(1-DATA!$B$6) -> 82068.024 | C13: =C12*EXP(RATES!O14)*(1-DATA!$B$6) -> 20517.006 | D13: =B13+C13 -> 102585.03 | E13: =E12*(1-'LIFE TABLE MALE'!D73/1000*1.15) -> 0.86810491 | F13: =F12*(1-0.15) -> 0.16734324 | G13: =D13-20 -> 102565.03 | H13: =MAX(D13,DATA!$B$3) -> 102585.03 | I13: =G13*DATA!$B$7*F12*E13 -> 2629.372 | J13: =H13*'LIFE TABLE MALE'!D73/1000*1.15*F12*E12 -> 359.53489 | K13: =0 -> 0 | L13: =DATA!$B$8*((1+DATA!$B$9)^A12)*F13*E13 -> 8.8542568 | M13: =B12*EXP(RATES!O14)*(DATA!$B$12) -> 1174.7979 | N13: =C12*EXP(RATES!O14)*(DATA!$B$12) -> 293.69947 | O13: =M13+N13 -> 1468.4974 | P13: =O13*E13*F13 -> 213.3308 | Q13: =RATES!G14 -> 0.76320888 | R13: =P13+L13+K13+J13+I13 -> 3211.092 | S13: =R13*Q13 -> 2450.7339 | T13: =C12*EXP(RATES!O14)*(DATA!$B$6-DATA!$B$12) -> 167.82827 | U13: =B12*EXP(RATES!O14)*(DATA!$B$6-DATA!$B$12) -> 671.31308 | V13: =T13+U13 -> 839.14135 | W13: =V13*E13*F13 -> 121.90332 | X13: =W13*BASE!Q13 -> 93.037692
A14: 12 | B14: =B13*EXP(RATES!O15)*(1-DATA!$B$6) -> 82258.657 | C14: =C13*EXP(RATES!O15)*(1-DATA!$B$6) -> 20564.664 | D14: =B14+C14 -> 102823.32 | E14: =E13*(1-'LIFE TABLE MALE'!D74/1000*1.15) -> 0.84840057 | F14: =F13*(1-0.15) -> 0.14224176 | G14: =D14-20 -> 102803.32 | H14: =MAX(D14,DATA!$B$3) -> 102823.32 | I14: =G14*DATA!$B$7*F13*E14 -> 2189.3114 | J14: =H14*'LIFE TABLE MALE'!D74/1000*1.15*F13*E13 -> 339.04829 | K14: =0 -> 0 | L14: =DATA!$B$8*((1+DATA!$B$9)^A13)*F14*E14 -> 7.5023955 | M14: =B13*EXP(RATES!O15)*(DATA!$B$12) -> 1177.5268 | N14: =C13*EXP(RATES!O15)*(DATA!$B$12) -> 294.3817 | O14: =M14+N14 -> 1471.9085 | P14: =O14*E14*F14 -> 177.62695 | Q14: =RATES!G15 -> 0.74468847 | R14: =P14+L14+K14+J14+I14 -> 2713.489 | S14: =R14*Q14 -> 2020.704 | T14: =C13*EXP(RATES!O15)*(DATA!$B$6-DATA!$B$12) -> 168.21811 | U14: =B13*EXP(RATES!O15)*(DATA!$B$6-DATA!$B$12) -> 672.87245 | V14: =T14+U14 -> 841.09056 | W14: =V14*E14*F14 -> 101.50112 | X14: =W14*BASE!Q14 -> 75.586712
... A51: 49 | B51: =B50*EXP(RATES!O52)*(1-DATA!$B$6) -> 102111.48 | C51: =C50*EXP(RATES!O52)*(1-DATA!$B$6) -> 25527.869 | D51: =B51+C51 -> 127639.35 | E51: =E50*(1-'LIFE TABLE MALE'!D111/1000*1.15) -> 1.0798816e-07 | F51: =F50*(1-0.15) -> 0.00034795843 | G51: =D51-20 -> 127619.35 | H51: =MAX(D51,DATA!$B$3) -> 127639.35 | I51: =G51*DATA!$B$7*F50*E51 -> 8.4623767e-07 | J51: =H51*'LIFE TABLE MALE'!D111/1000*1.15*F50*E50 -> 2.533559e-05 | K51: =0 -> 0 | L51: =DATA!$B$8*((1+DATA!$B$9)^A50)*F51*E51 -> 4.860509e-09 | M51: =B50*EXP(RATES!O52)*(DATA!$B$12) -> 1461.7185 | N51: =C50*EXP(RATES!O52)*(DATA!$B$12) -> 365.42962 | O51: =M51+N51 -> 1827.1481 | P51: =O51*E51*F51 -> 6.8655804e-08 | Q51: =RATES!G52 -> 0.26340215 | R51: =P51+L51+K51+J51+I51 -> 2.6255344e-05 | S51: =R51*Q51 -> 6.9157141e-06 | T51: =C50*EXP(RATES!O52)*(DATA!$B$6-DATA!$B$12) -> 208.81693 | U51: =B50*EXP(RATES!O52)*(DATA!$B$6-DATA!$B$12) -> 835.2677 | V51: =T51+U51 -> 1044.0846 | W51: =V51*E51*F51 -> 3.9231888e-08 | X51: =W51*BASE!Q51 -> 1.0333764e-08
A52: 50 | B52: =B51*EXP(RATES!O53)*(1-DATA!$B$6) -> 103172 | C52: =C51*EXP(RATES!O53)*(1-DATA!$B$6) -> 25793 | D52: =B52+C52 -> 128965 | E52: =E51*(1-'LIFE TABLE MALE'!D112/1000*1.15) -> 1.5983312e-08 | F52: =F51*(1-0.15) -> 0.00029576466 | G52: =D52-20 -> 128945 | H52: =MAX(D52,DATA!$B$3) -> 128965 | I52: =G52*DATA!$B$7*F51*E52 -> 1.0756968e-07 | J52: =H52*'LIFE TABLE MALE'!D112/1000*1.15*F51*E51 -> 4.1286678e-06 | K52: =E52*D52*F52 -> 6.0965608e-07 | L52: =DATA!$B$8*((1+DATA!$B$9)^A51)*F52*E52 -> 6.2372259e-10 | M52: =B51*EXP(RATES!O53)*(DATA!$B$12) -> 1476.8998 | N52: =C51*EXP(RATES!O53)*(DATA!$B$12) -> 369.22495 | O52: =M52+N52 -> 1846.1247 | P52: =O52*E52*F52 -> 8.7271832e-09 | Q52: =RATES!G53 -> 0.25495931 | R52: =P52+L52+K52+J52+I52 -> 4.8552445e-06 | S52: =R52*Q52 -> 1.2378898e-06 | T52: =C51*EXP(RATES!O53)*(DATA!$B$6-DATA!$B$12) -> 210.98568 | U52: =B51*EXP(RATES!O53)*(DATA!$B$6-DATA!$B$12) -> 843.94273 | V52: =T52+U52 -> 1054.9284 | W52: =V52*E52*F52 -> 4.9869618e-09 | X52: =W52*BASE!Q52 -> 1.2714724e-09
P56: LIABILITIES | Q56: =SUM(S3:S52) -> 94522.922 | T56: BEL COMPONENTS
P57: BOF | Q57: =DATA!B2-Q56 -> 5477.0775 | T57: DEATH | U57: =SUMPRODUCT(J3:J52,Q3:Q52) -> 7246.6768
T58: LAPSE | U58: =SUMPRODUCT(I3:I52,Q3:Q52) -> 80499.87
P59: DURATION | Q59: =SUMPRODUCT(S3:S52,A3:A52)/SUM(S3:S52) -> 5.5723484 | T59: EXPENSES | U59: =SUMPRODUCT(L3:L52,Q3:Q52) -> 245.10872
T60: COMMISSIONS | U60: =SUMPRODUCT(P3:P52,Q3:Q52) -> 6531.2667

Sheet LIFE CAT
B1: EQUITY | C1: PROPERTY | D1: ASSET | E1: SURVIVAL PROB | F1: non LAPSE PROB | G1: C lapse | H1: C death | I1: LIAB LAPSE | J1: LIAB DEATH | K1: LIAB SURVIVE | L1: EXPENSES | M1: EQ COMMISSIONS | N1: PR COMMISSIONS | O1: TOT COMMISSIONS | P1: COMMISSIONS LIAB | Q1: DISCOUNTS | R1: TOT LIAB | S1: TOT LIAB DISC | T1: PROFIT PR | U1: PROFIT EQ | V1: TOT PROFIT | W1: PROFIT LIAB | X1: PROFIT LIAB DISCOUNTED
A2: 0 | B2: =DATA!B2*0.8 -> 80000 | C2: =DATA!B2*0.2 -> 20000 | D2: =B2+C2 -> 100000 | E2: =1 -> 1 | F2: =1 -> 1 | G2: =D2-20 -> 99980 | H2: =MAX(D2,DATA!$B$3) -> 100000 | M2: =B2 -> 80000 | N2: =C2 -> 20000 | Q2: =RATES!G3 -> 1
A3: 1 | B3: =B2*EXP(RATES!O4)*(1-DATA!$B$6) -> 80989.354 | C3: =C2*EXP(RATES!O4)*(1-DATA!$B$6) -> 20247.338 | D3: =B3+C3 -> 101236.69 | E3: =E2*(1-'LIFE TABLE MALE'!D63/1000-0.0015) -> 0.99203213 | F3: =F2*(1-0.15) -> 0.85 | G3: =D3-20 -> 101216.69 | H3: =MAX(D3,DATA!$B$3) -> 101236.69 | I3: =G3*DATA!$B$7*F2*E3 -> 15061.532 | J3: =H3*('LIFE TABLE MALE'!D63/1000+0.0015)*F2*E2 -> 806.6408 | K3: =0 -> 0 | L3: =DATA!$B$8*((1+DATA!$B$9)^A2)*F3*E3 -> 42.161366 | M3: =B2*EXP(RATES!O4)*(DATA!$B$12) -> 1159.3568 | N3: =C2*EXP(RATES!O4)*(DATA!$B$12) -> 289.8392 | O3: =M3+N3 -> 1449.196 | P3: =O3*E3*F3 -> 1222.0016 | Q3: =RATES!G4 -> 0.9660529 | R3: =P3+L3+K3+J3+I3 -> 17132.335 | S3: =R3*Q3 -> 16550.742 | T3: =C2*EXP(RATES!O4)*(DATA!$B$6-DATA!$B$12) -> 165.6224 | U3: =B2*EXP(RATES!O4)*(DATA!$B$6-DATA!$B$12) -> 662.4896 | V3: =T3+U3 -> 828.112 | W3: =V3*E3*F3 -> 698.28665 | X3: =W3*BASE!Q3 -> 674.58185
A4: 2 | B4: =B3*EXP(RATES!O5)*(1-DATA!$B$6) -> 81233.889 | C4: =C3*EXP(RATES!O5)*(1-DATA!$B$6) -> 20308.472 | D4: =B4+C4 -> 101542.36 | E4: =E3*(1-'LIFE TABLE MALE'!D64/1000) -> 0.98498844 | F4: =F3*(1-0.15) -> 0.7225 | G4: =D4-20 -> 101522.36 | H4: =MAX(D4,DATA!$B$3) -> 101542.36 | I4: =G4*DATA!$B$7*F3*E4 -> 12749.79 | J4: =H4*'LIFE TABLE MALE'!D64/1000*F3*E3 -> 607.94764 | K4: =0 -> 0 | L4: =DATA!$B$8*((1+DATA!$B$9)^A3)*F4*E4 -> 36.294362 | M4: =B3*EXP(RATES!O5)*(DATA!$B$12) -> 1162.8573 | N4: =C3*EXP(RATES!O5)*(DATA!$B$12) -> 290.71433 | O4: =M4+N4 -> 1453.5716 | P4: =O4*E4*F4 -> 1034.4403 | Q4: =RATES!G5 -> 0.94195564 | R4: =P4+L4+K4+J4+I4 -> 14428.472 | S4: =R4*Q4 -> 13590.981 | T4: =C3*EXP(RATES!O5)*(DATA!$B$6-DATA!$B$12) -> 166.12247 | U4: =B3*EXP(RATES!O5)*(DATA!$B$6-DATA!$B$12) -> 664.48989 | V4: =T4+U4 -> 830.61237 | W4: =V4*E4*F4 -> 591.10874 | X4: =W4*BASE!Q4 -> 556.79821
A5: 3 | B5: =B4*EXP(RATES!O6)*(1-DATA!$B$6) -> 81258.803 | C5: =C4*EXP(RATES!O6)*(1-DATA!$B$6) -> 20314.701 | D5: =B5+C5 -> 101573.5 | E5: =E4*(1-'LIFE TABLE MALE'!D65/1000) -> 0.97729066 | F5: =F4*(1-0.15) -> 0.614125 | G5: =D5-20 -> 101553.5 | H5: =MAX(D5,DATA!$B$3) -> 101573.5 | I5: =G5*DATA!$B$7*F4*E5 -> 10755.925 | J5: =H5*'LIFE TABLE MALE'!D65/1000*F4*E4 -> 564.91611 | K5: =0 -> 0 | L5: =DATA!$B$8*((1+DATA!$B$9)^A4)*F5*E5 -> 31.221292 | M5: =B4*EXP(RATES!O6)*(DATA!$B$12) -> 1163.2139 | N5: =C4*EXP(RATES!O6)*(DATA!$B$12) -> 290.80349 | O5: =M5+N5 -> 1454.0174 | P5: =O5*E5*F5 -> 872.67019 | Q5: =RATES!G6 -> 0.92095017 | R5: =P5+L5+K5+J5+I5 -> 12224.733 | S5: =R5*Q5 -> 11258.37 | T5: =C4*EXP(RATES!O6)*(DATA!$B$6-DATA!$B$12) -> 166.17342 | U5: =B4*EXP(RATES!O6)*(DATA!$B$6-DATA!$B$12) -> 664.69368 | V5: =T5+U5 -> 830.86711 | W5: =V5*E5*F5 -> 498.66868 | X5: =W5*BASE!Q5 -> 459.249
A6: 4 | B6: =B5*EXP(RATES!O7)*(1-DATA!$B$6) -> 81219.667 | C6: =C5*EXP(RATES!O7)*(1-DATA!$B$6) -> 20304.917 | D6: =B6+C6 -> 101524.58 | E6: =E5*(1-'LIFE TABLE MALE'!D66/1000) -> 0.96882256 | F6: =F5*(1-0.15) -> 0.52200625 | G6: =D6-20 -> 101504.58 | H6: =MAX(D6,DATA!$B$3) -> 101524.58 | I6: =G6*DATA!$B$7*F5*E6 -> 9058.9515 | J6: =H6*'LIFE TABLE MALE'!D66/1000*F5*E5 -> 527.97553 | K6: =0 -> 0 | L6: =DATA!$B$8*((1+DATA!$B$9)^A5)*F6*E6 -> 26.834312 | M6: =B5*EXP(RATES!O7)*(DATA!$B$12) -> 1162.6537 | N6: =C5*EXP(RATES!O7)*(DATA!$B$12) -> 290.66343 | O6: =M6+N6 -> 1453.3171 | P6: =O6*E6*F6 -> 734.98816 | Q6: =RATES!G7 -> 0.90112326 | R6: =P6+L6+K6+J6+I6 -> 10348.75 | S6: =R6*Q6 -> 9325.499 | T6: =C5*EXP(RATES!O7)*(DATA!$B$6-DATA!$B$12) -> 166.09339 | U6: =B5*EXP(RATES!O7)*(DATA!$B$6-DATA!$B$12) -> 664.37355 | V6: =T6+U6 -> 830.46694 | W6: =V6*E6*F6 -> 419.99324 | X6: =W6*BASE!Q6 -> 378.46568
A7: 5 | B7: =B6*EXP(RATES!O8)*(1-DATA!$B$6) -> 81178.572 | C7: =C6*EXP(RATES!O8)*(1-DATA!$B$6) -> 20294.643 | D7: =B7+C7 -> 101473.22 | E7: =E6*(1-'LIFE TABLE MALE'!D67/1000) -> 0.95947081 | F7: =F6*(1-0.15) -> 0.44370531 | G7: =D7-20 -> 101453.22 | H7: =MAX(D7,DATA!$B$3) -> 101473.22 | I7: =G7*DATA!$B$7*F6*E7 -> 7621.9228 | J7: =H7*'LIFE TABLE MALE'!D67/1000*F6*E6 -> 495.35914 | K7: =0 -> 0 | L7: =DATA!$B$8*((1+DATA!$B$9)^A6)*F7*E7 -> 23.040775 | M7: =B6*EXP(RATES!O8)*(DATA!$B$12) -> 1162.0655 | N7: =C6*EXP(RATES!O8)*(DATA!$B$12) -> 290.51636 | O7: =M7+N7 -> 1452.5818 | P7: =O7*E7*F7 -> 618.39647 | Q7: =RATES!G8 -> 0.88174469 | R7: =P7+L7+K7+J7+I7 -> 8758.7192 | S7: =R7*Q7 -> 7722.9541 | T7: =C6*EXP(RATES!O8)*(DATA!$B$6-DATA!$B$12) -> 166.00935 | U7: =B6*EXP(RATES!O8)*(DATA!$B$6-DATA!$B$12) -> 664.0374 | V7: =T7+U7 -> 830.04675 | W7: =V7*E7*F7 -> 353.36941 | X7: =W7*BASE!Q7 -> 311.5816
A8: 6 | B8: =B7*EXP(RATES!O9)*(1-DATA!$B$6) -> 81192.731 | C8: =C7*EXP(RATES!O9)*(1-DATA!$B$6) -> 20298.183 | D8: =B8+C8 -> 101490.91 | E8: =E7*(1-'LIFE TABLE MALE'!D68/1000) -> 0.94911306 | F8: =F7*(1-0.15) -> 0.37714952 | G8: =D8-20 -> 101470.91 | H8: =MAX(D8,DATA!$B$3) -> 101490.91 | I8: =G8*DATA!$B$7*F7*E8 -> 6409.8138 | J8: =H8*'LIFE TABLE MALE'!D68/1000*F7*E7 -> 466.43064 | K8: =0 -> 0 | L8: =DATA!$B$8*((1+DATA!$B$9)^A7)*F8*E8 -> 19.760702 | M8: =B7*EXP(RATES!O9)*(DATA!$B$12) -> 1162.2681 | N8: =C7*EXP(RATES!O9)*(DATA!$B$12) -> 290.56703 | O8: =M8+N8 -> 1452.8352 | P8: =O8*E8*F8 -> 520.05329 | Q8: =RATES!G9 -> 0.86219592 | R8: =P8+L8+K8+J8+I8 -> 7416.0584 | S8: =R8*Q8 -> 6394.0953 | T8: =C7*EXP(RATES!O9)*(DATA!$B$6-DATA!$B$12) -> 166.03831 | U8: =B7*EXP(RATES!O9)*(DATA!$B$6-DATA!$B$12) -> 664.15322 | V8: =T8+U8 -> 830.19153 | W8: =V8*E8*F8 -> 297.17331 | X8: =W8*BASE!Q8 -> 256.22162
A9: 7 | B9: =B8*EXP(RATES!O10)*(1-DATA!$B$6) -> 81254.382 | C9: =C8*EXP(RATES!O10)*(1-DATA!$B$6) -> 20313.596 | D9: =B9+C9 -> 101567.98 | E9: =E8*(1-'LIFE TABLE MALE'!D69/1000) -> 0.93798162 | F9: =F8*(1-0.15) -> 0.32057709 | G9: =D9-20 -> 101547.98 | H9: =MAX(D9,DATA!$B$3) -> 101567.98 | I9: =G9*DATA!$B$7*F8*E9 -> 5388.5314 | J9: =H9*'LIFE TABLE MALE'!D69/1000*F8*E8 -> 426.40461 | K9: =0 -> 0 | L9: =DATA!$B$8*((1+DATA!$B$9)^A8)*F9*E9 -> 16.931594 | M9: =B8*EXP(RATES!O10)*(DATA!$B$12) -> 1163.1507 | N9: =C8*EXP(RATES!O10)*(DATA!$B$12) -> 290.78767 | O9: =M9+N9 -> 1453.9383 | P9: =O9*E9*F9 -> 437.19259 | Q9: =RATES!G10 -> 0.84258782 | R9: =P9+L9+K9+J9+I9 -> 6269.0602 | S9: =R9*Q9 -> 5282.2338 | T9: =C8*EXP(RATES!O10)*(DATA!$B$6-DATA!$B$12) -> 166.16438 | U9: =B8*EXP(RATES!O10)*(DATA!$B$6-DATA!$B$12) -> 664.65752 | V9: =T9+U9 -> 830.8219 | W9: =V9*E9*F9 -> 249.82434 | X9: =W9*BASE!Q9 -> 210.49895
A10: 8 | B10: =B9*EXP(RATES!O11)*(1-DATA!$B$6) -> 81365.273 | C10: =C9*EXP(RATES!O11)*(1-DATA!$B$6) -> 20341.318 | D10: =B10+C10 -> 101706.59 | E10: =E9*(1-'LIFE TABLE MALE'!D70/1000) -> 0.92597739 | F10: =F9*(1-0.15) -> 0.27249053 | G10: =D10-20 -> 101686.59 | H10: =MAX(D10,DATA!$B$3) -> 101706.59 | I10: =G10*DATA!$B$7*F9*E10 -> 4527.806 | J10: =H10*'LIFE TABLE MALE'!D70/1000*F9*E9 -> 391.39564 | K10: =0 -> 0 | L10: =DATA!$B$8*((1+DATA!$B$9)^A9)*F10*E10 -> 14.491822 | M10: =B9*EXP(RATES!O11)*(DATA!$B$12) -> 1164.7381 | N10: =C9*EXP(RATES!O11)*(DATA!$B$12) -> 291.18452 | O10: =M10+N10 -> 1455.9226 | P10: =O10*E10*F10 -> 367.35848 | Q10: =RATES!G11 -> 0.82292781 | R10: =P10+L10+K10+J10+I10 -> 5301.0519 | S10: =R10*Q10 -> 4362.383 | T10: =C9*EXP(RATES!O11)*(DATA!$B$6-DATA!$B$12) -> 166.39115 | U10: =B9*EXP(RATES!O11)*(DATA!$B$6-DATA!$B$12) -> 665.56461 | V10: =T10+U10 -> 831.95576 | W10: =V10*E10*F10 -> 209.91913 | X10: =W10*BASE!Q10 -> 172.74829
A11: 9 | B11: =B10*EXP(RATES!O12)*(1-DATA!$B$6) -> 81523.24 | C11: =C10*EXP(RATES!O12)*(1-DATA!$B$6) -> 20380.81 | D11: =B11+C11 -> 101904.05 | E11: =E10*(1-'LIFE TABLE MALE'!D71/1000) -> 0.91303686 | F11: =F10*(1-0.15) -> 0.23161695 | G11: =D11-20 -> 101884.05 | H11: =MAX(D11,DATA!$B$3) -> 101904.05 | I11: =G11*DATA!$B$7*F10*E11 -> 3802.2194 | J11: =H11*'LIFE TABLE MALE'!D71/1000*F10*E10 -> 359.33104 | K11: =0 -> 0 | L11: =DATA!$B$8*((1+DATA!$B$9)^A10)*F11*E11 -> 12.388822 | M11: =B10*EXP(RATES!O12)*(DATA!$B$12) -> 1166.9993 | N11: =C10*EXP(RATES!O12)*(DATA!$B$12) -> 291.74984 | O11: =M11+N11 -> 1458.7492 | P11: =O11*E11*F11 -> 308.48871 | Q11: =RATES!G12 -> 0.8032639 | R11: =P11+L11+K11+J11+I11 -> 4482.428 | S11: =R11*Q11 -> 3600.5726 | T11: =C10*EXP(RATES!O12)*(DATA!$B$6-DATA!$B$12) -> 166.71419 | U11: =B10*EXP(RATES!O12)*(DATA!$B$6-DATA!$B$12) -> 666.85677 | V11: =T11+U11 -> 833.57096 | W11: =V11*E11*F11 -> 176.27926 | X11: =W11*BASE!Q11 -> 141.59877
A12: 10 | B12: =B11*EXP(RATES!O13)*(1-DATA!$B$6) -> 81742.12 | C12: =C11*EXP(RATES!O13)*(1-DATA!$B$6) -> 20435.53 | D12: =B12+C12 -> 102177.65 | E12: =E11*(1-'LIFE TABLE MALE'!D72/1000) -> 0.89873866 | F12: =F11*(1-0.15) -> 0.1968744 | G12: =D12-20 -> 102157.65 | H12: =MAX(D12,DATA!$B$3) -> 102177.65 | I12: =G12*DATA!$B$7*F11*E12 -> 3189.818 | J12: =H12*'LIFE TABLE MALE'!D72/1000*F11*E11 -> 338.38235 | K12: =0 -> 0 | L12: =DATA!$B$8*((1+DATA!$B$9)^A11)*F12*E12 -> 10.572903 | M12: =B11*EXP(RATES!O13)*(DATA!$B$12) -> 1170.1326 | N12: =C11*EXP(RATES!O13)*(DATA!$B$12) -> 292.53315 | O12: =M12+N12 -> 1462.6657 | P12: =O12*E12*F12 -> 258.80209 | Q12: =RATES!G13 -> 0.78348852 | R12: =P12+L12+K12+J12+I12 -> 3797.5754 | S12: =R12*Q12 -> 2975.3567 | T12: =C11*EXP(RATES!O13)*(DATA!$B$6-DATA!$B$12) -> 167.1618 | U12: =B11*EXP(RATES!O13)*(DATA!$B$6-DATA!$B$12) -> 668.6472 | V12: =T12+U12 -> 835.809 | W12: =V12*E12*F12 -> 147.88691 | X12: =W12*BASE!Q12 -> 115.86769
A13: 11 | B13: =B12*EXP(RATES!O14)*(1-DATA!$B$6) -> 82068.024 | C13: =C12*EXP(RATES!O14)*(1-DATA!$B$6) -> 20517.006 | D13: =B13+C13 -> 102585.03 | E13: =E12*(1-'LIFE TABLE MALE'!D73/1000) -> 0.88303448 | F13: =F12*(1-0.15) -> 0.16734324 | G13: =D13-20 -> 102565.03 | H13: =MAX(D13,DATA!$B$3) -> 102585.03 | I13: =G13*DATA!$B$7*F12*E13 -> 2674.5917 | J13: =H13*'LIFE TABLE MALE'!D73/1000*F12*E12 -> 317.16742 | K13: =0 -> 0 | L13: =DATA!$B$8*((1+DATA!$B$9)^A12)*F13*E13 -> 9.0065314 | M13: =B12*EXP(RATES!O14)*(DATA!$B$12) -> 1174.7979 | N13: =C12*EXP(RATES!O14)*(DATA!$B$12) -> 293.69947 | O13: =M13+N13 -> 1468.4974 | P13: =O13*E13*F13 -> 216.99964 | Q13: =RATES!G14 -> 0.76320888 | R13: =P13+L13+K13+J13+I13 -> 3217.7653 | S13: =R13*Q13 -> 2455.827 | T13: =C12*EXP(RATES!O14)*(DATA!$B$6-DATA!$B$12) -> 167.82827 | U13: =B12*EXP(RATES!O14)*(DATA!$B$6-DATA!$B$12) -> 671.31308 | V13: =T13+U13 -> 839.14135 | W13: =V13*E13*F13 -> 123.99979 | X13: =W13*BASE!Q13 -> 94.637744
A14: 12 | B14: =B13*EXP(RATES!O15)*(1-DATA!$B$6) -> 82258.657 | C14: =C13*EXP(RATES!O15)*(1-DATA!$B$6) -> 20564.664 | D14: =B14+C14 -> 102823.32 | E14: =E13*(1-'LIFE TABLE MALE'!D74/1000) -> 0.8656056 | F14: =F13*(1-0.15) -> 0.14224176 | G14: =D14-20 -> 102803.32 | H14: =MAX(D14,DATA!$B$3) -> 102823.32 | I14: =G14*DATA!$B$7*F13*E14 -> 2233.7093 | J14: =H14*'LIFE TABLE MALE'!D74/1000*F13*E13 -> 299.89496 | K14: =0 -> 0 | L14: =DATA!$B$8*((1+DATA!$B$9)^A13)*F14*E14 -> 7.6545394 | M14: =B13*EXP(RATES!O15)*(DATA!$B$12) -> 1177.5268 | N14: =C13*EXP(RATES!O15)*(DATA!$B$12) -> 294.3817 | O14: =M14+N14 -> 1471.9085 | P14: =O14*E14*F14 -> 181.22912 | Q14: =RATES!G15 -> 0.74468847 | R14: =P14+L14+K14+J14+I14 -> 2722.4879 | S14: =R14*Q14 -> 2027.4053 | T14: =C13*EXP(RATES!O15)*(DATA!$B$6-DATA!$B$12) -> 168.21811 | U14: =B13*EXP(RATES!O15)*(DATA!$B$6-DATA!$B$12) -> 672.87245 | V14: =T14+U14 -> 841.09056 | W14: =V14*E14*F14 -> 103.5595 | X14: =W14*BASE!Q14 -> 77.119562
A15: 13 | B15: =B14*EXP(RATES!O16)*(1-DATA!$B$6) -> 82502.039 | C15: =C14*EXP(RATES!O16)*(1-DATA!$B$6) -> 20625.51 | D15: =B15+C15 -> 103127.55 | E15: =E14*(1-'LIFE TABLE MALE'!D75/1000) -> 0.84680312 | F15: =F14*(1-0.15) -> 0.12090549 | G15: =D15-20 -> 103107.55 | H15: =MAX(D15,DATA!$B$3) -> 103127.55 | I15: =G15*DATA!$B$7*F14*E15 -> 1862.9074 | J15: =H15*'LIFE TABLE MALE'!D75/1000*F14*E14 -> 275.81449 | K15: =0 -> 0 | L15: =DATA!$B$8*((1+DATA!$B$9)^A14)*F15*E15 -> 6.4923294 | M15: =B14*EXP(RATES!O16)*(DATA!$B$12) -> 1181.0108 | N15: =C14*EXP(RATES!O16)*(DATA!$B$12) -> 295.2527 | O15: =M15+N15 -> 1476.2635 | P15: =O15*E15*F15 -> 151.1445 | Q15: =RATES!G16 -> 0.72615681 | R15: =P15+L15+K15+J15+I15 -> 2296.3588 | S15: =R15*Q15 -> 1667.5166 | T15: =C14*EXP(RATES!O16)*(DATA!$B$6-DATA!$B$12) -> 168.71583 | U15: =B14*EXP(RATES!O16)*(DATA!$B$6-DATA!$B$12) -> 674.8633 | V15: =T15+U15 -> 843.57913 | W15: =V15*E15*F15 -> 86.368288 | X15: =W15*BASE!Q15 -> 62.716921
... A51: 49 | B51: =B50*EXP(RATES!O52)*(1-DATA!$B$6) -> 102111.48 | C51: =C50*EXP(RATES!O52)*(1-DATA!$B$6) -> 25527.869 | D51: =B51+C51 -> 127639.35 | E51: =E50*(1-'LIFE TABLE MALE'!D111/1000) -> 2.6181425e-06 | F51: =F50*(1-0.15) -> 0.00034795843 | G51: =D51-20 -> 127619.35 | H51: =MAX(D51,DATA!$B$3) -> 127639.35 | I51: =G51*DATA!$B$7*F50*E51 -> 2.0516794e-05 | J51: =H51*'LIFE TABLE MALE'!D111/1000*F50*E50 -> 0.00033685008 | K51: =0 -> 0 | L51: =DATA!$B$8*((1+DATA!$B$9)^A50)*F51*E51 -> 1.1784167e-07 | M51: =B50*EXP(RATES!O52)*(DATA!$B$12) -> 1461.7185 | N51: =C50*EXP(RATES!O52)*(DATA!$B$12) -> 365.42962 | O51: =M51+N51 -> 1827.1481 | P51: =O51*E51*F51 -> 1.6645406e-06 | Q51: =RATES!G52 -> 0.26340215 | R51: =P51+L51+K51+J51+I51 -> 0.00035914926 | S51: =R51*Q51 -> 9.4600687e-05 | T51: =C50*EXP(RATES!O52)*(DATA!$B$6-DATA!$B$12) -> 208.81693 | U51: =B50*EXP(RATES!O52)*(DATA!$B$6-DATA!$B$12) -> 835.2677 | V51: =T51+U51 -> 1044.0846 | W51: =V51*E51*F51 -> 9.5116607e-07 | X51: =W51*BASE!Q51 -> 2.5053919e-07
A52: 50 | B52: =B51*EXP(RATES!O53)*(1-DATA!$B$6) -> 103172 | C52: =C51*EXP(RATES!O53)*(1-DATA!$B$6) -> 25793 | D52: =B52+C52 -> 128965 | E52: =E51*(1-'LIFE TABLE MALE'!D112/1000) -> 6.7846284e-07 | F52: =F51*(1-0.15) -> 0.00029576466 | G52: =D52-20 -> 128945 | H52: =MAX(D52,DATA!$B$3) -> 128965 | I52: =G52*DATA!$B$7*F51*E52 -> 4.5661396e-06 | J52: =H52*'LIFE TABLE MALE'!D112/1000*F51*E51 -> 8.7042076e-05 | K52: =E52*D52*F52 -> 2.5878805e-05 | L52: =DATA!$B$8*((1+DATA!$B$9)^A51)*F52*E52 -> 2.6475903e-08 | M52: =B51*EXP(RATES!O53)*(DATA!$B$12) -> 1476.8998 | N52: =C51*EXP(RATES!O53)*(DATA!$B$12) -> 369.22495 | O52: =M52+N52 -> 1846.1247 | P52: =O52*E52*F52 -> 3.7045324e-07 | Q52: =RATES!G53 -> 0.25495931 | R52: =P52+L52+K52+J52+I52 -> 0.00011788395 | S52: =R52*Q52 -> 3.0055611e-05 | T52: =C51*EXP(RATES!O53)*(DATA!$B$6-DATA!$B$12) -> 210.98568 | U52: =B51*EXP(RATES!O53)*(DATA!$B$6-DATA!$B$12) -> 843.94273 | V52: =T52+U52 -> 1054.9284 | W52: =V52*E52*F52 -> 2.1168756e-07 | X52: =W52*BASE!Q52 -> 5.3971716e-08
P56: LIABILITIES | Q56: =SUM(S3:S52) -> 94498.608 | T56: BEL COMPONENTS
P57: BOF | Q57: =DATA!B2-Q56 -> 5501.3923 | T57: DEATH | U57: =SUMPRODUCT(J3:J52,Q3:Q52) -> 6566.5753
T58: LAPSE | U58: =SUMPRODUCT(I3:I52,Q3:Q52) -> 81104.467
P59: DURATION | Q59: =SUMPRODUCT(S3:S52,A3:A52)/SUM(S3:S52) -> 5.6058654 | T59: EXPENSES | U59: =SUMPRODUCT(L3:L52,Q3:Q52) -> 247.24602
T60: COMMISSIONS | U60: =SUMPRODUCT(P3:P52,Q3:Q52) -> 6580.3198

Sheet LAPSE STRESS UP 
B1: EQUITY | C1: PROPERTY | D1: ASSET | E1: SURVIVAL PROB | F1: non LAPSE PROB | G1: C lapse | H1: C death | I1: LIAB LAPSE | J1: LIAB DEATH | K1: LIAB SURVIVE | L1: EXPENSES | M1: EQ COMMISSIONS | N1: PR COMMISSIONS | O1: TOT COMMISSIONS | P1: COMMISSIONS LIAB | Q1: DISCOUNTS | R1: TOT LIAB | S1: TOT LIAB DISC | T1: PROFIT PR | U1: PROFIT EQ | V1: TOT PROFIT | W1: PROFIT LIAB | X1: PROFIT LIAB DISCOUNTED
A2: 0 | B2: =DATA!B2*0.8 -> 80000 | C2: =DATA!B2*0.2 -> 20000 | D2: =B2+C2 -> 100000 | E2: =1 -> 1 | F2: =1 -> 1 | G2: =D2-20 -> 99980 | H2: =MAX(D2,DATA!$B$3) -> 100000 | M2: =B2 -> 80000 | N2: =C2 -> 20000 | Q2: =RATES!G3 -> 1
A3: 1 | B3: =B2*EXP(RATES!O4)*(1-DATA!$B$6) -> 80989.354 | C3: =C2*EXP(RATES!O4)*(1-DATA!$B$6) -> 20247.338 | D3: =B3+C3 -> 101236.69 | E3: =E2*(1-'LIFE TABLE MALE'!D63/1000) -> 0.99353213 | F3: =F2*(1-0.15*1.5) -> 0.775 | G3: =D3-20 -> 101216.69 | H3: =MAX(D3,DATA!$B$3) -> 101236.69 | I3: =G3*DATA!$B$7*1.5*F2*E3 -> 22626.458 | J3: =H3*'LIFE TABLE MALE'!D63/1000*F2*E2 -> 654.78576 | K3: =0 -> 0 | L3: =DATA!$B$8*((1+DATA!$B$9)^A2)*F3*E3 -> 38.49937 | M3: =B2*EXP(RATES!O4)*(DATA!$B$12) -> 1159.3568 | N3: =C2*EXP(RATES!O4)*(DATA!$B$12) -> 289.8392 | O3: =M3+N3 -> 1449.196 | P3: =O3*E3*F3 -> 1115.8627 | Q3: =RATES!G4 -> 0.9660529 | R3: =P3+L3+K3+J3+I3 -> 24435.606 | S3: =R3*Q3 -> 23606.088 | T3: =C2*EXP(RATES!O4)*(DATA!$B$6-DATA!$B$12) -> 165.6224 | U3: =B2*EXP(RATES!O4)*(DATA!$B$6-DATA!$B$12) -> 662.4896 | V3: =T3+U3 -> 828.112 | W3: =V3*E3*F3 -> 637.63581 | X3: =W3*BASE!Q3 -> 615.98992
A4: 2 | B4: =B3*EXP(RATES!O5)*(1-DATA!$B$6) -> 81233.889 | C4: =C3*EXP(RATES!O5)*(1-DATA!$B$6) -> 20308.472 | D4: =B4+C4 -> 101542.36 | E4: =E3*(1-'LIFE TABLE MALE'!D64/1000) -> 0.98647779 | F4: =F3*(1-0.15*1.5) -> 0.600625 | G4: =D4-20 -> 101522.36 | H4: =MAX(D4,DATA!$B$3) -> 101542.36 | I4: =G4*DATA!$B$7*1.5*F3*E4 -> 17463.579 | J4: =H4*'LIFE TABLE MALE'!D64/1000*F3*E3 -> 555.14334 | K4: =0 -> 0 | L4: =DATA!$B$8*((1+DATA!$B$9)^A3)*F4*E4 -> 30.217664 | M4: =B3*EXP(RATES!O5)*(DATA!$B$12) -> 1162.8573 | N4: =C3*EXP(RATES!O5)*(DATA!$B$12) -> 290.71433 | O4: =M4+N4 -> 1453.5716 | P4: =O4*E4*F4 -> 861.24588 | Q4: =RATES!G5 -> 0.94195564 | R4: =P4+L4+K4+J4+I4 -> 18910.186 | S4: =R4*Q4 -> 17812.556 | T4: =C3*EXP(RATES!O5)*(DATA!$B$6-DATA!$B$12) -> 166.12247 | U4: =B3*EXP(RATES!O5)*(DATA!$B$6-DATA!$B$12) -> 664.48989 | V4: =T4+U4 -> 830.61237 | W4: =V4*E4*F4 -> 492.14051 | X4: =W4*BASE!Q4 -> 463.57452
A5: 3 | B5: =B4*EXP(RATES!O6)*(1-DATA!$B$6) -> 81258.803 | C5: =C4*EXP(RATES!O6)*(1-DATA!$B$6) -> 20314.701 | D5: =B5+C5 -> 101573.5 | E5: =E4*(1-'LIFE TABLE MALE'!D65/1000) -> 0.97876837 | F5: =F4*(1-0.15*1.5) -> 0.46548438 | G5: =D5-20 -> 101553.5 | H5: =MAX(D5,DATA!$B$3) -> 101573.5 | I5: =G5*DATA!$B$7*1.5*F4*E5 -> 13432.621 | J5: =H5*'LIFE TABLE MALE'!D65/1000*F4*E4 -> 470.33326 | K5: =0 -> 0 | L5: =DATA!$B$8*((1+DATA!$B$9)^A4)*F5*E5 -> 23.700384 | M5: =B4*EXP(RATES!O6)*(DATA!$B$12) -> 1163.2139 | N5: =C4*EXP(RATES!O6)*(DATA!$B$12) -> 290.80349 | O5: =M5+N5 -> 1454.0174 | P5: =O5*E5*F5 -> 662.45235 | Q5: =RATES!G6 -> 0.92095017 | R5: =P5+L5+K5+J5+I5 -> 14589.107 | S5: =R5*Q5 -> 13435.841 | T5: =C4*EXP(RATES!O6)*(DATA!$B$6-DATA!$B$12) -> 166.17342 | U5: =B4*EXP(RATES!O6)*(DATA!$B$6-DATA!$B$12) -> 664.69368 | V5: =T5+U5 -> 830.86711 | W5: =V5*E5*F5 -> 378.5442 | X5: =W5*BASE!Q5 -> 348.62035
A6: 4 | B6: =B5*EXP(RATES!O7)*(1-DATA!$B$6) -> 81219.667 | C6: =C5*EXP(RATES!O7)*(1-DATA!$B$6) -> 20304.917 | D6: =B6+C6 -> 101524.58 | E6: =E5*(1-'LIFE TABLE MALE'!D66/1000) -> 0.97028747 | F6: =F5*(1-0.15*1.5) -> 0.36075039 | G6: =D6-20 -> 101504.58 | H6: =MAX(D6,DATA!$B$3) -> 101524.58 | I6: =G6*DATA!$B$7*1.5*F5*E6 -> 10315.106 | J6: =H6*'LIFE TABLE MALE'!D66/1000*F5*E5 -> 400.79132 | K6: =0 -> 0 | L6: =DATA!$B$8*((1+DATA!$B$9)^A5)*F6*E6 -> 18.572816 | M6: =B5*EXP(RATES!O7)*(DATA!$B$12) -> 1162.6537 | N6: =C5*EXP(RATES!O7)*(DATA!$B$12) -> 290.66343 | O6: =M6+N6 -> 1453.3171 | P6: =O6*E6*F6 -> 508.7069 | Q6: =RATES!G7 -> 0.90112326 | R6: =P6+L6+K6+J6+I6 -> 11243.177 | S6: =R6*Q6 -> 10131.489 | T6: =C5*EXP(RATES!O7)*(DATA!$B$6-DATA!$B$12) -> 166.09339 | U6: =B5*EXP(RATES!O7)*(DATA!$B$6-DATA!$B$12) -> 664.37355 | V6: =T6+U6 -> 830.46694 | W6: =V6*E6*F6 -> 290.68966 | X6: =W6*BASE!Q6 -> 261.94721
A7: 5 | B7: =B6*EXP(RATES!O8)*(1-DATA!$B$6) -> 81178.572 | C7: =C6*EXP(RATES!O8)*(1-DATA!$B$6) -> 20294.643 | D7: =B7+C7 -> 101473.22 | E7: =E6*(1-'LIFE TABLE MALE'!D67/1000) -> 0.96092158 | F7: =F6*(1-0.15*1.5) -> 0.27958155 | G7: =D7-20 -> 101453.22 | H7: =MAX(D7,DATA!$B$3) -> 101473.22 | I7: =G7*DATA!$B$7*1.5*F6*E7 -> 7913.0351 | J7: =H7*'LIFE TABLE MALE'!D67/1000*F6*E6 -> 342.85261 | K7: =0 -> 0 | L7: =DATA!$B$8*((1+DATA!$B$9)^A6)*F7*E7 -> 14.540092 | M7: =B6*EXP(RATES!O8)*(DATA!$B$12) -> 1162.0655 | N7: =C6*EXP(RATES!O8)*(DATA!$B$12) -> 290.51636 | O7: =M7+N7 -> 1452.5818 | P7: =O7*E7*F7 -> 390.24474 | Q7: =RATES!G8 -> 0.88174469 | R7: =P7+L7+K7+J7+I7 -> 8660.6725 | S7: =R7*Q7 -> 7636.502 | T7: =C6*EXP(RATES!O8)*(DATA!$B$6-DATA!$B$12) -> 166.00935 | U7: =B6*EXP(RATES!O8)*(DATA!$B$6-DATA!$B$12) -> 664.0374 | V7: =T7+U7 -> 830.04675 | W7: =V7*E7*F7 -> 222.997 | X7: =W7*BASE!Q7 -> 196.62642
A8: 6 | B8: =B7*EXP(RATES!O9)*(1-DATA!$B$6) -> 81192.731 | C8: =C7*EXP(RATES!O9)*(1-DATA!$B$6) -> 20298.183 | D8: =B8+C8 -> 101490.91 | E8: =E7*(1-'LIFE TABLE MALE'!D68/1000) -> 0.95054817 | F8: =F7*(1-0.15*1.5) -> 0.2166757 | G8: =D8-20 -> 101470.91 | H8: =MAX(D8,DATA!$B$3) -> 101490.91 | I8: =G8*DATA!$B$7*1.5*F7*E8 -> 6067.4574 | J8: =H8*'LIFE TABLE MALE'!D68/1000*F7*E7 -> 294.34532 | K8: =0 -> 0 | L8: =DATA!$B$8*((1+DATA!$B$9)^A7)*F8*E8 -> 11.369862 | M8: =B7*EXP(RATES!O9)*(DATA!$B$12) -> 1162.2681 | N8: =C7*EXP(RATES!O9)*(DATA!$B$12) -> 290.56703 | O8: =M8+N8 -> 1452.8352 | P8: =O8*E8*F8 -> 299.22694 | Q8: =RATES!G9 -> 0.86219592 | R8: =P8+L8+K8+J8+I8 -> 6672.3995 | S8: =R8*Q8 -> 5752.9156 | T8: =C7*EXP(RATES!O9)*(DATA!$B$6-DATA!$B$12) -> 166.03831 | U8: =B7*EXP(RATES!O9)*(DATA!$B$6-DATA!$B$12) -> 664.15322 | V8: =T8+U8 -> 830.19153 | W8: =V8*E8*F8 -> 170.98682 | X8: =W8*BASE!Q8 -> 147.42414
A9: 7 | B9: =B8*EXP(RATES!O10)*(1-DATA!$B$6) -> 81254.382 | C9: =C8*EXP(RATES!O10)*(1-DATA!$B$6) -> 20313.596 | D9: =B9+C9 -> 101567.98 | E9: =E8*(1-'LIFE TABLE MALE'!D69/1000) -> 0.93939989 | F9: =F8*(1-0.15*1.5) -> 0.16792367 | G9: =D9-20 -> 101547.98 | H9: =MAX(D9,DATA!$B$3) -> 101567.98 | I9: =G9*DATA!$B$7*1.5*F8*E9 -> 4650.6592 | J9: =H9*'LIFE TABLE MALE'!D69/1000*F8*E8 -> 245.3436 | K9: =0 -> 0 | L9: =DATA!$B$8*((1+DATA!$B$9)^A8)*F9*E9 -> 8.8824641 | M9: =B8*EXP(RATES!O10)*(DATA!$B$12) -> 1163.1507 | N9: =C8*EXP(RATES!O10)*(DATA!$B$12) -> 290.78767 | O9: =M9+N9 -> 1453.9383 | P9: =O9*E9*F9 -> 229.3551 | Q9: =RATES!G10 -> 0.84258782 | R9: =P9+L9+K9+J9+I9 -> 5134.2404 | S9: =R9*Q9 -> 4326.0484 | T9: =C8*EXP(RATES!O10)*(DATA!$B$6-DATA!$B$12) -> 166.16438 | U9: =B8*EXP(RATES!O10)*(DATA!$B$6-DATA!$B$12) -> 664.65752 | V9: =T9+U9 -> 830.8219 | W9: =V9*E9*F9 -> 131.06006 | X9: =W9*BASE!Q9 -> 110.42961
A10: 8 | B10: =B9*EXP(RATES!O11)*(1-DATA!$B$6) -> 81365.273 | C10: =C9*EXP(RATES!O11)*(1-DATA!$B$6) -> 20341.318 | D10: =B10+C10 -> 101706.59 | E10: =E9*(1-'LIFE TABLE MALE'!D70/1000) -> 0.92737751 | F10: =F9*(1-0.15*1.5) -> 0.13014084 | G10: =D10-20 -> 101686.59 | H10: =MAX(D10,DATA!$B$3) -> 101706.59 | I10: =G10*DATA!$B$7*1.5*F9*E10 -> 3562.9907 | J10: =H10*'LIFE TABLE MALE'!D70/1000*F9*E9 -> 205.32962 | K10: =0 -> 0 | L10: =DATA!$B$8*((1+DATA!$B$9)^A9)*F10*E10 -> 6.931726 | M10: =B9*EXP(RATES!O11)*(DATA!$B$12) -> 1164.7381 | N10: =C9*EXP(RATES!O11)*(DATA!$B$12) -> 291.18452 | O10: =M10+N10 -> 1455.9226 | P10: =O10*E10*F10 -> 175.71485 | Q10: =RATES!G11 -> 0.82292781 | R10: =P10+L10+K10+J10+I10 -> 3950.9669 | S10: =R10*Q10 -> 3251.3605 | T10: =C9*EXP(RATES!O11)*(DATA!$B$6-DATA!$B$12) -> 166.39115 | U10: =B9*EXP(RATES!O11)*(DATA!$B$6-DATA!$B$12) -> 665.56461 | V10: =T10+U10 -> 831.95576 | W10: =V10*E10*F10 -> 100.40848 | X10: =W10*BASE!Q10 -> 82.628934
A11: 9 | B11: =B10*EXP(RATES!O12)*(1-DATA!$B$6) -> 81523.24 | C11: =C10*EXP(RATES!O12)*(1-DATA!$B$6) -> 20380.81 | D11: =B11+C11 -> 101904.05 | E11: =E10*(1-'LIFE TABLE MALE'!D71/1000) -> 0.91441742 | F11: =F10*(1-0.15*1.5) -> 0.10085915 | G11: =D11-20 -> 101884.05 | H11: =MAX(D11,DATA!$B$3) -> 101904.05 | I11: =G11*DATA!$B$7*1.5*F10*E11 -> 2728.0155 | J11: =H11*'LIFE TABLE MALE'!D71/1000*F10*E10 -> 171.87517 | K11: =0 -> 0 | L11: =DATA!$B$8*((1+DATA!$B$9)^A10)*F11*E11 -> 5.402953 | M11: =B10*EXP(RATES!O12)*(DATA!$B$12) -> 1166.9993 | N11: =C10*EXP(RATES!O12)*(DATA!$B$12) -> 291.74984 | O11: =M11+N11 -> 1458.7492 | P11: =O11*E11*F11 -> 134.5366 | Q11: =RATES!G12 -> 0.8032639 | R11: =P11+L11+K11+J11+I11 -> 3039.8302 | S11: =R11*Q11 -> 2441.7858 | T11: =C10*EXP(RATES!O12)*(DATA!$B$6-DATA!$B$12) -> 166.71419 | U11: =B10*EXP(RATES!O12)*(DATA!$B$6-DATA!$B$12) -> 666.85677 | V11: =T11+U11 -> 833.57096 | W11: =V11*E11*F11 -> 76.878056 | X11: =W11*BASE!Q11 -> 61.753366
A12: 10 | B12: =B11*EXP(RATES!O13)*(1-DATA!$B$6) -> 81742.12 | C12: =C11*EXP(RATES!O13)*(1-DATA!$B$6) -> 20435.53 | D12: =B12+C12 -> 102177.65 | E12: =E11*(1-'LIFE TABLE MALE'!D72/1000) -> 0.9000976 | F12: =F11*(1-0.15*1.5) -> 0.078165845 | G12: =D12-20 -> 102157.65 | H12: =MAX(D12,DATA!$B$3) -> 102177.65 | I12: =G12*DATA!$B$7*1.5*F11*E12 -> 2086.6919 | J12: =H12*'LIFE TABLE MALE'!D72/1000*F11*E11 -> 147.57367 | K12: =0 -> 0 | L12: =DATA!$B$8*((1+DATA!$B$9)^A11)*F12*E12 -> 4.2041497 | M12: =B11*EXP(RATES!O13)*(DATA!$B$12) -> 1170.1326 | N12: =C11*EXP(RATES!O13)*(DATA!$B$12) -> 292.53315 | O12: =M12+N12 -> 1462.6657 | P12: =O12*E12*F12 -> 102.90861 | Q12: =RATES!G13 -> 0.78348852 | R12: =P12+L12+K12+J12+I12 -> 2341.3784 | S12: =R12*Q12 -> 1834.4431 | T12: =C11*EXP(RATES!O13)*(DATA!$B$6-DATA!$B$12) -> 167.1618 | U12: =B11*EXP(RATES!O13)*(DATA!$B$6-DATA!$B$12) -> 668.6472 | V12: =T12+U12 -> 835.809 | W12: =V12*E12*F12 -> 58.804921 | X12: =W12*BASE!Q12 -> 46.07298
A13: 11 | B13: =B12*EXP(RATES!O14)*(1-DATA!$B$6) -> 82068.024 | C13: =C12*EXP(RATES!O14)*(1-DATA!$B$6) -> 20517.006 | D13: =B13+C13 -> 102585.03 | E13: =E12*(1-'LIFE TABLE MALE'!D73/1000) -> 0.88436967 | F13: =F12*(1-0.15*1.5) -> 0.06057853 | G13: =D13-20 -> 102565.03 | H13: =MAX(D13,DATA!$B$3) -> 102585.03 | I13: =G13*DATA!$B$7*1.5*F12*E13 -> 1595.2645 | J13: =H13*'LIFE TABLE MALE'!D73/1000*F12*E12 -> 126.11667 | K13: =0 -> 0 | L13: =DATA!$B$8*((1+DATA!$B$9)^A12)*F13*E13 -> 3.265309 | M13: =B12*EXP(RATES!O14)*(DATA!$B$12) -> 1174.7979 | N13: =C12*EXP(RATES!O14)*(DATA!$B$12) -> 293.69947 | O13: =M13+N13 -> 1468.4974 | P13: =O13*E13*F13 -> 78.673005 | Q13: =RATES!G14 -> 0.76320888 | R13: =P13+L13+K13+J13+I13 -> 1803.3195 | S13: =R13*Q13 -> 1376.3094 | T13: =C12*EXP(RATES!O14)*(DATA!$B$6-DATA!$B$12) -> 167.82827 | U13: =B12*EXP(RATES!O14)*(DATA!$B$6-DATA!$B$12) -> 671.31308 | V13: =T13+U13 -> 839.14135 | W13: =V13*E13*F13 -> 44.956003 | X13: =W13*BASE!Q13 -> 34.31082
A14: 12 | B14: =B13*EXP(RATES!O15)*(1-DATA!$B$6) -> 82258.657 | C14: =C13*EXP(RATES!O15)*(1-DATA!$B$6) -> 20564.664 | D14: =B14+C14 -> 102823.32 | E14: =E13*(1-'LIFE TABLE MALE'!D74/1000) -> 0.86691444 | F14: =F13*(1-0.15*1.5) -> 0.04694836 | G14: =D14-20 -> 102803.32 | H14: =MAX(D14,DATA!$B$3) -> 102823.32 | I14: =G14*DATA!$B$7*1.5*F13*E14 -> 1214.7436 | J14: =H14*'LIFE TABLE MALE'!D74/1000*F13*E13 -> 108.72662 | K14: =0 -> 0 | L14: =DATA!$B$8*((1+DATA!$B$9)^A13)*F14*E14 -> 2.5302799 | M14: =B13*EXP(RATES!O15)*(DATA!$B$12) -> 1177.5268 | N14: =C13*EXP(RATES!O15)*(DATA!$B$12) -> 294.3817 | O14: =M14+N14 -> 1471.9085 | P14: =O14*E14*F14 -> 59.906986 | Q14: =RATES!G15 -> 0.74468847 | R14: =P14+L14+K14+J14+I14 -> 1385.9075 | S14: =R14*Q14 -> 1032.0693 | T14: =C13*EXP(RATES!O15)*(DATA!$B$6-DATA!$B$12) -> 168.21811 | U14: =B13*EXP(RATES!O15)*(DATA!$B$6-DATA!$B$12) -> 672.87245 | V14: =T14+U14 -> 841.09056 | W14: =V14*E14*F14 -> 34.232564 | X14: =W14*BASE!Q14 -> 25.492596
... A51: 49 | B51: =B50*EXP(RATES!O52)*(1-DATA!$B$6) -> 102111.48 | C51: =C50*EXP(RATES!O52)*(1-DATA!$B$6) -> 25527.869 | D51: =B51+C51 -> 127639.35 | E51: =E50*(1-'LIFE TABLE MALE'!D111/1000) -> 2.6221013e-06 | F51: =F50*(1-0.15*1.5) -> 3.7651599e-06 | G51: =D51-20 -> 127619.35 | H51: =MAX(D51,DATA!$B$3) -> 127639.35 | I51: =G51*DATA!$B$7*1.5*F50*E51 -> 3.6578864e-07 | J51: =H51*'LIFE TABLE MALE'!D111/1000*F50*E50 -> 4.0037424e-06 | K51: =0 -> 0 | L51: =DATA!$B$8*((1+DATA!$B$9)^A50)*F51*E51 -> 1.2770595e-09 | M51: =B50*EXP(RATES!O52)*(DATA!$B$12) -> 1461.7185 | N51: =C50*EXP(RATES!O52)*(DATA!$B$12) -> 365.42962 | O51: =M51+N51 -> 1827.1481 | P51: =O51*E51*F51 -> 1.8038758e-08 | Q51: =RATES!G52 -> 0.26340215 | R51: =P51+L51+K51+J51+I51 -> 4.3888468e-06 | S51: =R51*Q51 -> 1.1560317e-06 | T51: =C50*EXP(RATES!O52)*(DATA!$B$6-DATA!$B$12) -> 208.81693 | U51: =B50*EXP(RATES!O52)*(DATA!$B$6-DATA!$B$12) -> 835.2677 | V51: =T51+U51 -> 1044.0846 | W51: =V51*E51*F51 -> 1.0307862e-08 | X51: =W51*BASE!Q51 -> 2.715113e-09
A52: 50 | B52: =B51*EXP(RATES!O53)*(1-DATA!$B$6) -> 103172 | C52: =C51*EXP(RATES!O53)*(1-DATA!$B$6) -> 25793 | D52: =B52+C52 -> 128965 | E52: =E51*(1-'LIFE TABLE MALE'!D112/1000) -> 6.7948871e-07 | F52: =F51*(1-0.15*1.5) -> 2.9179989e-06 | G52: =D52-20 -> 128945 | H52: =MAX(D52,DATA!$B$3) -> 128965 | I52: =G52*DATA!$B$7*1.5*F51*E52 -> 7.4225424e-08 | J52: =H52*'LIFE TABLE MALE'!D112/1000*F51*E51 -> 9.4328186e-07 | K52: =E52*D52*F52 -> 2.5570501e-07 | L52: =DATA!$B$8*((1+DATA!$B$9)^A51)*F52*E52 -> 2.6160485e-10 | M52: =B51*EXP(RATES!O53)*(DATA!$B$12) -> 1476.8998 | N52: =C51*EXP(RATES!O53)*(DATA!$B$12) -> 369.22495 | O52: =M52+N52 -> 1846.1247 | P52: =O52*E52*F52 -> 3.6603989e-09 | Q52: =RATES!G53 -> 0.25495931 | R52: =P52+L52+K52+J52+I52 -> 1.2771343e-06 | S52: =R52*Q52 -> 3.2561728e-07 | T52: =C51*EXP(RATES!O53)*(DATA!$B$6-DATA!$B$12) -> 210.98568 | U52: =B51*EXP(RATES!O53)*(DATA!$B$6-DATA!$B$12) -> 843.94273 | V52: =T52+U52 -> 1054.9284 | W52: =V52*E52*F52 -> 2.0916565e-09 | X52: =W52*BASE!Q52 -> 5.332873e-10
P56: LIABILITIES | Q56: =SUM(S3:S52) -> 95624.089 | T56: BEL COMPONENTS
P57: BOF | Q57: =DATA!B2-Q56 -> 4375.9114 | T57: DEATH | U57: =SUMPRODUCT(J3:J52,Q3:Q52) -> 3665.2089
T58: LAPSE | U58: =SUMPRODUCT(I3:I52,Q3:Q52) -> 87486.707
P59: DURATION | Q59: =SUMPRODUCT(S3:S52,A3:A52)/SUM(S3:S52) -> 4.0158341 | T59: EXPENSES | U59: =SUMPRODUCT(L3:L52,Q3:Q52) -> 157.61836
T60: COMMISSIONS | U60: =SUMPRODUCT(P3:P52,Q3:Q52) -> 4314.5545

Sheet LAPSE STRESS DOWN
B1: EQUITY | C1: PROPERTY | D1: ASSET | E1: SURVIVAL PROB | F1: non LAPSE PROB | G1: C lapse | H1: C death | I1: LIAB LAPSE | J1: LIAB DEATH | K1: LIAB SURVIVE | L1: EXPENSES | M1: EQ COMMISSIONS | N1: PR COMMISSIONS | O1: TOT COMMISSIONS | P1: COMMISSIONS LIAB | Q1: DISCOUNTS | R1: TOT LIAB | S1: TOT LIAB DISC | T1: PROFIT PR | U1: PROFIT EQ | V1: TOT PROFIT | W1: PROFIT LIAB | X1: PROFIT LIAB DISCOUNTED
A2: 0 | B2: =DATA!B2*0.8 -> 80000 | C2: =DATA!B2*0.2 -> 20000 | D2: =B2+C2 -> 100000 | E2: =1 -> 1 | F2: =1 -> 1 | G2: =D2-20 -> 99980 | H2: =MAX(D2,DATA!$B$3) -> 100000 | M2: =B2 -> 80000 | N2: =C2 -> 20000 | Q2: =RATES!G3 -> 1
A3: 1 | B3: =B2*EXP(RATES!O4)*(1-DATA!$B$6) -> 80989.354 | C3: =C2*EXP(RATES!O4)*(1-DATA!$B$6) -> 20247.338 | D3: =B3+C3 -> 101236.69 | E3: =E2*(1-'LIFE TABLE MALE'!D63/1000) -> 0.99353213 | F3: =F2*(1-0.075) -> 0.925 | G3: =D3-20 -> 101216.69 | H3: =MAX(D3,DATA!$B$3) -> 101236.69 | I3: =G3*0.075*F2*E3 -> 7542.1527 | J3: =H3*'LIFE TABLE MALE'!D63/1000*F2*E2 -> 654.78576 | K3: =0 -> 0 | L3: =DATA!$B$8*((1+DATA!$B$9)^A2)*F3*E3 -> 45.950861 | M3: =B2*EXP(RATES!O4)*(DATA!$B$12) -> 1159.3568 | N3: =C2*EXP(RATES!O4)*(DATA!$B$12) -> 289.8392 | O3: =M3+N3 -> 1449.196 | P3: =O3*E3*F3 -> 1331.8361 | Q3: =RATES!G4 -> 0.9660529 | R3: =P3+L3+K3+J3+I3 -> 9574.7254 | S3: =R3*Q3 -> 9249.6912 | T3: =C2*EXP(RATES!O4)*(DATA!$B$6-DATA!$B$12) -> 165.6224 | U3: =B2*EXP(RATES!O4)*(DATA!$B$6-DATA!$B$12) -> 662.4896 | V3: =T3+U3 -> 828.112 | W3: =V3*E3*F3 -> 761.04919 | X3: =W3*BASE!Q3 -> 735.21378
A4: 2 | B4: =B3*EXP(RATES!O5)*(1-DATA!$B$6) -> 81233.889 | C4: =C3*EXP(RATES!O5)*(1-DATA!$B$6) -> 20308.472 | D4: =B4+C4 -> 101542.36 | E4: =E3*(1-'LIFE TABLE MALE'!D64/1000) -> 0.98647779 | F4: =F3*(1-0.075) -> 0.855625 | G4: =D4-20 -> 101522.36 | H4: =MAX(D4,DATA!$B$3) -> 101542.36 | I4: =G4*0.075*F3*E4 -> 6947.8754 | J4: =H4*'LIFE TABLE MALE'!D64/1000*F3*E3 -> 662.59043 | K4: =0 -> 0 | L4: =DATA!$B$8*((1+DATA!$B$9)^A3)*F4*E4 -> 43.046808 | M4: =B3*EXP(RATES!O5)*(DATA!$B$12) -> 1162.8573 | N4: =C3*EXP(RATES!O5)*(DATA!$B$12) -> 290.71433 | O4: =M4+N4 -> 1453.5716 | P4: =O4*E4*F4 -> 1226.8945 | Q4: =RATES!G5 -> 0.94195564 | R4: =P4+L4+K4+J4+I4 -> 8880.4072 | S4: =R4*Q4 -> 8364.9496 | T4: =C3*EXP(RATES!O5)*(DATA!$B$6-DATA!$B$12) -> 166.12247 | U4: =B3*EXP(RATES!O5)*(DATA!$B$6-DATA!$B$12) -> 664.48989 | V4: =T4+U4 -> 830.61237 | W4: =V4*E4*F4 -> 701.08257 | X4: =W4*BASE!Q4 -> 660.38868
A5: 3 | B5: =B4*EXP(RATES!O6)*(1-DATA!$B$6) -> 81258.803 | C5: =C4*EXP(RATES!O6)*(1-DATA!$B$6) -> 20314.701 | D5: =B5+C5 -> 101573.5 | E5: =E4*(1-'LIFE TABLE MALE'!D65/1000) -> 0.97876837 | F5: =F4*(1-0.075) -> 0.79145313 | G5: =D5-20 -> 101553.5 | H5: =MAX(D5,DATA!$B$3) -> 101573.5 | I5: =G5*0.075*F4*E5 -> 6378.5148 | J5: =H5*'LIFE TABLE MALE'!D65/1000*F4*E4 -> 670.01689 | K5: =0 -> 0 | L5: =DATA!$B$8*((1+DATA!$B$9)^A4)*F5*E5 -> 40.297256 | M5: =B4*EXP(RATES!O6)*(DATA!$B$12) -> 1163.2139 | N5: =C4*EXP(RATES!O6)*(DATA!$B$12) -> 290.80349 | O5: =M5+N5 -> 1454.0174 | P5: =O5*E5*F5 -> 1126.3536 | Q5: =RATES!G6 -> 0.92095017 | R5: =P5+L5+K5+J5+I5 -> 8215.1825 | S5: =R5*Q5 -> 7565.7737 | T5: =C4*EXP(RATES!O6)*(DATA!$B$6-DATA!$B$12) -> 166.17342 | U5: =B4*EXP(RATES!O6)*(DATA!$B$6-DATA!$B$12) -> 664.69368 | V5: =T5+U5 -> 830.86711 | W5: =V5*E5*F5 -> 643.63061 | X5: =W5*BASE!Q5 -> 592.75172
A6: 4 | B6: =B5*EXP(RATES!O7)*(1-DATA!$B$6) -> 81219.667 | C6: =C5*EXP(RATES!O7)*(1-DATA!$B$6) -> 20304.917 | D6: =B6+C6 -> 101524.58 | E6: =E5*(1-'LIFE TABLE MALE'!D66/1000) -> 0.97028747 | F6: =F5*(1-0.075) -> 0.73209414 | G6: =D6-20 -> 101504.58 | H6: =MAX(D6,DATA!$B$3) -> 101524.58 | I6: =G6*0.075*F5*E6 -> 5846.1848 | J6: =H6*'LIFE TABLE MALE'!D66/1000*F5*E5 -> 681.4569 | K6: =0 -> 0 | L6: =DATA!$B$8*((1+DATA!$B$9)^A5)*F6*E6 -> 37.691019 | M6: =B5*EXP(RATES!O7)*(DATA!$B$12) -> 1162.6537 | N6: =C5*EXP(RATES!O7)*(DATA!$B$12) -> 290.66343 | O6: =M6+N6 -> 1453.3171 | P6: =O6*E6*F6 -> 1032.3519 | Q6: =RATES!G7 -> 0.90112326 | R6: =P6+L6+K6+J6+I6 -> 7597.6846 | S6: =R6*Q6 -> 6846.4503 | T6: =C5*EXP(RATES!O7)*(DATA!$B$6-DATA!$B$12) -> 166.09339 | U6: =B5*EXP(RATES!O7)*(DATA!$B$6-DATA!$B$12) -> 664.37355 | V6: =T6+U6 -> 830.46694 | W6: =V6*E6*F6 -> 589.91536 | X6: =W6*BASE!Q6 -> 531.58645
A7: 5 | B7: =B6*EXP(RATES!O8)*(1-DATA!$B$6) -> 81178.572 | C7: =C6*EXP(RATES!O8)*(1-DATA!$B$6) -> 20294.643 | D7: =B7+C7 -> 101473.22 | E7: =E6*(1-'LIFE TABLE MALE'!D67/1000) -> 0.96092158 | F7: =F6*(1-0.075) -> 0.67718708 | G7: =D7-20 -> 101453.22 | H7: =MAX(D7,DATA!$B$3) -> 101473.22 | I7: =G7*0.075*F6*E7 -> 5352.8116 | J7: =H7*'LIFE TABLE MALE'!D67/1000*F6*E6 -> 695.77302 | K7: =0 -> 0 | L7: =DATA!$B$8*((1+DATA!$B$9)^A6)*F7*E7 -> 35.218212 | M7: =B6*EXP(RATES!O8)*(DATA!$B$12) -> 1162.0655 | N7: =C6*EXP(RATES!O8)*(DATA!$B$12) -> 290.51636 | O7: =M7+N7 -> 1452.5818 | P7: =O7*E7*F7 -> 945.22938 | Q7: =RATES!G8 -> 0.88174469 | R7: =P7+L7+K7+J7+I7 -> 7029.0322 | S7: =R7*Q7 -> 6197.8118 | T7: =C6*EXP(RATES!O8)*(DATA!$B$6-DATA!$B$12) -> 166.00935 | U7: =B6*EXP(RATES!O8)*(DATA!$B$6-DATA!$B$12) -> 664.0374 | V7: =T7+U7 -> 830.04675 | W7: =V7*E7*F7 -> 540.13107 | X7: =W7*BASE!Q7 -> 476.25771
A8: 6 | B8: =B7*EXP(RATES!O9)*(1-DATA!$B$6) -> 81192.731 | C8: =C7*EXP(RATES!O9)*(1-DATA!$B$6) -> 20298.183 | D8: =B8+C8 -> 101490.91 | E8: =E7*(1-'LIFE TABLE MALE'!D68/1000) -> 0.95054817 | F8: =F7*(1-0.075) -> 0.62639805 | G8: =D8-20 -> 101470.91 | H8: =MAX(D8,DATA!$B$3) -> 101490.91 | I8: =G8*0.075*F7*E8 -> 4898.754 | J8: =H8*'LIFE TABLE MALE'!D68/1000*F7*E7 -> 712.94706 | K8: =0 -> 0 | L8: =DATA!$B$8*((1+DATA!$B$9)^A7)*F8*E8 -> 32.869673 | M8: =B7*EXP(RATES!O9)*(DATA!$B$12) -> 1162.2681 | N8: =C7*EXP(RATES!O9)*(DATA!$B$12) -> 290.56703 | O8: =M8+N8 -> 1452.8352 | P8: =O8*E8*F8 -> 865.04932 | Q8: =RATES!G9 -> 0.86219592 | R8: =P8+L8+K8+J8+I8 -> 6509.62 | S8: =R8*Q8 -> 5612.5679 | T8: =C7*EXP(RATES!O9)*(DATA!$B$6-DATA!$B$12) -> 166.03831 | U8: =B7*EXP(RATES!O9)*(DATA!$B$6-DATA!$B$12) -> 664.15322 | V8: =T8+U8 -> 830.19153 | W8: =V8*E8*F8 -> 494.3139 | X8: =W8*BASE!Q8 -> 426.19543
A9: 7 | B9: =B8*EXP(RATES!O10)*(1-DATA!$B$6) -> 81254.382 | C9: =C8*EXP(RATES!O10)*(1-DATA!$B$6) -> 20313.596 | D9: =B9+C9 -> 101567.98 | E9: =E8*(1-'LIFE TABLE MALE'!D69/1000) -> 0.93939989 | F9: =F8*(1-0.075) -> 0.5794182 | G9: =D9-20 -> 101547.98 | H9: =MAX(D9,DATA!$B$3) -> 101567.98 | I9: =G9*0.075*F8*E9 -> 4481.6036 | J9: =H9*'LIFE TABLE MALE'!D69/1000*F8*E8 -> 709.27543 | K9: =0 -> 0 | L9: =DATA!$B$8*((1+DATA!$B$9)^A8)*F9*E9 -> 30.648814 | M9: =B8*EXP(RATES!O10)*(DATA!$B$12) -> 1163.1507 | N9: =C8*EXP(RATES!O10)*(DATA!$B$12) -> 290.78767 | O9: =M9+N9 -> 1453.9383 | P9: =O9*E9*F9 -> 791.38647 | Q9: =RATES!G10 -> 0.84258782 | R9: =P9+L9+K9+J9+I9 -> 6012.9144 | S9: =R9*Q9 -> 5066.4084 | T9: =C8*EXP(RATES!O10)*(DATA!$B$6-DATA!$B$12) -> 166.16438 | U9: =B8*EXP(RATES!O10)*(DATA!$B$6-DATA!$B$12) -> 664.65752 | V9: =T9+U9 -> 830.8219 | W9: =V9*E9*F9 -> 452.22084 | X9: =W9*BASE!Q9 -> 381.03577
A10: 8 | B10: =B9*EXP(RATES!O11)*(1-DATA!$B$6) -> 81365.273 | C10: =C9*EXP(RATES!O11)*(1-DATA!$B$6) -> 20341.318 | D10: =B10+C10 -> 101706.59 | E10: =E9*(1-'LIFE TABLE MALE'!D70/1000) -> 0.92737751 | F10: =F9*(1-0.075) -> 0.53596183 | G10: =D10-20 -> 101686.59 | H10: =MAX(D10,DATA!$B$3) -> 101706.59 | I10: =G10*0.075*F9*E10 -> 4098.0159 | J10: =H10*'LIFE TABLE MALE'!D70/1000*F9*E9 -> 708.48687 | K10: =0 -> 0 | L10: =DATA!$B$8*((1+DATA!$B$9)^A9)*F10*E10 -> 28.547076 | M10: =B9*EXP(RATES!O11)*(DATA!$B$12) -> 1164.7381 | N10: =C9*EXP(RATES!O11)*(DATA!$B$12) -> 291.18452 | O10: =M10+N10 -> 1455.9226 | P10: =O10*E10*F10 -> 723.65023 | Q10: =RATES!G11 -> 0.82292781 | R10: =P10+L10+K10+J10+I10 -> 5558.7001 | S10: =R10*Q10 -> 4574.4089 | T10: =C9*EXP(RATES!O11)*(DATA!$B$6-DATA!$B$12) -> 166.39115 | U10: =B9*EXP(RATES!O11)*(DATA!$B$6-DATA!$B$12) -> 665.56461 | V10: =T10+U10 -> 831.95576 | W10: =V10*E10*F10 -> 413.51442 | X10: =W10*BASE!Q10 -> 340.29251
A11: 9 | B11: =B10*EXP(RATES!O12)*(1-DATA!$B$6) -> 81523.24 | C11: =C10*EXP(RATES!O12)*(1-DATA!$B$6) -> 20380.81 | D11: =B11+C11 -> 101904.05 | E11: =E10*(1-'LIFE TABLE MALE'!D71/1000) -> 0.91441742 | F11: =F10*(1-0.075) -> 0.49576469 | G11: =D11-20 -> 101884.05 | H11: =MAX(D11,DATA!$B$3) -> 101904.05 | I11: =G11*0.075*F10*E11 -> 3744.9482 | J11: =H11*'LIFE TABLE MALE'!D71/1000*F10*E10 -> 707.83718 | K11: =0 -> 0 | L11: =DATA!$B$8*((1+DATA!$B$9)^A10)*F11*E11 -> 26.557761 | M11: =B10*EXP(RATES!O12)*(DATA!$B$12) -> 1166.9993 | N11: =C10*EXP(RATES!O12)*(DATA!$B$12) -> 291.74984 | O11: =M11+N11 -> 1458.7492 | P11: =O11*E11*F11 -> 661.30333 | Q11: =RATES!G12 -> 0.8032639 | R11: =P11+L11+K11+J11+I11 -> 5140.6465 | S11: =R11*Q11 -> 4129.2957 | T11: =C10*EXP(RATES!O12)*(DATA!$B$6-DATA!$B$12) -> 166.71419 | U11: =B10*EXP(RATES!O12)*(DATA!$B$6-DATA!$B$12) -> 666.85677 | V11: =T11+U11 -> 833.57096 | W11: =V11*E11*F11 -> 377.88762 | X11: =W11*BASE!Q11 -> 303.54348
A12: 10 | B12: =B11*EXP(RATES!O13)*(1-DATA!$B$6) -> 81742.12 | C12: =C11*EXP(RATES!O13)*(1-DATA!$B$6) -> 20435.53 | D12: =B12+C12 -> 102177.65 | E12: =E11*(1-'LIFE TABLE MALE'!D72/1000) -> 0.9000976 | F12: =F11*(1-0.075) -> 0.45858234 | G12: =D12-20 -> 102157.65 | H12: =MAX(D12,DATA!$B$3) -> 102177.65 | I12: =G12*0.075*F11*E12 -> 3418.9862 | J12: =H12*'LIFE TABLE MALE'!D72/1000*F11*E11 -> 725.38595 | K12: =0 -> 0 | L12: =DATA!$B$8*((1+DATA!$B$9)^A11)*F12*E12 -> 24.66485 | M12: =B11*EXP(RATES!O13)*(DATA!$B$12) -> 1170.1326 | N12: =C11*EXP(RATES!O13)*(DATA!$B$12) -> 292.53315 | O12: =M12+N12 -> 1462.6657 | P12: =O12*E12*F12 -> 603.74288 | Q12: =RATES!G13 -> 0.78348852 | R12: =P12+L12+K12+J12+I12 -> 4772.7799 | S12: =R12*Q12 -> 3739.4183 | T12: =C11*EXP(RATES!O13)*(DATA!$B$6-DATA!$B$12) -> 167.1618 | U12: =B11*EXP(RATES!O13)*(DATA!$B$6-DATA!$B$12) -> 668.6472 | V12: =T12+U12 -> 835.809 | W12: =V12*E12*F12 -> 344.99593 | X12: =W12*BASE!Q12 -> 270.30035
A13: 11 | B13: =B12*EXP(RATES!O14)*(1-DATA!$B$6) -> 82068.024 | C13: =C12*EXP(RATES!O14)*(1-DATA!$B$6) -> 20517.006 | D13: =B13+C13 -> 102585.03 | E13: =E12*(1-'LIFE TABLE MALE'!D73/1000) -> 0.88436967 | F13: =F12*(1-0.075) -> 0.42418867 | G13: =D13-20 -> 102565.03 | H13: =MAX(D13,DATA!$B$3) -> 102585.03 | I13: =G13*0.075*F12*E13 -> 3119.6922 | J13: =H13*'LIFE TABLE MALE'!D73/1000*F12*E12 -> 739.89963 | K13: =0 -> 0 | L13: =DATA!$B$8*((1+DATA!$B$9)^A12)*F13*E13 -> 22.864653 | M13: =B12*EXP(RATES!O14)*(DATA!$B$12) -> 1174.7979 | N13: =C12*EXP(RATES!O14)*(DATA!$B$12) -> 293.69947 | O13: =M13+N13 -> 1468.4974 | P13: =O13*E13*F13 -> 550.8915 | Q13: =RATES!G14 -> 0.76320888 | R13: =P13+L13+K13+J13+I13 -> 4433.3479 | S13: =R13*Q13 -> 3383.5705 | T13: =C12*EXP(RATES!O14)*(DATA!$B$6-DATA!$B$12) -> 167.82827 | U13: =B12*EXP(RATES!O14)*(DATA!$B$6-DATA!$B$12) -> 671.31308 | V13: =T13+U13 -> 839.14135 | W13: =V13*E13*F13 -> 314.79514 | X13: =W13*BASE!Q13 -> 240.25445
A14: 12 | B14: =B13*EXP(RATES!O15)*(1-DATA!$B$6) -> 82258.657 | C14: =C13*EXP(RATES!O15)*(1-DATA!$B$6) -> 20564.664 | D14: =B14+C14 -> 102823.32 | E14: =E13*(1-'LIFE TABLE MALE'!D74/1000) -> 0.86691444 | F14: =F13*(1-0.075) -> 0.39237452 | G14: =D14-20 -> 102803.32 | H14: =MAX(D14,DATA!$B$3) -> 102823.32 | I14: =G14*0.075*F13*E14 -> 2835.3306 | J14: =H14*'LIFE TABLE MALE'!D74/1000*F13*E13 -> 761.33576 | K14: =0 -> 0 | L14: =DATA!$B$8*((1+DATA!$B$9)^A13)*F14*E14 -> 21.147008 | M14: =B13*EXP(RATES!O15)*(DATA!$B$12) -> 1177.5268 | N14: =C13*EXP(RATES!O15)*(DATA!$B$12) -> 294.3817 | O14: =M14+N14 -> 1471.9085 | P14: =O14*E14*F14 -> 500.67722 | Q14: =RATES!G15 -> 0.74468847 | R14: =P14+L14+K14+J14+I14 -> 4118.4906 | S14: =R14*Q14 -> 3066.9925 | T14: =C13*EXP(RATES!O15)*(DATA!$B$6-DATA!$B$12) -> 168.21811 | U14: =B13*EXP(RATES!O15)*(DATA!$B$6-DATA!$B$12) -> 672.87245 | V14: =T14+U14 -> 841.09056 | W14: =V14*E14*F14 -> 286.10127 | X14: =W14*BASE!Q14 -> 213.05632
... A51: 49 | B51: =B50*EXP(RATES!O52)*(1-DATA!$B$6) -> 102111.48 | C51: =C50*EXP(RATES!O52)*(1-DATA!$B$6) -> 25527.869 | D51: =B51+C51 -> 127639.35 | E51: =E50*(1-'LIFE TABLE MALE'!D111/1000) -> 2.6221013e-06 | F51: =F50*(1-0.075) -> 0.021925268 | G51: =D51-20 -> 127619.35 | H51: =MAX(D51,DATA!$B$3) -> 127639.35 | I51: =G51*0.075*F50*E51 -> 0.00059488143 | J51: =H51*'LIFE TABLE MALE'!D111/1000*F50*E50 -> 0.019533838 | K51: =0 -> 0 | L51: =DATA!$B$8*((1+DATA!$B$9)^A50)*F51*E51 -> 7.4365691e-06 | M51: =B50*EXP(RATES!O52)*(DATA!$B$12) -> 1461.7185 | N51: =C50*EXP(RATES!O52)*(DATA!$B$12) -> 365.42962 | O51: =M51+N51 -> 1827.1481 | P51: =O51*E51*F51 -> 0.00010504324 | Q51: =RATES!G52 -> 0.26340215 | R51: =P51+L51+K51+J51+I51 -> 0.020241199 | S51: =R51*Q51 -> 0.0053315753 | T51: =C50*EXP(RATES!O52)*(DATA!$B$6-DATA!$B$12) -> 208.81693 | U51: =B50*EXP(RATES!O52)*(DATA!$B$6-DATA!$B$12) -> 835.2677 | V51: =T51+U51 -> 1044.0846 | W51: =V51*E51*F51 -> 6.002471e-05 | X51: =W51*BASE!Q51 -> 1.5810638e-05
A52: 50 | B52: =B51*EXP(RATES!O53)*(1-DATA!$B$6) -> 103172 | C52: =C51*EXP(RATES!O53)*(1-DATA!$B$6) -> 25793 | D52: =B52+C52 -> 128965 | E52: =E51*(1-'LIFE TABLE MALE'!D112/1000) -> 6.7948871e-07 | F52: =F51*(1-0.075) -> 0.020280873 | G52: =D52-20 -> 128945 | H52: =MAX(D52,DATA!$B$3) -> 128965 | I52: =G52*0.075*F51*E52 -> 0.00014407642 | J52: =H52*'LIFE TABLE MALE'!D112/1000*F51*E51 -> 0.0054929161 | K52: =E52*D52*F52 -> 0.0017772182 | L52: =DATA!$B$8*((1+DATA!$B$9)^A51)*F52*E52 -> 1.8182237e-06 | M52: =B51*EXP(RATES!O53)*(DATA!$B$12) -> 1476.8998 | N52: =C51*EXP(RATES!O53)*(DATA!$B$12) -> 369.22495 | O52: =M52+N52 -> 1846.1247 | P52: =O52*E52*F52 -> 2.5440751e-05 | Q52: =RATES!G53 -> 0.25495931 | R52: =P52+L52+K52+J52+I52 -> 0.0074414696 | S52: =R52*Q52 -> 0.001897272 | T52: =C51*EXP(RATES!O53)*(DATA!$B$6-DATA!$B$12) -> 210.98568 | U52: =B51*EXP(RATES!O53)*(DATA!$B$6-DATA!$B$12) -> 843.94273 | V52: =T52+U52 -> 1054.9284 | W52: =V52*E52*F52 -> 1.4537572e-05 | X52: =W52*BASE!Q52 -> 3.7064893e-06
P56: LIABILITIES | Q56: =SUM(S3:S52) -> 92119.809 | T56: BEL COMPONENTS
P57: BOF | Q57: =DATA!B2-Q56 -> 7880.1908 | T57: DEATH | U57: =SUMPRODUCT(J3:J52,Q3:Q52) -> 15750.121
T58: LAPSE | U58: =SUMPRODUCT(I3:I52,Q3:Q52) -> 64525.803
P59: DURATION | Q59: =SUMPRODUCT(S3:S52,A3:A52)/SUM(S3:S52) -> 9.0321241 | T59: EXPENSES | U59: =SUMPRODUCT(L3:L52,Q3:Q52) -> 449.57127
T60: COMMISSIONS | U60: =SUMPRODUCT(P3:P52,Q3:Q52) -> 11394.313

Sheet LAPSE MASS
B1: EQUITY | C1: PROPERTY | D1: ASSET | E1: SURVIVAL PROB | F1: non LAPSE PROB | G1: C lapse | H1: C death | I1: LIAB LAPSE | J1: LIAB DEATH | K1: LIAB SURVIVE | L1: EXPENSES | M1: EQ COMMISSIONS | N1: PR COMMISSIONS | O1: TOT COMMISSIONS | P1: COMMISSIONS LIAB | Q1: DISCOUNTS | R1: TOT LIAB | S1: TOT LIAB DISC | T1: PROFIT PR | U1: PROFIT EQ | V1: TOT PROFIT | W1: PROFIT LIAB | X1: PROFIT LIAB DISCOUNTED
A2: 0 | B2: =DATA!B2*0.8 -> 80000 | C2: =DATA!B2*0.2 -> 20000 | D2: =B2+C2 -> 100000 | E2: =1 -> 1 | F2: =1 -> 1 | G2: =D2-20 -> 99980 | H2: =MAX(D2,DATA!$B$3) -> 100000 | M2: =B2 -> 80000 | N2: =C2 -> 20000 | Q2: =RATES!G3 -> 1
A3: 1 | B3: =B2*EXP(RATES!O4)*(1-DATA!$B$6) -> 80989.354 | C3: =C2*EXP(RATES!O4)*(1-DATA!$B$6) -> 20247.338 | D3: =B3+C3 -> 101236.69 | E3: =E2*(1-'LIFE TABLE MALE'!D63/1000) -> 0.99353213 | F3: =F2*(1-0.15-0.4) -> 0.45 | G3: =D3-20 -> 101216.69 | H3: =MAX(D3,DATA!$B$3) -> 101236.69 | I3: =G3*(DATA!$B$7+0.4)*F2*E3 -> 55309.12 | J3: =H3*'LIFE TABLE MALE'!D63/1000*F2*E2 -> 654.78576 | K3: =0 -> 0 | L3: =DATA!$B$8*((1+DATA!$B$9)^A2)*F3*E3 -> 22.354473 | M3: =B2*EXP(RATES!O4)*(DATA!$B$12) -> 1159.3568 | N3: =C2*EXP(RATES!O4)*(DATA!$B$12) -> 289.8392 | O3: =M3+N3 -> 1449.196 | P3: =O3*E3*F3 -> 647.92025 | Q3: =RATES!G4 -> 0.9660529 | R3: =P3+L3+K3+J3+I3 -> 56634.18 | S3: =R3*Q3 -> 54711.614 | T3: =C2*EXP(RATES!O4)*(DATA!$B$6-DATA!$B$12) -> 165.6224 | U3: =B2*EXP(RATES!O4)*(DATA!$B$6-DATA!$B$12) -> 662.4896 | V3: =T3+U3 -> 828.112 | W3: =V3*E3*F3 -> 370.24015 | X3: =W3*BASE!Q3 -> 357.67157
A4: 2 | B4: =B3*EXP(RATES!O5)*(1-DATA!$B$6) -> 81233.889 | C4: =C3*EXP(RATES!O5)*(1-DATA!$B$6) -> 20308.472 | D4: =B4+C4 -> 101542.36 | E4: =E3*(1-'LIFE TABLE MALE'!D64/1000) -> 0.98647779 | F4: =F3*(1-0.15) -> 0.3825 | G4: =D4-20 -> 101522.36 | H4: =MAX(D4,DATA!$B$3) -> 101542.36 | I4: =G4*DATA!$B$7*F3*E4 -> 6760.095 | J4: =H4*'LIFE TABLE MALE'!D64/1000*F3*E3 -> 322.34129 | K4: =0 -> 0 | L4: =DATA!$B$8*((1+DATA!$B$9)^A3)*F4*E4 -> 19.243716 | M4: =B3*EXP(RATES!O5)*(DATA!$B$12) -> 1162.8573 | N4: =C3*EXP(RATES!O5)*(DATA!$B$12) -> 290.71433 | O4: =M4+N4 -> 1453.5716 | P4: =O4*E4*F4 -> 548.47293 | Q4: =RATES!G5 -> 0.94195564 | R4: =P4+L4+K4+J4+I4 -> 7650.1529 | S4: =R4*Q4 -> 7206.1047 | T4: =C3*EXP(RATES!O5)*(DATA!$B$6-DATA!$B$12) -> 166.12247 | U4: =B3*EXP(RATES!O5)*(DATA!$B$6-DATA!$B$12) -> 664.48989 | V4: =T4+U4 -> 830.61237 | W4: =V4*E4*F4 -> 313.4131 | X4: =W4*BASE!Q4 -> 295.22124
A5: 3 | B5: =B4*EXP(RATES!O6)*(1-DATA!$B$6) -> 81258.803 | C5: =C4*EXP(RATES!O6)*(1-DATA!$B$6) -> 20314.701 | D5: =B5+C5 -> 101573.5 | E5: =E4*(1-'LIFE TABLE MALE'!D65/1000) -> 0.97876837 | F5: =F4*(1-0.15) -> 0.325125 | G5: =D5-20 -> 101553.5 | H5: =MAX(D5,DATA!$B$3) -> 101573.5 | I5: =G5*DATA!$B$7*F4*E5 -> 5702.9234 | J5: =H5*'LIFE TABLE MALE'!D65/1000*F4*E4 -> 299.52545 | K5: =0 -> 0 | L5: =DATA!$B$8*((1+DATA!$B$9)^A4)*F5*E5 -> 16.553912 | M5: =B4*EXP(RATES!O6)*(DATA!$B$12) -> 1163.2139 | N5: =C4*EXP(RATES!O6)*(DATA!$B$12) -> 290.80349 | O5: =M5+N5 -> 1454.0174 | P5: =O5*E5*F5 -> 462.70043 | Q5: =RATES!G6 -> 0.92095017 | R5: =P5+L5+K5+J5+I5 -> 6481.7032 | S5: =R5*Q5 -> 5969.3256 | T5: =C4*EXP(RATES!O6)*(DATA!$B$6-DATA!$B$12) -> 166.17342 | U5: =B4*EXP(RATES!O6)*(DATA!$B$6-DATA!$B$12) -> 664.69368 | V5: =T5+U5 -> 830.86711 | W5: =V5*E5*F5 -> 264.40025 | X5: =W5*BASE!Q5 -> 243.49945
A6: 4 | B6: =B5*EXP(RATES!O7)*(1-DATA!$B$6) -> 81219.667 | C6: =C5*EXP(RATES!O7)*(1-DATA!$B$6) -> 20304.917 | D6: =B6+C6 -> 101524.58 | E6: =E5*(1-'LIFE TABLE MALE'!D66/1000) -> 0.97028747 | F6: =F5*(1-0.15) -> 0.27635625 | G6: =D6-20 -> 101504.58 | H6: =MAX(D6,DATA!$B$3) -> 101524.58 | I6: =G6*DATA!$B$7*F5*E6 -> 4803.1672 | J6: =H6*'LIFE TABLE MALE'!D66/1000*F5*E5 -> 279.9391 | K6: =0 -> 0 | L6: =DATA!$B$8*((1+DATA!$B$9)^A5)*F6*E6 -> 14.227881 | M6: =B5*EXP(RATES!O7)*(DATA!$B$12) -> 1162.6537 | N6: =C5*EXP(RATES!O7)*(DATA!$B$12) -> 290.66343 | O6: =M6+N6 -> 1453.3171 | P6: =O6*E6*F6 -> 389.69974 | Q6: =RATES!G7 -> 0.90112326 | R6: =P6+L6+K6+J6+I6 -> 5487.0339 | S6: =R6*Q6 -> 4944.4939 | T6: =C5*EXP(RATES!O7)*(DATA!$B$6-DATA!$B$12) -> 166.09339 | U6: =B5*EXP(RATES!O7)*(DATA!$B$6-DATA!$B$12) -> 664.37355 | V6: =T6+U6 -> 830.46694 | W6: =V6*E6*F6 -> 222.68556 | X6: =W6*BASE!Q6 -> 200.66714
A7: 5 | B7: =B6*EXP(RATES!O8)*(1-DATA!$B$6) -> 81178.572 | C7: =C6*EXP(RATES!O8)*(1-DATA!$B$6) -> 20294.643 | D7: =B7+C7 -> 101473.22 | E7: =E6*(1-'LIFE TABLE MALE'!D67/1000) -> 0.96092158 | F7: =F6*(1-0.15) -> 0.23490281 | G7: =D7-20 -> 101453.22 | H7: =MAX(D7,DATA!$B$3) -> 101473.22 | I7: =G7*DATA!$B$7*F6*E7 -> 4041.2369 | J7: =H7*'LIFE TABLE MALE'!D67/1000*F6*E6 -> 262.64549 | K7: =0 -> 0 | L7: =DATA!$B$8*((1+DATA!$B$9)^A6)*F7*E7 -> 12.216502 | M7: =B6*EXP(RATES!O8)*(DATA!$B$12) -> 1162.0655 | N7: =C6*EXP(RATES!O8)*(DATA!$B$12) -> 290.51636 | O7: =M7+N7 -> 1452.5818 | P7: =O7*E7*F7 -> 327.88139 | Q7: =RATES!G8 -> 0.88174469 | R7: =P7+L7+K7+J7+I7 -> 4643.9803 | S7: =R7*Q7 -> 4094.8049 | T7: =C6*EXP(RATES!O8)*(DATA!$B$6-DATA!$B$12) -> 166.00935 | U7: =B6*EXP(RATES!O8)*(DATA!$B$6-DATA!$B$12) -> 664.0374 | V7: =T7+U7 -> 830.04675 | W7: =V7*E7*F7 -> 187.36079 | X7: =W7*BASE!Q7 -> 165.20438
A8: 6 | B8: =B7*EXP(RATES!O9)*(1-DATA!$B$6) -> 81192.731 | C8: =C7*EXP(RATES!O9)*(1-DATA!$B$6) -> 20298.183 | D8: =B8+C8 -> 101490.91 | E8: =E7*(1-'LIFE TABLE MALE'!D68/1000) -> 0.95054817 | F8: =F7*(1-0.15) -> 0.19966739 | G8: =D8-20 -> 101470.91 | H8: =MAX(D8,DATA!$B$3) -> 101490.91 | I8: =G8*DATA!$B$7*F7*E8 -> 3398.5619 | J8: =H8*'LIFE TABLE MALE'!D68/1000*F7*E7 -> 247.30724 | K8: =0 -> 0 | L8: =DATA!$B$8*((1+DATA!$B$9)^A7)*F8*E8 -> 10.477366 | M8: =B7*EXP(RATES!O9)*(DATA!$B$12) -> 1162.2681 | N8: =C7*EXP(RATES!O9)*(DATA!$B$12) -> 290.56703 | O8: =M8+N8 -> 1452.8352 | P8: =O8*E8*F8 -> 275.73863 | Q8: =RATES!G9 -> 0.86219592 | R8: =P8+L8+K8+J8+I8 -> 3932.0851 | S8: =R8*Q8 -> 3390.2277 | T8: =C7*EXP(RATES!O9)*(DATA!$B$6-DATA!$B$12) -> 166.03831 | U8: =B7*EXP(RATES!O9)*(DATA!$B$6-DATA!$B$12) -> 664.15322 | V8: =T8+U8 -> 830.19153 | W8: =V8*E8*F8 -> 157.56493 | X8: =W8*BASE!Q8 -> 135.85184
A9: 7 | B9: =B8*EXP(RATES!O10)*(1-DATA!$B$6) -> 81254.382 | C9: =C8*EXP(RATES!O10)*(1-DATA!$B$6) -> 20313.596 | D9: =B9+C9 -> 101567.98 | E9: =E8*(1-'LIFE TABLE MALE'!D69/1000) -> 0.93939989 | F9: =F8*(1-0.15) -> 0.16971728 | G9: =D9-20 -> 101547.98 | H9: =MAX(D9,DATA!$B$3) -> 101567.98 | I9: =G9*DATA!$B$7*F8*E9 -> 2857.0654 | J9: =H9*'LIFE TABLE MALE'!D69/1000*F8*E8 -> 226.08495 | K9: =0 -> 0 | L9: =DATA!$B$8*((1+DATA!$B$9)^A8)*F9*E9 -> 8.9773387 | M9: =B8*EXP(RATES!O10)*(DATA!$B$12) -> 1163.1507 | N9: =C8*EXP(RATES!O10)*(DATA!$B$12) -> 290.78767 | O9: =M9+N9 -> 1453.9383 | P9: =O9*E9*F9 -> 231.80487 | Q9: =RATES!G10 -> 0.84258782 | R9: =P9+L9+K9+J9+I9 -> 3323.9326 | S9: =R9*Q9 -> 2800.7051 | T9: =C8*EXP(RATES!O10)*(DATA!$B$6-DATA!$B$12) -> 166.16438 | U9: =B8*EXP(RATES!O10)*(DATA!$B$6-DATA!$B$12) -> 664.65752 | V9: =T9+U9 -> 830.8219 | W9: =V9*E9*F9 -> 132.45993 | X9: =W9*BASE!Q9 -> 111.60912
A10: 8 | B10: =B9*EXP(RATES!O11)*(1-DATA!$B$6) -> 81365.273 | C10: =C9*EXP(RATES!O11)*(1-DATA!$B$6) -> 20341.318 | D10: =B10+C10 -> 101706.59 | E10: =E9*(1-'LIFE TABLE MALE'!D70/1000) -> 0.92737751 | F10: =F9*(1-0.15) -> 0.14425969 | G10: =D10-20 -> 101686.59 | H10: =MAX(D10,DATA!$B$3) -> 101706.59 | I10: =G10*DATA!$B$7*F9*E10 -> 2400.6983 | J10: =H10*'LIFE TABLE MALE'!D70/1000*F9*E9 -> 207.52276 | K10: =0 -> 0 | L10: =DATA!$B$8*((1+DATA!$B$9)^A9)*F10*E10 -> 7.6837417 | M10: =B9*EXP(RATES!O11)*(DATA!$B$12) -> 1164.7381 | N10: =C9*EXP(RATES!O11)*(DATA!$B$12) -> 291.18452 | O10: =M10+N10 -> 1455.9226 | P10: =O10*E10*F10 -> 194.77797 | Q10: =RATES!G11 -> 0.82292781 | R10: =P10+L10+K10+J10+I10 -> 2810.6827 | S10: =R10*Q10 -> 2312.989 | T10: =C9*EXP(RATES!O11)*(DATA!$B$6-DATA!$B$12) -> 166.39115 | U10: =B9*EXP(RATES!O11)*(DATA!$B$6-DATA!$B$12) -> 665.56461 | V10: =T10+U10 -> 831.95576 | W10: =V10*E10*F10 -> 111.3017 | X10: =W10*BASE!Q10 -> 91.593261
A11: 9 | B11: =B10*EXP(RATES!O12)*(1-DATA!$B$6) -> 81523.24 | C11: =C10*EXP(RATES!O12)*(1-DATA!$B$6) -> 20380.81 | D11: =B11+C11 -> 101904.05 | E11: =E10*(1-'LIFE TABLE MALE'!D71/1000) -> 0.91441742 | F11: =F10*(1-0.15) -> 0.12262074 | G11: =D11-20 -> 101884.05 | H11: =MAX(D11,DATA!$B$3) -> 101904.05 | I11: =G11*DATA!$B$7*F10*E11 -> 2015.9834 | J11: =H11*'LIFE TABLE MALE'!D71/1000*F10*E10 -> 190.52172 | K11: =0 -> 0 | L11: =DATA!$B$8*((1+DATA!$B$9)^A10)*F11*E11 -> 6.5687054 | M11: =B10*EXP(RATES!O12)*(DATA!$B$12) -> 1166.9993 | N11: =C10*EXP(RATES!O12)*(DATA!$B$12) -> 291.74984 | O11: =M11+N11 -> 1458.7492 | P11: =O11*E11*F11 -> 163.56449 | Q11: =RATES!G12 -> 0.8032639 | R11: =P11+L11+K11+J11+I11 -> 2376.6383 | S11: =R11*Q11 -> 1909.0677 | T11: =C10*EXP(RATES!O12)*(DATA!$B$6-DATA!$B$12) -> 166.71419 | U11: =B10*EXP(RATES!O12)*(DATA!$B$6-DATA!$B$12) -> 666.85677 | V11: =T11+U11 -> 833.57096 | W11: =V11*E11*F11 -> 93.465426 | X11: =W11*BASE!Q11 -> 75.077402
A12: 10 | B12: =B11*EXP(RATES!O13)*(1-DATA!$B$6) -> 81742.12 | C12: =C11*EXP(RATES!O13)*(1-DATA!$B$6) -> 20435.53 | D12: =B12+C12 -> 102177.65 | E12: =E11*(1-'LIFE TABLE MALE'!D72/1000) -> 0.9000976 | F12: =F11*(1-0.15) -> 0.10422763 | G12: =D12-20 -> 102157.65 | H12: =MAX(D12,DATA!$B$3) -> 102177.65 | I12: =G12*DATA!$B$7*F11*E12 -> 1691.2806 | J12: =H12*'LIFE TABLE MALE'!D72/1000*F11*E11 -> 179.41447 | K12: =0 -> 0 | L12: =DATA!$B$8*((1+DATA!$B$9)^A11)*F12*E12 -> 5.6058826 | M12: =B11*EXP(RATES!O13)*(DATA!$B$12) -> 1170.1326 | N12: =C11*EXP(RATES!O13)*(DATA!$B$12) -> 292.53315 | O12: =M12+N12 -> 1462.6657 | P12: =O12*E12*F12 -> 137.22004 | Q12: =RATES!G13 -> 0.78348852 | R12: =P12+L12+K12+J12+I12 -> 2013.521 | S12: =R12*Q12 -> 1577.5706 | T12: =C11*EXP(RATES!O13)*(DATA!$B$6-DATA!$B$12) -> 167.1618 | U12: =B11*EXP(RATES!O13)*(DATA!$B$6-DATA!$B$12) -> 668.6472 | V12: =T12+U12 -> 835.809 | W12: =V12*E12*F12 -> 78.411451 | X12: =W12*BASE!Q12 -> 61.434472
A13: 11 | B13: =B12*EXP(RATES!O14)*(1-DATA!$B$6) -> 82068.024 | C13: =C12*EXP(RATES!O14)*(1-DATA!$B$6) -> 20517.006 | D13: =B13+C13 -> 102585.03 | E13: =E12*(1-'LIFE TABLE MALE'!D73/1000) -> 0.88436967 | F13: =F12*(1-0.15) -> 0.088593482 | G13: =D13-20 -> 102565.03 | H13: =MAX(D13,DATA!$B$3) -> 102585.03 | I13: =G13*DATA!$B$7*F12*E13 -> 1418.1013 | J13: =H13*'LIFE TABLE MALE'!D73/1000*F12*E12 -> 168.16605 | K13: =0 -> 0 | L13: =DATA!$B$8*((1+DATA!$B$9)^A12)*F13*E13 -> 4.7753734 | M13: =B12*EXP(RATES!O14)*(DATA!$B$12) -> 1174.7979 | N13: =C12*EXP(RATES!O14)*(DATA!$B$12) -> 293.69947 | O13: =M13+N13 -> 1468.4974 | P13: =O13*E13*F13 -> 115.05587 | Q13: =RATES!G14 -> 0.76320888 | R13: =P13+L13+K13+J13+I13 -> 1706.0986 | S13: =R13*Q13 -> 1302.1096 | T13: =C12*EXP(RATES!O14)*(DATA!$B$6-DATA!$B$12) -> 167.82827 | U13: =B12*EXP(RATES!O14)*(DATA!$B$6-DATA!$B$12) -> 671.31308 | V13: =T13+U13 -> 839.14135 | W13: =V13*E13*F13 -> 65.746211 | X13: =W13*BASE!Q13 -> 50.178092
A14: 12 | B14: =B13*EXP(RATES!O15)*(1-DATA!$B$6) -> 82258.657 | C14: =C13*EXP(RATES!O15)*(1-DATA!$B$6) -> 20564.664 | D14: =B14+C14 -> 102823.32 | E14: =E13*(1-'LIFE TABLE MALE'!D74/1000) -> 0.86691444 | F14: =F13*(1-0.15) -> 0.07530446 | G14: =D14-20 -> 102803.32 | H14: =MAX(D14,DATA!$B$3) -> 102823.32 | I14: =G14*DATA!$B$7*F13*E14 -> 1184.34 | J14: =H14*'LIFE TABLE MALE'!D74/1000*F13*E13 -> 159.00799 | K14: =0 -> 0 | L14: =DATA!$B$8*((1+DATA!$B$9)^A13)*F14*E14 -> 4.0585306 | M14: =B13*EXP(RATES!O15)*(DATA!$B$12) -> 1177.5268 | N14: =C13*EXP(RATES!O15)*(DATA!$B$12) -> 294.3817 | O14: =M14+N14 -> 1471.9085 | P14: =O14*E14*F14 -> 96.0899 | Q14: =RATES!G15 -> 0.74468847 | R14: =P14+L14+K14+J14+I14 -> 1443.4964 | S14: =R14*Q14 -> 1074.9552 | T14: =C13*EXP(RATES!O15)*(DATA!$B$6-DATA!$B$12) -> 168.21811 | U14: =B13*EXP(RATES!O15)*(DATA!$B$6-DATA!$B$12) -> 672.87245 | V14: =T14+U14 -> 841.09056 | W14: =V14*E14*F14 -> 54.908514 | X14: =W14*BASE!Q14 -> 40.889738
A15: 13 | B15: =B14*EXP(RATES!O16)*(1-DATA!$B$6) -> 82502.039 | C15: =C14*EXP(RATES!O16)*(1-DATA!$B$6) -> 20625.51 | D15: =B15+C15 -> 103127.55 | E15: =E14*(1-'LIFE TABLE MALE'!D75/1000) -> 0.84808352 | F15: =F14*(1-0.15) -> 0.064008791 | G15: =D15-20 -> 103107.55 | H15: =MAX(D15,DATA!$B$3) -> 103127.55 | I15: =G15*DATA!$B$7*F14*E15 -> 987.73637 | J15: =H15*'LIFE TABLE MALE'!D75/1000*F14*E14 -> 146.24022 | K15: =0 -> 0 | L15: =DATA!$B$8*((1+DATA!$B$9)^A14)*F15*E15 -> 3.4423127 | M15: =B14*EXP(RATES!O16)*(DATA!$B$12) -> 1181.0108 | N15: =C14*EXP(RATES!O16)*(DATA!$B$12) -> 295.2527 | O15: =M15+N15 -> 1476.2635 | P15: =O15*E15*F15 -> 80.138669 | Q15: =RATES!G16 -> 0.72615681 | R15: =P15+L15+K15+J15+I15 -> 1217.5576 | S15: =R15*Q15 -> 884.13773 | T15: =C14*EXP(RATES!O16)*(DATA!$B$6-DATA!$B$12) -> 168.71583 | U15: =B14*EXP(RATES!O16)*(DATA!$B$6-DATA!$B$12) -> 674.8633 | V15: =T15+U15 -> 843.57913 | W15: =V15*E15*F15 -> 45.793525 | X15: =W15*BASE!Q15 -> 33.25328
... A51: 49 | B51: =B50*EXP(RATES!O52)*(1-DATA!$B$6) -> 102111.48 | C51: =C50*EXP(RATES!O52)*(1-DATA!$B$6) -> 25527.869 | D51: =B51+C51 -> 127639.35 | E51: =E50*(1-'LIFE TABLE MALE'!D111/1000) -> 2.6221013e-06 | F51: =F50*(1-0.15) -> 0.00018421329 | G51: =D51-20 -> 127619.35 | H51: =MAX(D51,DATA!$B$3) -> 127639.35 | I51: =G51*DATA!$B$7*F50*E51 -> 1.0878256e-05 | J51: =H51*'LIFE TABLE MALE'!D111/1000*F50*E50 -> 0.00017860204 | K51: =0 -> 0 | L51: =DATA!$B$8*((1+DATA!$B$9)^A50)*F51*E51 -> 6.24811e-08 | M51: =B50*EXP(RATES!O52)*(DATA!$B$12) -> 1461.7185 | N51: =C50*EXP(RATES!O52)*(DATA!$B$12) -> 365.42962 | O51: =M51+N51 -> 1827.1481 | P51: =O51*E51*F51 -> 8.8255985e-07 | Q51: =RATES!G52 -> 0.26340215 | R51: =P51+L51+K51+J51+I51 -> 0.00019042534 | S51: =R51*Q51 -> 5.0158444e-05 | T51: =C50*EXP(RATES!O52)*(DATA!$B$6-DATA!$B$12) -> 208.81693 | U51: =B50*EXP(RATES!O52)*(DATA!$B$6-DATA!$B$12) -> 835.2677 | V51: =T51+U51 -> 1044.0846 | W51: =V51*E51*F51 -> 5.0431991e-07 | X51: =W51*BASE!Q51 -> 1.3283895e-07
A52: 50 | B52: =B51*EXP(RATES!O53)*(1-DATA!$B$6) -> 103172 | C52: =C51*EXP(RATES!O53)*(1-DATA!$B$6) -> 25793 | D52: =B52+C52 -> 128965 | E52: =E51*(1-'LIFE TABLE MALE'!D112/1000) -> 6.7948871e-07 | F52: =F51*(1-0.15) -> 0.00015658129 | G52: =D52-20 -> 128945 | H52: =MAX(D52,DATA!$B$3) -> 128965 | I52: =G52*DATA!$B$7*F51*E52 -> 2.4210232e-06 | J52: =H52*'LIFE TABLE MALE'!D112/1000*F51*E51 -> 4.6150776e-05 | K52: =E52*D52*F52 -> 1.372126e-05 | L52: =DATA!$B$8*((1+DATA!$B$9)^A51)*F52*E52 -> 1.4037848e-08 | M52: =B51*EXP(RATES!O53)*(DATA!$B$12) -> 1476.8998 | N52: =C51*EXP(RATES!O53)*(DATA!$B$12) -> 369.22495 | O52: =M52+N52 -> 1846.1247 | P52: =O52*E52*F52 -> 1.9641885e-07 | Q52: =RATES!G53 -> 0.25495931 | R52: =P52+L52+K52+J52+I52 -> 6.2503515e-05 | S52: =R52*Q52 -> 1.5935853e-05 | T52: =C51*EXP(RATES!O53)*(DATA!$B$6-DATA!$B$12) -> 210.98568 | U52: =B51*EXP(RATES!O53)*(DATA!$B$6-DATA!$B$12) -> 843.94273 | V52: =T52+U52 -> 1054.9284 | W52: =V52*E52*F52 -> 1.1223934e-07 | X52: =W52*BASE!Q52 -> 2.8616465e-08
P56: LIABILITIES | Q56: =SUM(S3:S52) -> 96040.528 | T56: BEL COMPONENTS
P57: BOF | Q57: =DATA!B2-Q56 -> 3959.4721 | T57: DEATH | U57: =SUMPRODUCT(J3:J52,Q3:Q52) -> 3701.0644
T58: LAPSE | U58: =SUMPRODUCT(I3:I52,Q3:Q52) -> 88719.404
P59: DURATION | Q59: =SUMPRODUCT(S3:S52,A3:A52)/SUM(S3:S52) -> 3.4028789 | T59: EXPENSES | U59: =SUMPRODUCT(L3:L52,Q3:Q52) -> 131.09287
T60: COMMISSIONS | U60: =SUMPRODUCT(P3:P52,Q3:Q52) -> 3488.9662

Sheet BSCR
B2: Market Risk | N2: Life Risk
B3: Interest | C3: equity | D3: property | N3: Mortality | O3: Lapse | P3: Cat | Q3: expense
B4: =MAX(V7,V8,0) -> 359.457 | C4: =MAX(0,V5) -> 1790.2664 | D4: =MAX(0,V6) -> 286.90166 | N4: =MAX(0,V10) -> 29.30665 | O4: =MAX(0,V12,V13,V14) -> 1546.912 | P4: =MAX(0,V11) -> 4.991863 | Q4: =MAX(0,V9) -> 38.106405 | U4: SCR
U5: Equity | V5: =MAX(BASE!Q57-'EQ STRESS 1'!Q57,0) -> 1790.2664
B6: Corr Market - IR UP | H6: Corr Market - IR DOWN | N6: Corr Life | U6: Property | V6: =MAX(BASE!Q57-'PROPERTY STRESS'!Q57,0) -> 286.90166
C7: Interest | D7: Equity | E7: Property | I7: Interest | J7: Equity | K7: Property | O7: Mortality | P7: Lapse | Q7: CAT | R7: EXPENSE | U7: IR up | V7: =MAX(BASE!Q57-'IR UP '!Q57,0) -> 0
B8: Interest | C8: 1 | D8: 0 | E8: 0 | H8: Interest | I8: 1 | J8: 0.5 | K8: 0.5 | N8: Mortality | O8: 1 | P8: 0 | Q8: 0.25 | R8: 0.25 | U8: IR down | V8: =MAX(BASE!Q57-'IR DOWN '!Q57,0) -> 359.457
B9: Equity | C9: 0 | D9: 1 | E9: 0.75 | H9: Equity | I9: 0.5 | J9: 1 | K9: 0.75 | N9: Lapse | O9: 0 | P9: 1 | Q9: 0.25 | R9: 0.5 | U9: Expense | V9: =MAX(BASE!Q57-'EXPENSE STRESS'!Q57,0) -> 38.106405
B10: Property | C10: 0 | D10: 0.75 | E10: 1 | H10: Property | I10: 0.5 | J10: 0.75 | K10: 1 | N10: CAT | O10: 0.25 | P10: 0.25 | Q10: 1 | R10: 0.25 | U10: Mortality | V10: =MAX(BASE!Q57-MORTALITY!Q57,0) -> 29.30665
N11: EXPENSE | O11: 0.25 | P11: 0.5 | Q11: 0.25 | R11: 1 | U11: Cat | V11: =MAX(BASE!Q57-'LIFE CAT'!Q57,0) -> 4.991863
U12: Lapse up | V12: =MAX(BASE!Q57-'LAPSE STRESS UP '!Q57,0) -> 1130.4727
U13: Lapse down | V13: =MAX(BASE!Q57-'LAPSE STRESS DOWN'!Q57,0) -> 0
U14: Lapse mass | V14: =MAX(BASE!Q57-'LAPSE MASS'!Q57,0) -> 1546.912
B16: Intermidiate results | G16: Corr BSCR | K16: BSCR | N16: Corr Market - EQUITY
B17: IR UP | C17: {=MMULT(MMULT(B4:D4,C8:E10),TRANSPOSE(B4:D4))} -> 4187021.3 | E17: SCR_market | H17: Market | I17: Life | K17: =SQRT((E18*H18+E20*H19)*E18+(E18*I18+E20*I19)*E20) -> 3022.2438 | O17: Equity 1 | P17: Equity 2
B18: IR DOWN | C18: {=MMULT(MMULT(B4:D4,I8:K10),TRANSPOSE(B4:D4))} -> 4933673.9 | E18: =IF(V7<V8,SQRT(C18),SQRT(C17)) -> 2221.1875 | G18: Market | H18: 1 | I18: 0.25 | N18: Equity 1 | O18: 1 | P18: 0.75
E19: SCR_life | G19: Life | H19: 0.25 | I19: 1 | N19: Equity 2 | O19: 0.75 | P19: 1
B20: Life | C20: {=MMULT(MMULT(N4:Q4,O8:R11),TRANSPOSE(N4:Q4))} -> 2458807.6 | E20: =SQRT(C20) -> 1568.0585
